Workbook

Sheet Read me
A1: F1 canon register v2 — full coverage at zero cost
A2: Built 2026-09-28. Companion to the doc 'F1 Scope v2 — everything, at zero cost'.
A4: What this is
A5: Every grouping, technique, material, object type, living practice and 'first known' claim F1's Atlas should hold, so nothing a learner might look for is missing. 4,228 nodes in 24 kinds (round 2 added communities, people, places, events, periods and the blind-map additions), plus 198 zero-cost source routes and 130 primary texts.
A6: Tiers
A7: R1 = taught in a unit, full grouping page with an authored walk. R2 = card and member grid (needs 5+ verified members and a source). R3 = card and link out. Every node gets at least R3; promotion is by evidence, not fame.
A8: How it was checked
A9: Drafted from knowledge in six parallel passes, then fact-checked independently: every R1 row, every low/medium-confidence R1/R2 row, every UNESCO claim, and random samples (about 620 rows). 66 rows corrected; logs in REVIEW_LOG_people.md and REVIEW_LOG_things.md. Random-sample error rate 1 in 120; UNESCO statuses written from memory were wrong 19 times in 124, so UNESCO status must be harvested from the ICH dataset, never typed. Round 2 (29 September): about 680 more rows checked (people, places, events, periods, communities, blind-map additions) and 106 corrected; priority rows (R1/R2, living people, UNESCO claims, endonyms) erred at 8–14%, random samples at 0–8%. Logs: REVIEW_LOG_round2_*.md.
A10: Not yet done
A11: No Wikidata/Getty/PeriodO identifiers are included on purpose (none were guessed); the harvest matches them. Rows at confidence 'low' or 'medium' outside R1 are unverified drafts.
A12: Sheets
A13: Summary — counts by kind and tier (formulas). Canon — all nodes, one row each, filterable. Coverage grid — nodes per sub-region and period band (formulas; recalculates as rows change). Functions x worlds — object types per function per world. Sources — zero-cost routes with licence and commercial-safe flag. Primary texts — texts on making, with public-domain status.
... A15: Sub-regions: 46 codes (AF-, AM-, AS-, WA-, EU-, OC-, GL). Period bands B01–B11. Worlds: F1.6 Africa · F1.7 Americas · F1.8 East Asia · F1.9 South and Southeast Asia · F1.9a West Asia before Islam · F1.10 Islamic world · F1.11 Europe and the Mediterranean · F1.12 Australia and the Pacific · F1.12a Steppe and Central Asia · F1.13 Networks · THEME.

Sheet Summary
A1: Kind | B1: R1 | C1: R2 | D1: R3 | E1: Total
A2: person | B2: =COUNTIFS(Canon!$D$2:$D$4229,$A2,Canon!$S$2:$S$4229,"R1") -> 5 | C2: =COUNTIFS(Canon!$D$2:$D$4229,$A2,Canon!$S$2:$S$4229,"R2") -> 25 | D2: =COUNTIFS(Canon!$D$2:$D$4229,$A2,Canon!$S$2:$S$4229,"R3") -> 450 | E2: =SUM(B2:D2) -> 480
A3: place | B3: =COUNTIFS(Canon!$D$2:$D$4229,$A3,Canon!$S$2:$S$4229,"R1") -> 22 | C3: =COUNTIFS(Canon!$D$2:$D$4229,$A3,Canon!$S$2:$S$4229,"R2") -> 144 | D3: =COUNTIFS(Canon!$D$2:$D$4229,$A3,Canon!$S$2:$S$4229,"R3") -> 253 | E3: =SUM(B3:D3) -> 419
A4: object-type | B4: =COUNTIFS(Canon!$D$2:$D$4229,$A4,Canon!$S$2:$S$4229,"R1") -> 31 | C4: =COUNTIFS(Canon!$D$2:$D$4229,$A4,Canon!$S$2:$S$4229,"R2") -> 155 | D4: =COUNTIFS(Canon!$D$2:$D$4229,$A4,Canon!$S$2:$S$4229,"R3") -> 172 | E4: =SUM(B4:D4) -> 358
A5: event | B5: =COUNTIFS(Canon!$D$2:$D$4229,$A5,Canon!$S$2:$S$4229,"R1") -> 14 | C5: =COUNTIFS(Canon!$D$2:$D$4229,$A5,Canon!$S$2:$S$4229,"R2") -> 107 | D5: =COUNTIFS(Canon!$D$2:$D$4229,$A5,Canon!$S$2:$S$4229,"R3") -> 207 | E5: =SUM(B5:D5) -> 328
A6: community | B6: =COUNTIFS(Canon!$D$2:$D$4229,$A6,Canon!$S$2:$S$4229,"R1") -> 19 | C6: =COUNTIFS(Canon!$D$2:$D$4229,$A6,Canon!$S$2:$S$4229,"R2") -> 96 | D6: =COUNTIFS(Canon!$D$2:$D$4229,$A6,Canon!$S$2:$S$4229,"R3") -> 185 | E6: =SUM(B6:D6) -> 300
A7: polity | B7: =COUNTIFS(Canon!$D$2:$D$4229,$A7,Canon!$S$2:$S$4229,"R1") -> 50 | C7: =COUNTIFS(Canon!$D$2:$D$4229,$A7,Canon!$S$2:$S$4229,"R2") -> 145 | D7: =COUNTIFS(Canon!$D$2:$D$4229,$A7,Canon!$S$2:$S$4229,"R3") -> 45 | E7: =SUM(B7:D7) -> 240
A8: technique | B8: =COUNTIFS(Canon!$D$2:$D$4229,$A8,Canon!$S$2:$S$4229,"R1") -> 13 | C8: =COUNTIFS(Canon!$D$2:$D$4229,$A8,Canon!$S$2:$S$4229,"R2") -> 51 | D8: =COUNTIFS(Canon!$D$2:$D$4229,$A8,Canon!$S$2:$S$4229,"R3") -> 173 | E8: =SUM(B8:D8) -> 237
A9: archaeological-culture | B9: =COUNTIFS(Canon!$D$2:$D$4229,$A9,Canon!$S$2:$S$4229,"R1") -> 4 | C9: =COUNTIFS(Canon!$D$2:$D$4229,$A9,Canon!$S$2:$S$4229,"R2") -> 54 | D9: =COUNTIFS(Canon!$D$2:$D$4229,$A9,Canon!$S$2:$S$4229,"R3") -> 172 | E9: =SUM(B9:D9) -> 230
A10: period | B10: =COUNTIFS(Canon!$D$2:$D$4229,$A10,Canon!$S$2:$S$4229,"R1") -> 5 | C10: =COUNTIFS(Canon!$D$2:$D$4229,$A10,Canon!$S$2:$S$4229,"R2") -> 50 | D10: =COUNTIFS(Canon!$D$2:$D$4229,$A10,Canon!$S$2:$S$4229,"R3") -> 165 | E10: =SUM(B10:D10) -> 220
A11: living-practice | B11: =COUNTIFS(Canon!$D$2:$D$4229,$A11,Canon!$S$2:$S$4229,"R1") -> 17 | C11: =COUNTIFS(Canon!$D$2:$D$4229,$A11,Canon!$S$2:$S$4229,"R2") -> 94 | D11: =COUNTIFS(Canon!$D$2:$D$4229,$A11,Canon!$S$2:$S$4229,"R3") -> 103 | E11: =SUM(B11:D11) -> 214
A12: style | B12: =COUNTIFS(Canon!$D$2:$D$4229,$A12,Canon!$S$2:$S$4229,"R1") -> 9 | C12: =COUNTIFS(Canon!$D$2:$D$4229,$A12,Canon!$S$2:$S$4229,"R2") -> 66 | D12: =COUNTIFS(Canon!$D$2:$D$4229,$A12,Canon!$S$2:$S$4229,"R3") -> 120 | E12: =SUM(B12:D12) -> 195
A13: first-known | B13: =COUNTIFS(Canon!$D$2:$D$4229,$A13,Canon!$S$2:$S$4229,"R1") -> 22 | C13: =COUNTIFS(Canon!$D$2:$D$4229,$A13,Canon!$S$2:$S$4229,"R2") -> 70 | D13: =COUNTIFS(Canon!$D$2:$D$4229,$A13,Canon!$S$2:$S$4229,"R3") -> 82 | E13: =SUM(B13:D13) -> 174
... A25: interaction-sphere | B25: =COUNTIFS(Canon!$D$2:$D$4229,$A25,Canon!$S$2:$S$4229,"R1") -> 0 | C25: =COUNTIFS(Canon!$D$2:$D$4229,$A25,Canon!$S$2:$S$4229,"R2") -> 3 | D25: =COUNTIFS(Canon!$D$2:$D$4229,$A25,Canon!$S$2:$S$4229,"R3") -> 0 | E25: =SUM(B25:D25) -> 3
A26: All kinds | B26: =SUM(B2:B25) -> 269 | C26: =SUM(C2:C25) -> 1268 | D26: =SUM(D2:D25) -> 2691 | E26: =SUM(E2:E25) -> 4228

Sheet Coverage grid
A1: Nodes per sub-region and period band (a node counts in every band its date range touches). 0 = gap, or no people there yet (see note column). Band edges are in rows 3–4 and drive the formulas.
B3: band start | C3: -9999999 | D3: -8000 | E3: -4000 | F3: -2000 | G3: -1000 | H3: 1 | I3: 500 | J3: 1000 | K3: 1400 | L3: 1700 | M3: 1900
B4: band end | C4: -8000 | D4: -4000 | E4: -2000 | F4: -1000 | G4: 1 | H4: 500 | I4: 1000 | J4: 1400 | K4: 1700 | L4: 1900 | M4: 2027
A5: Code | B5: Sub-region | C5: B01 before 8000 BCE | D5: B02 8000–4000 BCE | E5: B03 4000–2000 BCE | F5: B04 2000–1000 BCE | G5: B05 1000 BCE–1 CE | H5: B06 1–500 | I5: B07 500–1000 | J5: B08 1000–1400 | K5: B09 1400–1700 | L5: B10 1700–1900 | M5: B11 1900–now | N5: Note
A6: AF-EGY | B6: Egypt | C6: =COUNTIFS(Canon!$G$2:$G$4229,"*"&$A6&"*",Canon!$H$2:$H$4229,"<"&C$4,Canon!$I$2:$I$4229,">="&C$3)+COUNTIFS(Canon!$G$2:$G$4229,"*"&$A6&"*",Canon!$H$2:$H$4229,"<"&C$4,Canon!$I$2:$I$4229,"") -> 4 | D6: =COUNTIFS(Canon!$G$2:$G$4229,"*"&$A6&"*",Canon!$H$2:$H$4229,"<"&D$4,Canon!$I$2:$I$4229,">="&D$3)+COUNTIFS(Canon!$G$2:$G$4229,"*"&$A6&"*",Canon!$H$2:$H$4229,"<"&D$4,Canon!$I$2:$I$4229,"") -> 10 | E6: =COUNTIFS(Canon!$G$2:$G$4229,"*"&$A6&"*",Canon!$H$2:$H$4229,"<"&E$4,Canon!$I$2:$I$4229,">="&E$3)+COUNTIFS(Canon!$G$2:$G$4229,"*"&$A6&"*",Canon!$H$2:$H$4229,"<"&E$4,Canon!$I$2:$I$4229,"") -> 67 | F6: =COUNTIFS(Canon!$G$2:$G$4229,"*"&$A6&"*",Canon!$H$2:$H$4229,"<"&F$4,Canon!$I$2:$I$4229,">="&F$3)+COUNTIFS(Canon!$G$2:$G$4229,"*"&$A6&"*",Canon!$H$2:$H$4229,"<"&F$4,Canon!$I$2:$I$4229,"") -> 86 | G6: =COUNTIFS(Canon!$G$2:$G$4229,"*"&$A6&"*",Canon!$H$2:$H$4229,"<"&G$4,Canon!$I$2:$I$4229,">="&G$3)+COUNTIFS(Canon!$G$2:$G$4229,"*"&$A6&"*",Canon!$H$2:$H$4229,"<"&G$4,Canon!$I$2:$I$4229,"") -> 92 | H6: =COUNTIFS(Canon!$G$2:$G$4229,"*"&$A6&"*",Canon!$H$2:$H$4229,"<"&H$4,Canon!$I$2:$I$4229,">="&H$3)+COUNTIFS(Canon!$G$2:$G$4229,"*"&$A6&"*",Canon!$H$2:$H$4229,"<"&H$4,Canon!$I$2:$I$4229,"") -> 91 | I6: =COUNTIFS(Canon!$G$2:$G$4229,"*"&$A6&"*",Canon!$H$2:$H$4229,"<"&I$4,Canon!$I$2:$I$4229,">="&I$3)+COUNTIFS(Canon!$G$2:$G$4229,"*"&$A6&"*",Canon!$H$2:$H$4229,"<"&I$4,Canon!$I$2:$I$4229,"") -> 97 | J6: =COUNTIFS(Canon!$G$2:$G$4229,"*"&$A6&"*",Canon!$H$2:$H$4229,"<"&J$4,Canon!$I$2:$I$4229,">="&J$3)+COUNTIFS(Canon!$G$2:$G$4229,"*"&$A6&"*",Canon!$H$2:$H$4229,"<"&J$4,Canon!$I$2:$I$4229,"") -> 101 | ... M6: =COUNTIFS(Canon!$G$2:$G$4229,"*"&$A6&"*",Canon!$H$2:$H$4229,"<"&M$4,Canon!$I$2:$I$4229,">="&M$3)+COUNTIFS(Canon!$G$2:$G$4229,"*"&$A6&"*",Canon!$H$2:$H$4229,"<"&M$4,Canon!$I$2:$I$4229,"") -> 94
A7: AF-NUB | B7: Nubia and Sudan | C7: =COUNTIFS(Canon!$G$2:$G$4229,"*"&$A7&"*",Canon!$H$2:$H$4229,"<"&C$4,Canon!$I$2:$I$4229,">="&C$3)+COUNTIFS(Canon!$G$2:$G$4229,"*"&$A7&"*",Canon!$H$2:$H$4229,"<"&C$4,Canon!$I$2:$I$4229,"") -> 1 | D7: =COUNTIFS(Canon!$G$2:$G$4229,"*"&$A7&"*",Canon!$H$2:$H$4229,"<"&D$4,Canon!$I$2:$I$4229,">="&D$3)+COUNTIFS(Canon!$G$2:$G$4229,"*"&$A7&"*",Canon!$H$2:$H$4229,"<"&D$4,Canon!$I$2:$I$4229,"") -> 3 | E7: =COUNTIFS(Canon!$G$2:$G$4229,"*"&$A7&"*",Canon!$H$2:$H$4229,"<"&E$4,Canon!$I$2:$I$4229,">="&E$3)+COUNTIFS(Canon!$G$2:$G$4229,"*"&$A7&"*",Canon!$H$2:$H$4229,"<"&E$4,Canon!$I$2:$I$4229,"") -> 16 | F7: =COUNTIFS(Canon!$G$2:$G$4229,"*"&$A7&"*",Canon!$H$2:$H$4229,"<"&F$4,Canon!$I$2:$I$4229,">="&F$3)+COUNTIFS(Canon!$G$2:$G$4229,"*"&$A7&"*",Canon!$H$2:$H$4229,"<"&F$4,Canon!$I$2:$I$4229,"") -> 21 | G7: =COUNTIFS(Canon!$G$2:$G$4229,"*"&$A7&"*",Canon!$H$2:$H$4229,"<"&G$4,Canon!$I$2:$I$4229,">="&G$3)+COUNTIFS(Canon!$G$2:$G$4229,"*"&$A7&"*",Canon!$H$2:$H$4229,"<"&G$4,Canon!$I$2:$I$4229,"") -> 21 | H7: =COUNTIFS(Canon!$G$2:$G$4229,"*"&$A7&"*",Canon!$H$2:$H$4229,"<"&H$4,Canon!$I$2:$I$4229,">="&H$3)+COUNTIFS(Canon!$G$2:$G$4229,"*"&$A7&"*",Canon!$H$2:$H$4229,"<"&H$4,Canon!$I$2:$I$4229,"") -> 21 | I7: =COUNTIFS(Canon!$G$2:$G$4229,"*"&$A7&"*",Canon!$H$2:$H$4229,"<"&I$4,Canon!$I$2:$I$4229,">="&I$3)+COUNTIFS(Canon!$G$2:$G$4229,"*"&$A7&"*",Canon!$H$2:$H$4229,"<"&I$4,Canon!$I$2:$I$4229,"") -> 19 | J7: =COUNTIFS(Canon!$G$2:$G$4229,"*"&$A7&"*",Canon!$H$2:$H$4229,"<"&J$4,Canon!$I$2:$I$4229,">="&J$3)+COUNTIFS(Canon!$G$2:$G$4229,"*"&$A7&"*",Canon!$H$2:$H$4229,"<"&J$4,Canon!$I$2:$I$4229,"") -> 20 | ... M7: =COUNTIFS(Canon!$G$2:$G$4229,"*"&$A7&"*",Canon!$H$2:$H$4229,"<"&M$4,Canon!$I$2:$I$4229,">="&M$3)+COUNTIFS(Canon!$G$2:$G$4229,"*"&$A7&"*",Canon!$H$2:$H$4229,"<"&M$4,Canon!$I$2:$I$4229,"") -> 23
A8: AF-MAG | B8: Maghrib | C8: =COUNTIFS(Canon!$G$2:$G$4229,"*"&$A8&"*",Canon!$H$2:$H$4229,"<"&C$4,Canon!$I$2:$I$4229,">="&C$3)+COUNTIFS(Canon!$G$2:$G$4229,"*"&$A8&"*",Canon!$H$2:$H$4229,"<"&C$4,Canon!$I$2:$I$4229,"") -> 9 | D8: =COUNTIFS(Canon!$G$2:$G$4229,"*"&$A8&"*",Canon!$H$2:$H$4229,"<"&D$4,Canon!$I$2:$I$4229,">="&D$3)+COUNTIFS(Canon!$G$2:$G$4229,"*"&$A8&"*",Canon!$H$2:$H$4229,"<"&D$4,Canon!$I$2:$I$4229,"") -> 7 | E8: =COUNTIFS(Canon!$G$2:$G$4229,"*"&$A8&"*",Canon!$H$2:$H$4229,"<"&E$4,Canon!$I$2:$I$4229,">="&E$3)+COUNTIFS(Canon!$G$2:$G$4229,"*"&$A8&"*",Canon!$H$2:$H$4229,"<"&E$4,Canon!$I$2:$I$4229,"") -> 7 | F8: =COUNTIFS(Canon!$G$2:$G$4229,"*"&$A8&"*",Canon!$H$2:$H$4229,"<"&F$4,Canon!$I$2:$I$4229,">="&F$3)+COUNTIFS(Canon!$G$2:$G$4229,"*"&$A8&"*",Canon!$H$2:$H$4229,"<"&F$4,Canon!$I$2:$I$4229,"") -> 9 | G8: =COUNTIFS(Canon!$G$2:$G$4229,"*"&$A8&"*",Canon!$H$2:$H$4229,"<"&G$4,Canon!$I$2:$I$4229,">="&G$3)+COUNTIFS(Canon!$G$2:$G$4229,"*"&$A8&"*",Canon!$H$2:$H$4229,"<"&G$4,Canon!$I$2:$I$4229,"") -> 24 | H8: =COUNTIFS(Canon!$G$2:$G$4229,"*"&$A8&"*",Canon!$H$2:$H$4229,"<"&H$4,Canon!$I$2:$I$4229,">="&H$3)+COUNTIFS(Canon!$G$2:$G$4229,"*"&$A8&"*",Canon!$H$2:$H$4229,"<"&H$4,Canon!$I$2:$I$4229,"") -> 21 | I8: =COUNTIFS(Canon!$G$2:$G$4229,"*"&$A8&"*",Canon!$H$2:$H$4229,"<"&I$4,Canon!$I$2:$I$4229,">="&I$3)+COUNTIFS(Canon!$G$2:$G$4229,"*"&$A8&"*",Canon!$H$2:$H$4229,"<"&I$4,Canon!$I$2:$I$4229,"") -> 36 | J8: =COUNTIFS(Canon!$G$2:$G$4229,"*"&$A8&"*",Canon!$H$2:$H$4229,"<"&J$4,Canon!$I$2:$I$4229,">="&J$3)+COUNTIFS(Canon!$G$2:$G$4229,"*"&$A8&"*",Canon!$H$2:$H$4229,"<"&J$4,Canon!$I$2:$I$4229,"") -> 47 | ... M8: =COUNTIFS(Canon!$G$2:$G$4229,"*"&$A8&"*",Canon!$H$2:$H$4229,"<"&M$4,Canon!$I$2:$I$4229,">="&M$3)+COUNTIFS(Canon!$G$2:$G$4229,"*"&$A8&"*",Canon!$H$2:$H$4229,"<"&M$4,Canon!$I$2:$I$4229,"") -> 41
A9: AF-SAH | B9: Sahel and Western Sudan | C9: =COUNTIFS(Canon!$G$2:$G$4229,"*"&$A9&"*",Canon!$H$2:$H$4229,"<"&C$4,Canon!$I$2:$I$4229,">="&C$3)+COUNTIFS(Canon!$G$2:$G$4229,"*"&$A9&"*",Canon!$H$2:$H$4229,"<"&C$4,Canon!$I$2:$I$4229,"") -> 5 | D9: =COUNTIFS(Canon!$G$2:$G$4229,"*"&$A9&"*",Canon!$H$2:$H$4229,"<"&D$4,Canon!$I$2:$I$4229,">="&D$3)+COUNTIFS(Canon!$G$2:$G$4229,"*"&$A9&"*",Canon!$H$2:$H$4229,"<"&D$4,Canon!$I$2:$I$4229,"") -> 11 | E9: =COUNTIFS(Canon!$G$2:$G$4229,"*"&$A9&"*",Canon!$H$2:$H$4229,"<"&E$4,Canon!$I$2:$I$4229,">="&E$3)+COUNTIFS(Canon!$G$2:$G$4229,"*"&$A9&"*",Canon!$H$2:$H$4229,"<"&E$4,Canon!$I$2:$I$4229,"") -> 12 | F9: =COUNTIFS(Canon!$G$2:$G$4229,"*"&$A9&"*",Canon!$H$2:$H$4229,"<"&F$4,Canon!$I$2:$I$4229,">="&F$3)+COUNTIFS(Canon!$G$2:$G$4229,"*"&$A9&"*",Canon!$H$2:$H$4229,"<"&F$4,Canon!$I$2:$I$4229,"") -> 15 | G9: =COUNTIFS(Canon!$G$2:$G$4229,"*"&$A9&"*",Canon!$H$2:$H$4229,"<"&G$4,Canon!$I$2:$I$4229,">="&G$3)+COUNTIFS(Canon!$G$2:$G$4229,"*"&$A9&"*",Canon!$H$2:$H$4229,"<"&G$4,Canon!$I$2:$I$4229,"") -> 24 | H9: =COUNTIFS(Canon!$G$2:$G$4229,"*"&$A9&"*",Canon!$H$2:$H$4229,"<"&H$4,Canon!$I$2:$I$4229,">="&H$3)+COUNTIFS(Canon!$G$2:$G$4229,"*"&$A9&"*",Canon!$H$2:$H$4229,"<"&H$4,Canon!$I$2:$I$4229,"") -> 26 | I9: =COUNTIFS(Canon!$G$2:$G$4229,"*"&$A9&"*",Canon!$H$2:$H$4229,"<"&I$4,Canon!$I$2:$I$4229,">="&I$3)+COUNTIFS(Canon!$G$2:$G$4229,"*"&$A9&"*",Canon!$H$2:$H$4229,"<"&I$4,Canon!$I$2:$I$4229,"") -> 32 | J9: =COUNTIFS(Canon!$G$2:$G$4229,"*"&$A9&"*",Canon!$H$2:$H$4229,"<"&J$4,Canon!$I$2:$I$4229,">="&J$3)+COUNTIFS(Canon!$G$2:$G$4229,"*"&$A9&"*",Canon!$H$2:$H$4229,"<"&J$4,Canon!$I$2:$I$4229,"") -> 55 | ... M9: =COUNTIFS(Canon!$G$2:$G$4229,"*"&$A9&"*",Canon!$H$2:$H$4229,"<"&M$4,Canon!$I$2:$I$4229,">="&M$3)+COUNTIFS(Canon!$G$2:$G$4229,"*"&$A9&"*",Canon!$H$2:$H$4229,"<"&M$4,Canon!$I$2:$I$4229,"") -> 72
A10: AF-GUI | B10: Guinea Coast | C10: =COUNTIFS(Canon!$G$2:$G$4229,"*"&$A10&"*",Canon!$H$2:$H$4229,"<"&C$4,Canon!$I$2:$I$4229,">="&C$3)+COUNTIFS(Canon!$G$2:$G$4229,"*"&$A10&"*",Canon!$H$2:$H$4229,"<"&C$4,Canon!$I$2:$I$4229,"") -> 3 | D10: =COUNTIFS(Canon!$G$2:$G$4229,"*"&$A10&"*",Canon!$H$2:$H$4229,"<"&D$4,Canon!$I$2:$I$4229,">="&D$3)+COUNTIFS(Canon!$G$2:$G$4229,"*"&$A10&"*",Canon!$H$2:$H$4229,"<"&D$4,Canon!$I$2:$I$4229,"") -> 7 | E10: =COUNTIFS(Canon!$G$2:$G$4229,"*"&$A10&"*",Canon!$H$2:$H$4229,"<"&E$4,Canon!$I$2:$I$4229,">="&E$3)+COUNTIFS(Canon!$G$2:$G$4229,"*"&$A10&"*",Canon!$H$2:$H$4229,"<"&E$4,Canon!$I$2:$I$4229,"") -> 12 | F10: =COUNTIFS(Canon!$G$2:$G$4229,"*"&$A10&"*",Canon!$H$2:$H$4229,"<"&F$4,Canon!$I$2:$I$4229,">="&F$3)+COUNTIFS(Canon!$G$2:$G$4229,"*"&$A10&"*",Canon!$H$2:$H$4229,"<"&F$4,Canon!$I$2:$I$4229,"") -> 19 | G10: =COUNTIFS(Canon!$G$2:$G$4229,"*"&$A10&"*",Canon!$H$2:$H$4229,"<"&G$4,Canon!$I$2:$I$4229,">="&G$3)+COUNTIFS(Canon!$G$2:$G$4229,"*"&$A10&"*",Canon!$H$2:$H$4229,"<"&G$4,Canon!$I$2:$I$4229,"") -> 21 | H10: =COUNTIFS(Canon!$G$2:$G$4229,"*"&$A10&"*",Canon!$H$2:$H$4229,"<"&H$4,Canon!$I$2:$I$4229,">="&H$3)+COUNTIFS(Canon!$G$2:$G$4229,"*"&$A10&"*",Canon!$H$2:$H$4229,"<"&H$4,Canon!$I$2:$I$4229,"") -> 22 | I10: =COUNTIFS(Canon!$G$2:$G$4229,"*"&$A10&"*",Canon!$H$2:$H$4229,"<"&I$4,Canon!$I$2:$I$4229,">="&I$3)+COUNTIFS(Canon!$G$2:$G$4229,"*"&$A10&"*",Canon!$H$2:$H$4229,"<"&I$4,Canon!$I$2:$I$4229,"") -> 23 | J10: =COUNTIFS(Canon!$G$2:$G$4229,"*"&$A10&"*",Canon!$H$2:$H$4229,"<"&J$4,Canon!$I$2:$I$4229,">="&J$3)+COUNTIFS(Canon!$G$2:$G$4229,"*"&$A10&"*",Canon!$H$2:$H$4229,"<"&J$4,Canon!$I$2:$I$4229,"") -> 45 | ... M10: =COUNTIFS(Canon!$G$2:$G$4229,"*"&$A10&"*",Canon!$H$2:$H$4229,"<"&M$4,Canon!$I$2:$I$4229,">="&M$3)+COUNTIFS(Canon!$G$2:$G$4229,"*"&$A10&"*",Canon!$H$2:$H$4229,"<"&M$4,Canon!$I$2:$I$4229,"") -> 123
A11: AF-CEN | B11: Central Africa | C11: =COUNTIFS(Canon!$G$2:$G$4229,"*"&$A11&"*",Canon!$H$2:$H$4229,"<"&C$4,Canon!$I$2:$I$4229,">="&C$3)+COUNTIFS(Canon!$G$2:$G$4229,"*"&$A11&"*",Canon!$H$2:$H$4229,"<"&C$4,Canon!$I$2:$I$4229,"") -> 8 | D11: =COUNTIFS(Canon!$G$2:$G$4229,"*"&$A11&"*",Canon!$H$2:$H$4229,"<"&D$4,Canon!$I$2:$I$4229,">="&D$3)+COUNTIFS(Canon!$G$2:$G$4229,"*"&$A11&"*",Canon!$H$2:$H$4229,"<"&D$4,Canon!$I$2:$I$4229,"") -> 7 | E11: =COUNTIFS(Canon!$G$2:$G$4229,"*"&$A11&"*",Canon!$H$2:$H$4229,"<"&E$4,Canon!$I$2:$I$4229,">="&E$3)+COUNTIFS(Canon!$G$2:$G$4229,"*"&$A11&"*",Canon!$H$2:$H$4229,"<"&E$4,Canon!$I$2:$I$4229,"") -> 9 | F11: =COUNTIFS(Canon!$G$2:$G$4229,"*"&$A11&"*",Canon!$H$2:$H$4229,"<"&F$4,Canon!$I$2:$I$4229,">="&F$3)+COUNTIFS(Canon!$G$2:$G$4229,"*"&$A11&"*",Canon!$H$2:$H$4229,"<"&F$4,Canon!$I$2:$I$4229,"") -> 14 | G11: =COUNTIFS(Canon!$G$2:$G$4229,"*"&$A11&"*",Canon!$H$2:$H$4229,"<"&G$4,Canon!$I$2:$I$4229,">="&G$3)+COUNTIFS(Canon!$G$2:$G$4229,"*"&$A11&"*",Canon!$H$2:$H$4229,"<"&G$4,Canon!$I$2:$I$4229,"") -> 18 | H11: =COUNTIFS(Canon!$G$2:$G$4229,"*"&$A11&"*",Canon!$H$2:$H$4229,"<"&H$4,Canon!$I$2:$I$4229,">="&H$3)+COUNTIFS(Canon!$G$2:$G$4229,"*"&$A11&"*",Canon!$H$2:$H$4229,"<"&H$4,Canon!$I$2:$I$4229,"") -> 18 | I11: =COUNTIFS(Canon!$G$2:$G$4229,"*"&$A11&"*",Canon!$H$2:$H$4229,"<"&I$4,Canon!$I$2:$I$4229,">="&I$3)+COUNTIFS(Canon!$G$2:$G$4229,"*"&$A11&"*",Canon!$H$2:$H$4229,"<"&I$4,Canon!$I$2:$I$4229,"") -> 21 | J11: =COUNTIFS(Canon!$G$2:$G$4229,"*"&$A11&"*",Canon!$H$2:$H$4229,"<"&J$4,Canon!$I$2:$I$4229,">="&J$3)+COUNTIFS(Canon!$G$2:$G$4229,"*"&$A11&"*",Canon!$H$2:$H$4229,"<"&J$4,Canon!$I$2:$I$4229,"") -> 29 | ... M11: =COUNTIFS(Canon!$G$2:$G$4229,"*"&$A11&"*",Canon!$H$2:$H$4229,"<"&M$4,Canon!$I$2:$I$4229,">="&M$3)+COUNTIFS(Canon!$G$2:$G$4229,"*"&$A11&"*",Canon!$H$2:$H$4229,"<"&M$4,Canon!$I$2:$I$4229,"") -> 63
A12: AF-HRN | B12: Ethiopia and the Horn | C12: =COUNTIFS(Canon!$G$2:$G$4229,"*"&$A12&"*",Canon!$H$2:$H$4229,"<"&C$4,Canon!$I$2:$I$4229,">="&C$3)+COUNTIFS(Canon!$G$2:$G$4229,"*"&$A12&"*",Canon!$H$2:$H$4229,"<"&C$4,Canon!$I$2:$I$4229,"") -> 11 | D12: =COUNTIFS(Canon!$G$2:$G$4229,"*"&$A12&"*",Canon!$H$2:$H$4229,"<"&D$4,Canon!$I$2:$I$4229,">="&D$3)+COUNTIFS(Canon!$G$2:$G$4229,"*"&$A12&"*",Canon!$H$2:$H$4229,"<"&D$4,Canon!$I$2:$I$4229,"") -> 7 | E12: =COUNTIFS(Canon!$G$2:$G$4229,"*"&$A12&"*",Canon!$H$2:$H$4229,"<"&E$4,Canon!$I$2:$I$4229,">="&E$3)+COUNTIFS(Canon!$G$2:$G$4229,"*"&$A12&"*",Canon!$H$2:$H$4229,"<"&E$4,Canon!$I$2:$I$4229,"") -> 15 | F12: =COUNTIFS(Canon!$G$2:$G$4229,"*"&$A12&"*",Canon!$H$2:$H$4229,"<"&F$4,Canon!$I$2:$I$4229,">="&F$3)+COUNTIFS(Canon!$G$2:$G$4229,"*"&$A12&"*",Canon!$H$2:$H$4229,"<"&F$4,Canon!$I$2:$I$4229,"") -> 16 | G12: =COUNTIFS(Canon!$G$2:$G$4229,"*"&$A12&"*",Canon!$H$2:$H$4229,"<"&G$4,Canon!$I$2:$I$4229,">="&G$3)+COUNTIFS(Canon!$G$2:$G$4229,"*"&$A12&"*",Canon!$H$2:$H$4229,"<"&G$4,Canon!$I$2:$I$4229,"") -> 24 | H12: =COUNTIFS(Canon!$G$2:$G$4229,"*"&$A12&"*",Canon!$H$2:$H$4229,"<"&H$4,Canon!$I$2:$I$4229,">="&H$3)+COUNTIFS(Canon!$G$2:$G$4229,"*"&$A12&"*",Canon!$H$2:$H$4229,"<"&H$4,Canon!$I$2:$I$4229,"") -> 28 | I12: =COUNTIFS(Canon!$G$2:$G$4229,"*"&$A12&"*",Canon!$H$2:$H$4229,"<"&I$4,Canon!$I$2:$I$4229,">="&I$3)+COUNTIFS(Canon!$G$2:$G$4229,"*"&$A12&"*",Canon!$H$2:$H$4229,"<"&I$4,Canon!$I$2:$I$4229,"") -> 30 | J12: =COUNTIFS(Canon!$G$2:$G$4229,"*"&$A12&"*",Canon!$H$2:$H$4229,"<"&J$4,Canon!$I$2:$I$4229,">="&J$3)+COUNTIFS(Canon!$G$2:$G$4229,"*"&$A12&"*",Canon!$H$2:$H$4229,"<"&J$4,Canon!$I$2:$I$4229,"") -> 35 | ... M12: =COUNTIFS(Canon!$G$2:$G$4229,"*"&$A12&"*",Canon!$H$2:$H$4229,"<"&M$4,Canon!$I$2:$I$4229,">="&M$3)+COUNTIFS(Canon!$G$2:$G$4229,"*"&$A12&"*",Canon!$H$2:$H$4229,"<"&M$4,Canon!$I$2:$I$4229,"") -> 45
A13: AF-SWA | B13: Swahili coast and interior | C13: =COUNTIFS(Canon!$G$2:$G$4229,"*"&$A13&"*",Canon!$H$2:$H$4229,"<"&C$4,Canon!$I$2:$I$4229,">="&C$3)+COUNTIFS(Canon!$G$2:$G$4229,"*"&$A13&"*",Canon!$H$2:$H$4229,"<"&C$4,Canon!$I$2:$I$4229,"") -> 20 | D13: =COUNTIFS(Canon!$G$2:$G$4229,"*"&$A13&"*",Canon!$H$2:$H$4229,"<"&D$4,Canon!$I$2:$I$4229,">="&D$3)+COUNTIFS(Canon!$G$2:$G$4229,"*"&$A13&"*",Canon!$H$2:$H$4229,"<"&D$4,Canon!$I$2:$I$4229,"") -> 14 | E13: =COUNTIFS(Canon!$G$2:$G$4229,"*"&$A13&"*",Canon!$H$2:$H$4229,"<"&E$4,Canon!$I$2:$I$4229,">="&E$3)+COUNTIFS(Canon!$G$2:$G$4229,"*"&$A13&"*",Canon!$H$2:$H$4229,"<"&E$4,Canon!$I$2:$I$4229,"") -> 18 | F13: =COUNTIFS(Canon!$G$2:$G$4229,"*"&$A13&"*",Canon!$H$2:$H$4229,"<"&F$4,Canon!$I$2:$I$4229,">="&F$3)+COUNTIFS(Canon!$G$2:$G$4229,"*"&$A13&"*",Canon!$H$2:$H$4229,"<"&F$4,Canon!$I$2:$I$4229,"") -> 20 | G13: =COUNTIFS(Canon!$G$2:$G$4229,"*"&$A13&"*",Canon!$H$2:$H$4229,"<"&G$4,Canon!$I$2:$I$4229,">="&G$3)+COUNTIFS(Canon!$G$2:$G$4229,"*"&$A13&"*",Canon!$H$2:$H$4229,"<"&G$4,Canon!$I$2:$I$4229,"") -> 24 | H13: =COUNTIFS(Canon!$G$2:$G$4229,"*"&$A13&"*",Canon!$H$2:$H$4229,"<"&H$4,Canon!$I$2:$I$4229,">="&H$3)+COUNTIFS(Canon!$G$2:$G$4229,"*"&$A13&"*",Canon!$H$2:$H$4229,"<"&H$4,Canon!$I$2:$I$4229,"") -> 25 | I13: =COUNTIFS(Canon!$G$2:$G$4229,"*"&$A13&"*",Canon!$H$2:$H$4229,"<"&I$4,Canon!$I$2:$I$4229,">="&I$3)+COUNTIFS(Canon!$G$2:$G$4229,"*"&$A13&"*",Canon!$H$2:$H$4229,"<"&I$4,Canon!$I$2:$I$4229,"") -> 37 | J13: =COUNTIFS(Canon!$G$2:$G$4229,"*"&$A13&"*",Canon!$H$2:$H$4229,"<"&J$4,Canon!$I$2:$I$4229,">="&J$3)+COUNTIFS(Canon!$G$2:$G$4229,"*"&$A13&"*",Canon!$H$2:$H$4229,"<"&J$4,Canon!$I$2:$I$4229,"") -> 44 | ... M13: =COUNTIFS(Canon!$G$2:$G$4229,"*"&$A13&"*",Canon!$H$2:$H$4229,"<"&M$4,Canon!$I$2:$I$4229,">="&M$3)+COUNTIFS(Canon!$G$2:$G$4229,"*"&$A13&"*",Canon!$H$2:$H$4229,"<"&M$4,Canon!$I$2:$I$4229,"") -> 62
A14: AF-SOU | B14: Southern Africa | C14: =COUNTIFS(Canon!$G$2:$G$4229,"*"&$A14&"*",Canon!$H$2:$H$4229,"<"&C$4,Canon!$I$2:$I$4229,">="&C$3)+COUNTIFS(Canon!$G$2:$G$4229,"*"&$A14&"*",Canon!$H$2:$H$4229,"<"&C$4,Canon!$I$2:$I$4229,"") -> 29 | D14: =COUNTIFS(Canon!$G$2:$G$4229,"*"&$A14&"*",Canon!$H$2:$H$4229,"<"&D$4,Canon!$I$2:$I$4229,">="&D$3)+COUNTIFS(Canon!$G$2:$G$4229,"*"&$A14&"*",Canon!$H$2:$H$4229,"<"&D$4,Canon!$I$2:$I$4229,"") -> 20 | E14: =COUNTIFS(Canon!$G$2:$G$4229,"*"&$A14&"*",Canon!$H$2:$H$4229,"<"&E$4,Canon!$I$2:$I$4229,">="&E$3)+COUNTIFS(Canon!$G$2:$G$4229,"*"&$A14&"*",Canon!$H$2:$H$4229,"<"&E$4,Canon!$I$2:$I$4229,"") -> 23 | F14: =COUNTIFS(Canon!$G$2:$G$4229,"*"&$A14&"*",Canon!$H$2:$H$4229,"<"&F$4,Canon!$I$2:$I$4229,">="&F$3)+COUNTIFS(Canon!$G$2:$G$4229,"*"&$A14&"*",Canon!$H$2:$H$4229,"<"&F$4,Canon!$I$2:$I$4229,"") -> 25 | G14: =COUNTIFS(Canon!$G$2:$G$4229,"*"&$A14&"*",Canon!$H$2:$H$4229,"<"&G$4,Canon!$I$2:$I$4229,">="&G$3)+COUNTIFS(Canon!$G$2:$G$4229,"*"&$A14&"*",Canon!$H$2:$H$4229,"<"&G$4,Canon!$I$2:$I$4229,"") -> 28 | H14: =COUNTIFS(Canon!$G$2:$G$4229,"*"&$A14&"*",Canon!$H$2:$H$4229,"<"&H$4,Canon!$I$2:$I$4229,">="&H$3)+COUNTIFS(Canon!$G$2:$G$4229,"*"&$A14&"*",Canon!$H$2:$H$4229,"<"&H$4,Canon!$I$2:$I$4229,"") -> 28 | I14: =COUNTIFS(Canon!$G$2:$G$4229,"*"&$A14&"*",Canon!$H$2:$H$4229,"<"&I$4,Canon!$I$2:$I$4229,">="&I$3)+COUNTIFS(Canon!$G$2:$G$4229,"*"&$A14&"*",Canon!$H$2:$H$4229,"<"&I$4,Canon!$I$2:$I$4229,"") -> 30 | J14: =COUNTIFS(Canon!$G$2:$G$4229,"*"&$A14&"*",Canon!$H$2:$H$4229,"<"&J$4,Canon!$I$2:$I$4229,">="&J$3)+COUNTIFS(Canon!$G$2:$G$4229,"*"&$A14&"*",Canon!$H$2:$H$4229,"<"&J$4,Canon!$I$2:$I$4229,"") -> 42 | ... M14: =COUNTIFS(Canon!$G$2:$G$4229,"*"&$A14&"*",Canon!$H$2:$H$4229,"<"&M$4,Canon!$I$2:$I$4229,">="&M$3)+COUNTIFS(Canon!$G$2:$G$4229,"*"&$A14&"*",Canon!$H$2:$H$4229,"<"&M$4,Canon!$I$2:$I$4229,"") -> 51
A15: AF-MAD | B15: Madagascar and Indian Ocean islands | C15: =COUNTIFS(Canon!$G$2:$G$4229,"*"&$A15&"*",Canon!$H$2:$H$4229,"<"&C$4,Canon!$I$2:$I$4229,">="&C$3)+COUNTIFS(Canon!$G$2:$G$4229,"*"&$A15&"*",Canon!$H$2:$H$4229,"<"&C$4,Canon!$I$2:$I$4229,"") -> 0 | D15: =COUNTIFS(Canon!$G$2:$G$4229,"*"&$A15&"*",Canon!$H$2:$H$4229,"<"&D$4,Canon!$I$2:$I$4229,">="&D$3)+COUNTIFS(Canon!$G$2:$G$4229,"*"&$A15&"*",Canon!$H$2:$H$4229,"<"&D$4,Canon!$I$2:$I$4229,"") -> 0 | E15: =COUNTIFS(Canon!$G$2:$G$4229,"*"&$A15&"*",Canon!$H$2:$H$4229,"<"&E$4,Canon!$I$2:$I$4229,">="&E$3)+COUNTIFS(Canon!$G$2:$G$4229,"*"&$A15&"*",Canon!$H$2:$H$4229,"<"&E$4,Canon!$I$2:$I$4229,"") -> 4 | F15: =COUNTIFS(Canon!$G$2:$G$4229,"*"&$A15&"*",Canon!$H$2:$H$4229,"<"&F$4,Canon!$I$2:$I$4229,">="&F$3)+COUNTIFS(Canon!$G$2:$G$4229,"*"&$A15&"*",Canon!$H$2:$H$4229,"<"&F$4,Canon!$I$2:$I$4229,"") -> 6 | G15: =COUNTIFS(Canon!$G$2:$G$4229,"*"&$A15&"*",Canon!$H$2:$H$4229,"<"&G$4,Canon!$I$2:$I$4229,">="&G$3)+COUNTIFS(Canon!$G$2:$G$4229,"*"&$A15&"*",Canon!$H$2:$H$4229,"<"&G$4,Canon!$I$2:$I$4229,"") -> 6 | H15: =COUNTIFS(Canon!$G$2:$G$4229,"*"&$A15&"*",Canon!$H$2:$H$4229,"<"&H$4,Canon!$I$2:$I$4229,">="&H$3)+COUNTIFS(Canon!$G$2:$G$4229,"*"&$A15&"*",Canon!$H$2:$H$4229,"<"&H$4,Canon!$I$2:$I$4229,"") -> 6 | I15: =COUNTIFS(Canon!$G$2:$G$4229,"*"&$A15&"*",Canon!$H$2:$H$4229,"<"&I$4,Canon!$I$2:$I$4229,">="&I$3)+COUNTIFS(Canon!$G$2:$G$4229,"*"&$A15&"*",Canon!$H$2:$H$4229,"<"&I$4,Canon!$I$2:$I$4229,"") -> 12 | J15: =COUNTIFS(Canon!$G$2:$G$4229,"*"&$A15&"*",Canon!$H$2:$H$4229,"<"&J$4,Canon!$I$2:$I$4229,">="&J$3)+COUNTIFS(Canon!$G$2:$G$4229,"*"&$A15&"*",Canon!$H$2:$H$4229,"<"&J$4,Canon!$I$2:$I$4229,"") -> 15 | ... M15: =COUNTIFS(Canon!$G$2:$G$4229,"*"&$A15&"*",Canon!$H$2:$H$4229,"<"&M$4,Canon!$I$2:$I$4229,">="&M$3)+COUNTIFS(Canon!$G$2:$G$4229,"*"&$A15&"*",Canon!$H$2:$H$4229,"<"&M$4,Canon!$I$2:$I$4229,"") -> 22 | N15: B01–B02: human arrival in Madagascar is debated (claims before 8000 BCE contested); likely no makers to record
A16: AM-ARC | B16: Arctic | C16: =COUNTIFS(Canon!$G$2:$G$4229,"*"&$A16&"*",Canon!$H$2:$H$4229,"<"&C$4,Canon!$I$2:$I$4229,">="&C$3)+COUNTIFS(Canon!$G$2:$G$4229,"*"&$A16&"*",Canon!$H$2:$H$4229,"<"&C$4,Canon!$I$2:$I$4229,"") -> 3 | D16: =COUNTIFS(Canon!$G$2:$G$4229,"*"&$A16&"*",Canon!$H$2:$H$4229,"<"&D$4,Canon!$I$2:$I$4229,">="&D$3)+COUNTIFS(Canon!$G$2:$G$4229,"*"&$A16&"*",Canon!$H$2:$H$4229,"<"&D$4,Canon!$I$2:$I$4229,"") -> 5 | E16: =COUNTIFS(Canon!$G$2:$G$4229,"*"&$A16&"*",Canon!$H$2:$H$4229,"<"&E$4,Canon!$I$2:$I$4229,">="&E$3)+COUNTIFS(Canon!$G$2:$G$4229,"*"&$A16&"*",Canon!$H$2:$H$4229,"<"&E$4,Canon!$I$2:$I$4229,"") -> 9 | F16: =COUNTIFS(Canon!$G$2:$G$4229,"*"&$A16&"*",Canon!$H$2:$H$4229,"<"&F$4,Canon!$I$2:$I$4229,">="&F$3)+COUNTIFS(Canon!$G$2:$G$4229,"*"&$A16&"*",Canon!$H$2:$H$4229,"<"&F$4,Canon!$I$2:$I$4229,"") -> 9 | G16: =COUNTIFS(Canon!$G$2:$G$4229,"*"&$A16&"*",Canon!$H$2:$H$4229,"<"&G$4,Canon!$I$2:$I$4229,">="&G$3)+COUNTIFS(Canon!$G$2:$G$4229,"*"&$A16&"*",Canon!$H$2:$H$4229,"<"&G$4,Canon!$I$2:$I$4229,"") -> 11 | H16: =COUNTIFS(Canon!$G$2:$G$4229,"*"&$A16&"*",Canon!$H$2:$H$4229,"<"&H$4,Canon!$I$2:$I$4229,">="&H$3)+COUNTIFS(Canon!$G$2:$G$4229,"*"&$A16&"*",Canon!$H$2:$H$4229,"<"&H$4,Canon!$I$2:$I$4229,"") -> 10 | I16: =COUNTIFS(Canon!$G$2:$G$4229,"*"&$A16&"*",Canon!$H$2:$H$4229,"<"&I$4,Canon!$I$2:$I$4229,">="&I$3)+COUNTIFS(Canon!$G$2:$G$4229,"*"&$A16&"*",Canon!$H$2:$H$4229,"<"&I$4,Canon!$I$2:$I$4229,"") -> 12 | J16: =COUNTIFS(Canon!$G$2:$G$4229,"*"&$A16&"*",Canon!$H$2:$H$4229,"<"&J$4,Canon!$I$2:$I$4229,">="&J$3)+COUNTIFS(Canon!$G$2:$G$4229,"*"&$A16&"*",Canon!$H$2:$H$4229,"<"&J$4,Canon!$I$2:$I$4229,"") -> 21 | ... M16: =COUNTIFS(Canon!$G$2:$G$4229,"*"&$A16&"*",Canon!$H$2:$H$4229,"<"&M$4,Canon!$I$2:$I$4229,">="&M$3)+COUNTIFS(Canon!$G$2:$G$4229,"*"&$A16&"*",Canon!$H$2:$H$4229,"<"&M$4,Canon!$I$2:$I$4229,"") -> 28
A17: AM-NWC | B17: Northwest Coast | C17: =COUNTIFS(Canon!$G$2:$G$4229,"*"&$A17&"*",Canon!$H$2:$H$4229,"<"&C$4,Canon!$I$2:$I$4229,">="&C$3)+COUNTIFS(Canon!$G$2:$G$4229,"*"&$A17&"*",Canon!$H$2:$H$4229,"<"&C$4,Canon!$I$2:$I$4229,"") -> 3 | D17: =COUNTIFS(Canon!$G$2:$G$4229,"*"&$A17&"*",Canon!$H$2:$H$4229,"<"&D$4,Canon!$I$2:$I$4229,">="&D$3)+COUNTIFS(Canon!$G$2:$G$4229,"*"&$A17&"*",Canon!$H$2:$H$4229,"<"&D$4,Canon!$I$2:$I$4229,"") -> 3 | E17: =COUNTIFS(Canon!$G$2:$G$4229,"*"&$A17&"*",Canon!$H$2:$H$4229,"<"&E$4,Canon!$I$2:$I$4229,">="&E$3)+COUNTIFS(Canon!$G$2:$G$4229,"*"&$A17&"*",Canon!$H$2:$H$4229,"<"&E$4,Canon!$I$2:$I$4229,"") -> 3 | F17: =COUNTIFS(Canon!$G$2:$G$4229,"*"&$A17&"*",Canon!$H$2:$H$4229,"<"&F$4,Canon!$I$2:$I$4229,">="&F$3)+COUNTIFS(Canon!$G$2:$G$4229,"*"&$A17&"*",Canon!$H$2:$H$4229,"<"&F$4,Canon!$I$2:$I$4229,"") -> 4 | G17: =COUNTIFS(Canon!$G$2:$G$4229,"*"&$A17&"*",Canon!$H$2:$H$4229,"<"&G$4,Canon!$I$2:$I$4229,">="&G$3)+COUNTIFS(Canon!$G$2:$G$4229,"*"&$A17&"*",Canon!$H$2:$H$4229,"<"&G$4,Canon!$I$2:$I$4229,"") -> 6 | H17: =COUNTIFS(Canon!$G$2:$G$4229,"*"&$A17&"*",Canon!$H$2:$H$4229,"<"&H$4,Canon!$I$2:$I$4229,">="&H$3)+COUNTIFS(Canon!$G$2:$G$4229,"*"&$A17&"*",Canon!$H$2:$H$4229,"<"&H$4,Canon!$I$2:$I$4229,"") -> 5 | I17: =COUNTIFS(Canon!$G$2:$G$4229,"*"&$A17&"*",Canon!$H$2:$H$4229,"<"&I$4,Canon!$I$2:$I$4229,">="&I$3)+COUNTIFS(Canon!$G$2:$G$4229,"*"&$A17&"*",Canon!$H$2:$H$4229,"<"&I$4,Canon!$I$2:$I$4229,"") -> 5 | J17: =COUNTIFS(Canon!$G$2:$G$4229,"*"&$A17&"*",Canon!$H$2:$H$4229,"<"&J$4,Canon!$I$2:$I$4229,">="&J$3)+COUNTIFS(Canon!$G$2:$G$4229,"*"&$A17&"*",Canon!$H$2:$H$4229,"<"&J$4,Canon!$I$2:$I$4229,"") -> 10 | ... M17: =COUNTIFS(Canon!$G$2:$G$4229,"*"&$A17&"*",Canon!$H$2:$H$4229,"<"&M$4,Canon!$I$2:$I$4229,">="&M$3)+COUNTIFS(Canon!$G$2:$G$4229,"*"&$A17&"*",Canon!$H$2:$H$4229,"<"&M$4,Canon!$I$2:$I$4229,"") -> 29
A18: AM-WST | B18: North American West | C18: =COUNTIFS(Canon!$G$2:$G$4229,"*"&$A18&"*",Canon!$H$2:$H$4229,"<"&C$4,Canon!$I$2:$I$4229,">="&C$3)+COUNTIFS(Canon!$G$2:$G$4229,"*"&$A18&"*",Canon!$H$2:$H$4229,"<"&C$4,Canon!$I$2:$I$4229,"") -> 8 | D18: =COUNTIFS(Canon!$G$2:$G$4229,"*"&$A18&"*",Canon!$H$2:$H$4229,"<"&D$4,Canon!$I$2:$I$4229,">="&D$3)+COUNTIFS(Canon!$G$2:$G$4229,"*"&$A18&"*",Canon!$H$2:$H$4229,"<"&D$4,Canon!$I$2:$I$4229,"") -> 8 | E18: =COUNTIFS(Canon!$G$2:$G$4229,"*"&$A18&"*",Canon!$H$2:$H$4229,"<"&E$4,Canon!$I$2:$I$4229,">="&E$3)+COUNTIFS(Canon!$G$2:$G$4229,"*"&$A18&"*",Canon!$H$2:$H$4229,"<"&E$4,Canon!$I$2:$I$4229,"") -> 10 | F18: =COUNTIFS(Canon!$G$2:$G$4229,"*"&$A18&"*",Canon!$H$2:$H$4229,"<"&F$4,Canon!$I$2:$I$4229,">="&F$3)+COUNTIFS(Canon!$G$2:$G$4229,"*"&$A18&"*",Canon!$H$2:$H$4229,"<"&F$4,Canon!$I$2:$I$4229,"") -> 13 | G18: =COUNTIFS(Canon!$G$2:$G$4229,"*"&$A18&"*",Canon!$H$2:$H$4229,"<"&G$4,Canon!$I$2:$I$4229,">="&G$3)+COUNTIFS(Canon!$G$2:$G$4229,"*"&$A18&"*",Canon!$H$2:$H$4229,"<"&G$4,Canon!$I$2:$I$4229,"") -> 13 | H18: =COUNTIFS(Canon!$G$2:$G$4229,"*"&$A18&"*",Canon!$H$2:$H$4229,"<"&H$4,Canon!$I$2:$I$4229,">="&H$3)+COUNTIFS(Canon!$G$2:$G$4229,"*"&$A18&"*",Canon!$H$2:$H$4229,"<"&H$4,Canon!$I$2:$I$4229,"") -> 15 | I18: =COUNTIFS(Canon!$G$2:$G$4229,"*"&$A18&"*",Canon!$H$2:$H$4229,"<"&I$4,Canon!$I$2:$I$4229,">="&I$3)+COUNTIFS(Canon!$G$2:$G$4229,"*"&$A18&"*",Canon!$H$2:$H$4229,"<"&I$4,Canon!$I$2:$I$4229,"") -> 26 | J18: =COUNTIFS(Canon!$G$2:$G$4229,"*"&$A18&"*",Canon!$H$2:$H$4229,"<"&J$4,Canon!$I$2:$I$4229,">="&J$3)+COUNTIFS(Canon!$G$2:$G$4229,"*"&$A18&"*",Canon!$H$2:$H$4229,"<"&J$4,Canon!$I$2:$I$4229,"") -> 37 | ... M18: =COUNTIFS(Canon!$G$2:$G$4229,"*"&$A18&"*",Canon!$H$2:$H$4229,"<"&M$4,Canon!$I$2:$I$4229,">="&M$3)+COUNTIFS(Canon!$G$2:$G$4229,"*"&$A18&"*",Canon!$H$2:$H$4229,"<"&M$4,Canon!$I$2:$I$4229,"") -> 91
A19: AM-EWD | B19: Eastern Woodlands | C19: =COUNTIFS(Canon!$G$2:$G$4229,"*"&$A19&"*",Canon!$H$2:$H$4229,"<"&C$4,Canon!$I$2:$I$4229,">="&C$3)+COUNTIFS(Canon!$G$2:$G$4229,"*"&$A19&"*",Canon!$H$2:$H$4229,"<"&C$4,Canon!$I$2:$I$4229,"") -> 2 | D19: =COUNTIFS(Canon!$G$2:$G$4229,"*"&$A19&"*",Canon!$H$2:$H$4229,"<"&D$4,Canon!$I$2:$I$4229,">="&D$3)+COUNTIFS(Canon!$G$2:$G$4229,"*"&$A19&"*",Canon!$H$2:$H$4229,"<"&D$4,Canon!$I$2:$I$4229,"") -> 10 | E19: =COUNTIFS(Canon!$G$2:$G$4229,"*"&$A19&"*",Canon!$H$2:$H$4229,"<"&E$4,Canon!$I$2:$I$4229,">="&E$3)+COUNTIFS(Canon!$G$2:$G$4229,"*"&$A19&"*",Canon!$H$2:$H$4229,"<"&E$4,Canon!$I$2:$I$4229,"") -> 16 | F19: =COUNTIFS(Canon!$G$2:$G$4229,"*"&$A19&"*",Canon!$H$2:$H$4229,"<"&F$4,Canon!$I$2:$I$4229,">="&F$3)+COUNTIFS(Canon!$G$2:$G$4229,"*"&$A19&"*",Canon!$H$2:$H$4229,"<"&F$4,Canon!$I$2:$I$4229,"") -> 18 | G19: =COUNTIFS(Canon!$G$2:$G$4229,"*"&$A19&"*",Canon!$H$2:$H$4229,"<"&G$4,Canon!$I$2:$I$4229,">="&G$3)+COUNTIFS(Canon!$G$2:$G$4229,"*"&$A19&"*",Canon!$H$2:$H$4229,"<"&G$4,Canon!$I$2:$I$4229,"") -> 24 | H19: =COUNTIFS(Canon!$G$2:$G$4229,"*"&$A19&"*",Canon!$H$2:$H$4229,"<"&H$4,Canon!$I$2:$I$4229,">="&H$3)+COUNTIFS(Canon!$G$2:$G$4229,"*"&$A19&"*",Canon!$H$2:$H$4229,"<"&H$4,Canon!$I$2:$I$4229,"") -> 21 | I19: =COUNTIFS(Canon!$G$2:$G$4229,"*"&$A19&"*",Canon!$H$2:$H$4229,"<"&I$4,Canon!$I$2:$I$4229,">="&I$3)+COUNTIFS(Canon!$G$2:$G$4229,"*"&$A19&"*",Canon!$H$2:$H$4229,"<"&I$4,Canon!$I$2:$I$4229,"") -> 25 | J19: =COUNTIFS(Canon!$G$2:$G$4229,"*"&$A19&"*",Canon!$H$2:$H$4229,"<"&J$4,Canon!$I$2:$I$4229,">="&J$3)+COUNTIFS(Canon!$G$2:$G$4229,"*"&$A19&"*",Canon!$H$2:$H$4229,"<"&J$4,Canon!$I$2:$I$4229,"") -> 26 | ... M19: =COUNTIFS(Canon!$G$2:$G$4229,"*"&$A19&"*",Canon!$H$2:$H$4229,"<"&M$4,Canon!$I$2:$I$4229,">="&M$3)+COUNTIFS(Canon!$G$2:$G$4229,"*"&$A19&"*",Canon!$H$2:$H$4229,"<"&M$4,Canon!$I$2:$I$4229,"") -> 162
A20: AM-MES | B20: Mesoamerica | C20: =COUNTIFS(Canon!$G$2:$G$4229,"*"&$A20&"*",Canon!$H$2:$H$4229,"<"&C$4,Canon!$I$2:$I$4229,">="&C$3)+COUNTIFS(Canon!$G$2:$G$4229,"*"&$A20&"*",Canon!$H$2:$H$4229,"<"&C$4,Canon!$I$2:$I$4229,"") -> 5 | D20: =COUNTIFS(Canon!$G$2:$G$4229,"*"&$A20&"*",Canon!$H$2:$H$4229,"<"&D$4,Canon!$I$2:$I$4229,">="&D$3)+COUNTIFS(Canon!$G$2:$G$4229,"*"&$A20&"*",Canon!$H$2:$H$4229,"<"&D$4,Canon!$I$2:$I$4229,"") -> 13 | E20: =COUNTIFS(Canon!$G$2:$G$4229,"*"&$A20&"*",Canon!$H$2:$H$4229,"<"&E$4,Canon!$I$2:$I$4229,">="&E$3)+COUNTIFS(Canon!$G$2:$G$4229,"*"&$A20&"*",Canon!$H$2:$H$4229,"<"&E$4,Canon!$I$2:$I$4229,"") -> 14 | F20: =COUNTIFS(Canon!$G$2:$G$4229,"*"&$A20&"*",Canon!$H$2:$H$4229,"<"&F$4,Canon!$I$2:$I$4229,">="&F$3)+COUNTIFS(Canon!$G$2:$G$4229,"*"&$A20&"*",Canon!$H$2:$H$4229,"<"&F$4,Canon!$I$2:$I$4229,"") -> 31 | G20: =COUNTIFS(Canon!$G$2:$G$4229,"*"&$A20&"*",Canon!$H$2:$H$4229,"<"&G$4,Canon!$I$2:$I$4229,">="&G$3)+COUNTIFS(Canon!$G$2:$G$4229,"*"&$A20&"*",Canon!$H$2:$H$4229,"<"&G$4,Canon!$I$2:$I$4229,"") -> 50 | H20: =COUNTIFS(Canon!$G$2:$G$4229,"*"&$A20&"*",Canon!$H$2:$H$4229,"<"&H$4,Canon!$I$2:$I$4229,">="&H$3)+COUNTIFS(Canon!$G$2:$G$4229,"*"&$A20&"*",Canon!$H$2:$H$4229,"<"&H$4,Canon!$I$2:$I$4229,"") -> 47 | I20: =COUNTIFS(Canon!$G$2:$G$4229,"*"&$A20&"*",Canon!$H$2:$H$4229,"<"&I$4,Canon!$I$2:$I$4229,">="&I$3)+COUNTIFS(Canon!$G$2:$G$4229,"*"&$A20&"*",Canon!$H$2:$H$4229,"<"&I$4,Canon!$I$2:$I$4229,"") -> 65 | J20: =COUNTIFS(Canon!$G$2:$G$4229,"*"&$A20&"*",Canon!$H$2:$H$4229,"<"&J$4,Canon!$I$2:$I$4229,">="&J$3)+COUNTIFS(Canon!$G$2:$G$4229,"*"&$A20&"*",Canon!$H$2:$H$4229,"<"&J$4,Canon!$I$2:$I$4229,"") -> 66 | ... M20: =COUNTIFS(Canon!$G$2:$G$4229,"*"&$A20&"*",Canon!$H$2:$H$4229,"<"&M$4,Canon!$I$2:$I$4229,">="&M$3)+COUNTIFS(Canon!$G$2:$G$4229,"*"&$A20&"*",Canon!$H$2:$H$4229,"<"&M$4,Canon!$I$2:$I$4229,"") -> 41
A21: AM-CAM | B21: Central America | C21: =COUNTIFS(Canon!$G$2:$G$4229,"*"&$A21&"*",Canon!$H$2:$H$4229,"<"&C$4,Canon!$I$2:$I$4229,">="&C$3)+COUNTIFS(Canon!$G$2:$G$4229,"*"&$A21&"*",Canon!$H$2:$H$4229,"<"&C$4,Canon!$I$2:$I$4229,"") -> 1 | D21: =COUNTIFS(Canon!$G$2:$G$4229,"*"&$A21&"*",Canon!$H$2:$H$4229,"<"&D$4,Canon!$I$2:$I$4229,">="&D$3)+COUNTIFS(Canon!$G$2:$G$4229,"*"&$A21&"*",Canon!$H$2:$H$4229,"<"&D$4,Canon!$I$2:$I$4229,"") -> 3 | E21: =COUNTIFS(Canon!$G$2:$G$4229,"*"&$A21&"*",Canon!$H$2:$H$4229,"<"&E$4,Canon!$I$2:$I$4229,">="&E$3)+COUNTIFS(Canon!$G$2:$G$4229,"*"&$A21&"*",Canon!$H$2:$H$4229,"<"&E$4,Canon!$I$2:$I$4229,"") -> 4 | F21: =COUNTIFS(Canon!$G$2:$G$4229,"*"&$A21&"*",Canon!$H$2:$H$4229,"<"&F$4,Canon!$I$2:$I$4229,">="&F$3)+COUNTIFS(Canon!$G$2:$G$4229,"*"&$A21&"*",Canon!$H$2:$H$4229,"<"&F$4,Canon!$I$2:$I$4229,"") -> 6 | G21: =COUNTIFS(Canon!$G$2:$G$4229,"*"&$A21&"*",Canon!$H$2:$H$4229,"<"&G$4,Canon!$I$2:$I$4229,">="&G$3)+COUNTIFS(Canon!$G$2:$G$4229,"*"&$A21&"*",Canon!$H$2:$H$4229,"<"&G$4,Canon!$I$2:$I$4229,"") -> 9 | H21: =COUNTIFS(Canon!$G$2:$G$4229,"*"&$A21&"*",Canon!$H$2:$H$4229,"<"&H$4,Canon!$I$2:$I$4229,">="&H$3)+COUNTIFS(Canon!$G$2:$G$4229,"*"&$A21&"*",Canon!$H$2:$H$4229,"<"&H$4,Canon!$I$2:$I$4229,"") -> 17 | I21: =COUNTIFS(Canon!$G$2:$G$4229,"*"&$A21&"*",Canon!$H$2:$H$4229,"<"&I$4,Canon!$I$2:$I$4229,">="&I$3)+COUNTIFS(Canon!$G$2:$G$4229,"*"&$A21&"*",Canon!$H$2:$H$4229,"<"&I$4,Canon!$I$2:$I$4229,"") -> 23 | J21: =COUNTIFS(Canon!$G$2:$G$4229,"*"&$A21&"*",Canon!$H$2:$H$4229,"<"&J$4,Canon!$I$2:$I$4229,">="&J$3)+COUNTIFS(Canon!$G$2:$G$4229,"*"&$A21&"*",Canon!$H$2:$H$4229,"<"&J$4,Canon!$I$2:$I$4229,"") -> 16 | ... M21: =COUNTIFS(Canon!$G$2:$G$4229,"*"&$A21&"*",Canon!$H$2:$H$4229,"<"&M$4,Canon!$I$2:$I$4229,">="&M$3)+COUNTIFS(Canon!$G$2:$G$4229,"*"&$A21&"*",Canon!$H$2:$H$4229,"<"&M$4,Canon!$I$2:$I$4229,"") -> 15
A22: AM-CAR | B22: Caribbean | C22: =COUNTIFS(Canon!$G$2:$G$4229,"*"&$A22&"*",Canon!$H$2:$H$4229,"<"&C$4,Canon!$I$2:$I$4229,">="&C$3)+COUNTIFS(Canon!$G$2:$G$4229,"*"&$A22&"*",Canon!$H$2:$H$4229,"<"&C$4,Canon!$I$2:$I$4229,"") -> 2 | D22: =COUNTIFS(Canon!$G$2:$G$4229,"*"&$A22&"*",Canon!$H$2:$H$4229,"<"&D$4,Canon!$I$2:$I$4229,">="&D$3)+COUNTIFS(Canon!$G$2:$G$4229,"*"&$A22&"*",Canon!$H$2:$H$4229,"<"&D$4,Canon!$I$2:$I$4229,"") -> 2 | E22: =COUNTIFS(Canon!$G$2:$G$4229,"*"&$A22&"*",Canon!$H$2:$H$4229,"<"&E$4,Canon!$I$2:$I$4229,">="&E$3)+COUNTIFS(Canon!$G$2:$G$4229,"*"&$A22&"*",Canon!$H$2:$H$4229,"<"&E$4,Canon!$I$2:$I$4229,"") -> 5 | F22: =COUNTIFS(Canon!$G$2:$G$4229,"*"&$A22&"*",Canon!$H$2:$H$4229,"<"&F$4,Canon!$I$2:$I$4229,">="&F$3)+COUNTIFS(Canon!$G$2:$G$4229,"*"&$A22&"*",Canon!$H$2:$H$4229,"<"&F$4,Canon!$I$2:$I$4229,"") -> 5 | G22: =COUNTIFS(Canon!$G$2:$G$4229,"*"&$A22&"*",Canon!$H$2:$H$4229,"<"&G$4,Canon!$I$2:$I$4229,">="&G$3)+COUNTIFS(Canon!$G$2:$G$4229,"*"&$A22&"*",Canon!$H$2:$H$4229,"<"&G$4,Canon!$I$2:$I$4229,"") -> 8 | H22: =COUNTIFS(Canon!$G$2:$G$4229,"*"&$A22&"*",Canon!$H$2:$H$4229,"<"&H$4,Canon!$I$2:$I$4229,">="&H$3)+COUNTIFS(Canon!$G$2:$G$4229,"*"&$A22&"*",Canon!$H$2:$H$4229,"<"&H$4,Canon!$I$2:$I$4229,"") -> 6 | I22: =COUNTIFS(Canon!$G$2:$G$4229,"*"&$A22&"*",Canon!$H$2:$H$4229,"<"&I$4,Canon!$I$2:$I$4229,">="&I$3)+COUNTIFS(Canon!$G$2:$G$4229,"*"&$A22&"*",Canon!$H$2:$H$4229,"<"&I$4,Canon!$I$2:$I$4229,"") -> 10 | J22: =COUNTIFS(Canon!$G$2:$G$4229,"*"&$A22&"*",Canon!$H$2:$H$4229,"<"&J$4,Canon!$I$2:$I$4229,">="&J$3)+COUNTIFS(Canon!$G$2:$G$4229,"*"&$A22&"*",Canon!$H$2:$H$4229,"<"&J$4,Canon!$I$2:$I$4229,"") -> 13 | ... M22: =COUNTIFS(Canon!$G$2:$G$4229,"*"&$A22&"*",Canon!$H$2:$H$4229,"<"&M$4,Canon!$I$2:$I$4229,">="&M$3)+COUNTIFS(Canon!$G$2:$G$4229,"*"&$A22&"*",Canon!$H$2:$H$4229,"<"&M$4,Canon!$I$2:$I$4229,"") -> 40
A23: AM-AND | B23: Andes and Pacific coast | C23: =COUNTIFS(Canon!$G$2:$G$4229,"*"&$A23&"*",Canon!$H$2:$H$4229,"<"&C$4,Canon!$I$2:$I$4229,">="&C$3)+COUNTIFS(Canon!$G$2:$G$4229,"*"&$A23&"*",Canon!$H$2:$H$4229,"<"&C$4,Canon!$I$2:$I$4229,"") -> 6 | D23: =COUNTIFS(Canon!$G$2:$G$4229,"*"&$A23&"*",Canon!$H$2:$H$4229,"<"&D$4,Canon!$I$2:$I$4229,">="&D$3)+COUNTIFS(Canon!$G$2:$G$4229,"*"&$A23&"*",Canon!$H$2:$H$4229,"<"&D$4,Canon!$I$2:$I$4229,"") -> 20 | E23: =COUNTIFS(Canon!$G$2:$G$4229,"*"&$A23&"*",Canon!$H$2:$H$4229,"<"&E$4,Canon!$I$2:$I$4229,">="&E$3)+COUNTIFS(Canon!$G$2:$G$4229,"*"&$A23&"*",Canon!$H$2:$H$4229,"<"&E$4,Canon!$I$2:$I$4229,"") -> 42 | F23: =COUNTIFS(Canon!$G$2:$G$4229,"*"&$A23&"*",Canon!$H$2:$H$4229,"<"&F$4,Canon!$I$2:$I$4229,">="&F$3)+COUNTIFS(Canon!$G$2:$G$4229,"*"&$A23&"*",Canon!$H$2:$H$4229,"<"&F$4,Canon!$I$2:$I$4229,"") -> 49 | G23: =COUNTIFS(Canon!$G$2:$G$4229,"*"&$A23&"*",Canon!$H$2:$H$4229,"<"&G$4,Canon!$I$2:$I$4229,">="&G$3)+COUNTIFS(Canon!$G$2:$G$4229,"*"&$A23&"*",Canon!$H$2:$H$4229,"<"&G$4,Canon!$I$2:$I$4229,"") -> 60 | H23: =COUNTIFS(Canon!$G$2:$G$4229,"*"&$A23&"*",Canon!$H$2:$H$4229,"<"&H$4,Canon!$I$2:$I$4229,">="&H$3)+COUNTIFS(Canon!$G$2:$G$4229,"*"&$A23&"*",Canon!$H$2:$H$4229,"<"&H$4,Canon!$I$2:$I$4229,"") -> 61 | I23: =COUNTIFS(Canon!$G$2:$G$4229,"*"&$A23&"*",Canon!$H$2:$H$4229,"<"&I$4,Canon!$I$2:$I$4229,">="&I$3)+COUNTIFS(Canon!$G$2:$G$4229,"*"&$A23&"*",Canon!$H$2:$H$4229,"<"&I$4,Canon!$I$2:$I$4229,"") -> 83 | J23: =COUNTIFS(Canon!$G$2:$G$4229,"*"&$A23&"*",Canon!$H$2:$H$4229,"<"&J$4,Canon!$I$2:$I$4229,">="&J$3)+COUNTIFS(Canon!$G$2:$G$4229,"*"&$A23&"*",Canon!$H$2:$H$4229,"<"&J$4,Canon!$I$2:$I$4229,"") -> 74 | ... M23: =COUNTIFS(Canon!$G$2:$G$4229,"*"&$A23&"*",Canon!$H$2:$H$4229,"<"&M$4,Canon!$I$2:$I$4229,">="&M$3)+COUNTIFS(Canon!$G$2:$G$4229,"*"&$A23&"*",Canon!$H$2:$H$4229,"<"&M$4,Canon!$I$2:$I$4229,"") -> 71
A24: AM-AMZ | B24: Amazonia and lowlands | C24: =COUNTIFS(Canon!$G$2:$G$4229,"*"&$A24&"*",Canon!$H$2:$H$4229,"<"&C$4,Canon!$I$2:$I$4229,">="&C$3)+COUNTIFS(Canon!$G$2:$G$4229,"*"&$A24&"*",Canon!$H$2:$H$4229,"<"&C$4,Canon!$I$2:$I$4229,"") -> 3 | D24: =COUNTIFS(Canon!$G$2:$G$4229,"*"&$A24&"*",Canon!$H$2:$H$4229,"<"&D$4,Canon!$I$2:$I$4229,">="&D$3)+COUNTIFS(Canon!$G$2:$G$4229,"*"&$A24&"*",Canon!$H$2:$H$4229,"<"&D$4,Canon!$I$2:$I$4229,"") -> 10 | E24: =COUNTIFS(Canon!$G$2:$G$4229,"*"&$A24&"*",Canon!$H$2:$H$4229,"<"&E$4,Canon!$I$2:$I$4229,">="&E$3)+COUNTIFS(Canon!$G$2:$G$4229,"*"&$A24&"*",Canon!$H$2:$H$4229,"<"&E$4,Canon!$I$2:$I$4229,"") -> 10 | F24: =COUNTIFS(Canon!$G$2:$G$4229,"*"&$A24&"*",Canon!$H$2:$H$4229,"<"&F$4,Canon!$I$2:$I$4229,">="&F$3)+COUNTIFS(Canon!$G$2:$G$4229,"*"&$A24&"*",Canon!$H$2:$H$4229,"<"&F$4,Canon!$I$2:$I$4229,"") -> 10 | G24: =COUNTIFS(Canon!$G$2:$G$4229,"*"&$A24&"*",Canon!$H$2:$H$4229,"<"&G$4,Canon!$I$2:$I$4229,">="&G$3)+COUNTIFS(Canon!$G$2:$G$4229,"*"&$A24&"*",Canon!$H$2:$H$4229,"<"&G$4,Canon!$I$2:$I$4229,"") -> 15 | H24: =COUNTIFS(Canon!$G$2:$G$4229,"*"&$A24&"*",Canon!$H$2:$H$4229,"<"&H$4,Canon!$I$2:$I$4229,">="&H$3)+COUNTIFS(Canon!$G$2:$G$4229,"*"&$A24&"*",Canon!$H$2:$H$4229,"<"&H$4,Canon!$I$2:$I$4229,"") -> 22 | I24: =COUNTIFS(Canon!$G$2:$G$4229,"*"&$A24&"*",Canon!$H$2:$H$4229,"<"&I$4,Canon!$I$2:$I$4229,">="&I$3)+COUNTIFS(Canon!$G$2:$G$4229,"*"&$A24&"*",Canon!$H$2:$H$4229,"<"&I$4,Canon!$I$2:$I$4229,"") -> 27 | J24: =COUNTIFS(Canon!$G$2:$G$4229,"*"&$A24&"*",Canon!$H$2:$H$4229,"<"&J$4,Canon!$I$2:$I$4229,">="&J$3)+COUNTIFS(Canon!$G$2:$G$4229,"*"&$A24&"*",Canon!$H$2:$H$4229,"<"&J$4,Canon!$I$2:$I$4229,"") -> 27 | ... M24: =COUNTIFS(Canon!$G$2:$G$4229,"*"&$A24&"*",Canon!$H$2:$H$4229,"<"&M$4,Canon!$I$2:$I$4229,">="&M$3)+COUNTIFS(Canon!$G$2:$G$4229,"*"&$A24&"*",Canon!$H$2:$H$4229,"<"&M$4,Canon!$I$2:$I$4229,"") -> 25
A25: AM-LAT | B25: Colonial and modern Latin America | C25: =COUNTIFS(Canon!$G$2:$G$4229,"*"&$A25&"*",Canon!$H$2:$H$4229,"<"&C$4,Canon!$I$2:$I$4229,">="&C$3)+COUNTIFS(Canon!$G$2:$G$4229,"*"&$A25&"*",Canon!$H$2:$H$4229,"<"&C$4,Canon!$I$2:$I$4229,"") -> 0 | D25: =COUNTIFS(Canon!$G$2:$G$4229,"*"&$A25&"*",Canon!$H$2:$H$4229,"<"&D$4,Canon!$I$2:$I$4229,">="&D$3)+COUNTIFS(Canon!$G$2:$G$4229,"*"&$A25&"*",Canon!$H$2:$H$4229,"<"&D$4,Canon!$I$2:$I$4229,"") -> 1 | E25: =COUNTIFS(Canon!$G$2:$G$4229,"*"&$A25&"*",Canon!$H$2:$H$4229,"<"&E$4,Canon!$I$2:$I$4229,">="&E$3)+COUNTIFS(Canon!$G$2:$G$4229,"*"&$A25&"*",Canon!$H$2:$H$4229,"<"&E$4,Canon!$I$2:$I$4229,"") -> 4 | F25: =COUNTIFS(Canon!$G$2:$G$4229,"*"&$A25&"*",Canon!$H$2:$H$4229,"<"&F$4,Canon!$I$2:$I$4229,">="&F$3)+COUNTIFS(Canon!$G$2:$G$4229,"*"&$A25&"*",Canon!$H$2:$H$4229,"<"&F$4,Canon!$I$2:$I$4229,"") -> 4 | G25: =COUNTIFS(Canon!$G$2:$G$4229,"*"&$A25&"*",Canon!$H$2:$H$4229,"<"&G$4,Canon!$I$2:$I$4229,">="&G$3)+COUNTIFS(Canon!$G$2:$G$4229,"*"&$A25&"*",Canon!$H$2:$H$4229,"<"&G$4,Canon!$I$2:$I$4229,"") -> 8 | H25: =COUNTIFS(Canon!$G$2:$G$4229,"*"&$A25&"*",Canon!$H$2:$H$4229,"<"&H$4,Canon!$I$2:$I$4229,">="&H$3)+COUNTIFS(Canon!$G$2:$G$4229,"*"&$A25&"*",Canon!$H$2:$H$4229,"<"&H$4,Canon!$I$2:$I$4229,"") -> 8 | I25: =COUNTIFS(Canon!$G$2:$G$4229,"*"&$A25&"*",Canon!$H$2:$H$4229,"<"&I$4,Canon!$I$2:$I$4229,">="&I$3)+COUNTIFS(Canon!$G$2:$G$4229,"*"&$A25&"*",Canon!$H$2:$H$4229,"<"&I$4,Canon!$I$2:$I$4229,"") -> 10 | J25: =COUNTIFS(Canon!$G$2:$G$4229,"*"&$A25&"*",Canon!$H$2:$H$4229,"<"&J$4,Canon!$I$2:$I$4229,">="&J$3)+COUNTIFS(Canon!$G$2:$G$4229,"*"&$A25&"*",Canon!$H$2:$H$4229,"<"&J$4,Canon!$I$2:$I$4229,"") -> 18 | ... M25: =COUNTIFS(Canon!$G$2:$G$4229,"*"&$A25&"*",Canon!$H$2:$H$4229,"<"&M$4,Canon!$I$2:$I$4229,">="&M$3)+COUNTIFS(Canon!$G$2:$G$4229,"*"&$A25&"*",Canon!$H$2:$H$4229,"<"&M$4,Canon!$I$2:$I$4229,"") -> 95 | N25: Period-region: starts 1492
A26: AS-CHN | B26: China | C26: =COUNTIFS(Canon!$G$2:$G$4229,"*"&$A26&"*",Canon!$H$2:$H$4229,"<"&C$4,Canon!$I$2:$I$4229,">="&C$3)+COUNTIFS(Canon!$G$2:$G$4229,"*"&$A26&"*",Canon!$H$2:$H$4229,"<"&C$4,Canon!$I$2:$I$4229,"") -> 10 | D26: =COUNTIFS(Canon!$G$2:$G$4229,"*"&$A26&"*",Canon!$H$2:$H$4229,"<"&D$4,Canon!$I$2:$I$4229,">="&D$3)+COUNTIFS(Canon!$G$2:$G$4229,"*"&$A26&"*",Canon!$H$2:$H$4229,"<"&D$4,Canon!$I$2:$I$4229,"") -> 30 | E26: =COUNTIFS(Canon!$G$2:$G$4229,"*"&$A26&"*",Canon!$H$2:$H$4229,"<"&E$4,Canon!$I$2:$I$4229,">="&E$3)+COUNTIFS(Canon!$G$2:$G$4229,"*"&$A26&"*",Canon!$H$2:$H$4229,"<"&E$4,Canon!$I$2:$I$4229,"") -> 54 | F26: =COUNTIFS(Canon!$G$2:$G$4229,"*"&$A26&"*",Canon!$H$2:$H$4229,"<"&F$4,Canon!$I$2:$I$4229,">="&F$3)+COUNTIFS(Canon!$G$2:$G$4229,"*"&$A26&"*",Canon!$H$2:$H$4229,"<"&F$4,Canon!$I$2:$I$4229,"") -> 75 | G26: =COUNTIFS(Canon!$G$2:$G$4229,"*"&$A26&"*",Canon!$H$2:$H$4229,"<"&G$4,Canon!$I$2:$I$4229,">="&G$3)+COUNTIFS(Canon!$G$2:$G$4229,"*"&$A26&"*",Canon!$H$2:$H$4229,"<"&G$4,Canon!$I$2:$I$4229,"") -> 118 | H26: =COUNTIFS(Canon!$G$2:$G$4229,"*"&$A26&"*",Canon!$H$2:$H$4229,"<"&H$4,Canon!$I$2:$I$4229,">="&H$3)+COUNTIFS(Canon!$G$2:$G$4229,"*"&$A26&"*",Canon!$H$2:$H$4229,"<"&H$4,Canon!$I$2:$I$4229,"") -> 120 | I26: =COUNTIFS(Canon!$G$2:$G$4229,"*"&$A26&"*",Canon!$H$2:$H$4229,"<"&I$4,Canon!$I$2:$I$4229,">="&I$3)+COUNTIFS(Canon!$G$2:$G$4229,"*"&$A26&"*",Canon!$H$2:$H$4229,"<"&I$4,Canon!$I$2:$I$4229,"") -> 154 | J26: =COUNTIFS(Canon!$G$2:$G$4229,"*"&$A26&"*",Canon!$H$2:$H$4229,"<"&J$4,Canon!$I$2:$I$4229,">="&J$3)+COUNTIFS(Canon!$G$2:$G$4229,"*"&$A26&"*",Canon!$H$2:$H$4229,"<"&J$4,Canon!$I$2:$I$4229,"") -> 183 | ... M26: =COUNTIFS(Canon!$G$2:$G$4229,"*"&$A26&"*",Canon!$H$2:$H$4229,"<"&M$4,Canon!$I$2:$I$4229,">="&M$3)+COUNTIFS(Canon!$G$2:$G$4229,"*"&$A26&"*",Canon!$H$2:$H$4229,"<"&M$4,Canon!$I$2:$I$4229,"") -> 203
A27: AS-KOR | B27: Korea | C27: =COUNTIFS(Canon!$G$2:$G$4229,"*"&$A27&"*",Canon!$H$2:$H$4229,"<"&C$4,Canon!$I$2:$I$4229,">="&C$3)+COUNTIFS(Canon!$G$2:$G$4229,"*"&$A27&"*",Canon!$H$2:$H$4229,"<"&C$4,Canon!$I$2:$I$4229,"") -> 1 | D27: =COUNTIFS(Canon!$G$2:$G$4229,"*"&$A27&"*",Canon!$H$2:$H$4229,"<"&D$4,Canon!$I$2:$I$4229,">="&D$3)+COUNTIFS(Canon!$G$2:$G$4229,"*"&$A27&"*",Canon!$H$2:$H$4229,"<"&D$4,Canon!$I$2:$I$4229,"") -> 4 | E27: =COUNTIFS(Canon!$G$2:$G$4229,"*"&$A27&"*",Canon!$H$2:$H$4229,"<"&E$4,Canon!$I$2:$I$4229,">="&E$3)+COUNTIFS(Canon!$G$2:$G$4229,"*"&$A27&"*",Canon!$H$2:$H$4229,"<"&E$4,Canon!$I$2:$I$4229,"") -> 7 | F27: =COUNTIFS(Canon!$G$2:$G$4229,"*"&$A27&"*",Canon!$H$2:$H$4229,"<"&F$4,Canon!$I$2:$I$4229,">="&F$3)+COUNTIFS(Canon!$G$2:$G$4229,"*"&$A27&"*",Canon!$H$2:$H$4229,"<"&F$4,Canon!$I$2:$I$4229,"") -> 14 | G27: =COUNTIFS(Canon!$G$2:$G$4229,"*"&$A27&"*",Canon!$H$2:$H$4229,"<"&G$4,Canon!$I$2:$I$4229,">="&G$3)+COUNTIFS(Canon!$G$2:$G$4229,"*"&$A27&"*",Canon!$H$2:$H$4229,"<"&G$4,Canon!$I$2:$I$4229,"") -> 28 | H27: =COUNTIFS(Canon!$G$2:$G$4229,"*"&$A27&"*",Canon!$H$2:$H$4229,"<"&H$4,Canon!$I$2:$I$4229,">="&H$3)+COUNTIFS(Canon!$G$2:$G$4229,"*"&$A27&"*",Canon!$H$2:$H$4229,"<"&H$4,Canon!$I$2:$I$4229,"") -> 30 | I27: =COUNTIFS(Canon!$G$2:$G$4229,"*"&$A27&"*",Canon!$H$2:$H$4229,"<"&I$4,Canon!$I$2:$I$4229,">="&I$3)+COUNTIFS(Canon!$G$2:$G$4229,"*"&$A27&"*",Canon!$H$2:$H$4229,"<"&I$4,Canon!$I$2:$I$4229,"") -> 41 | J27: =COUNTIFS(Canon!$G$2:$G$4229,"*"&$A27&"*",Canon!$H$2:$H$4229,"<"&J$4,Canon!$I$2:$I$4229,">="&J$3)+COUNTIFS(Canon!$G$2:$G$4229,"*"&$A27&"*",Canon!$H$2:$H$4229,"<"&J$4,Canon!$I$2:$I$4229,"") -> 44 | ... M27: =COUNTIFS(Canon!$G$2:$G$4229,"*"&$A27&"*",Canon!$H$2:$H$4229,"<"&M$4,Canon!$I$2:$I$4229,">="&M$3)+COUNTIFS(Canon!$G$2:$G$4229,"*"&$A27&"*",Canon!$H$2:$H$4229,"<"&M$4,Canon!$I$2:$I$4229,"") -> 53
A28: AS-JPN | B28: Japan | C28: =COUNTIFS(Canon!$G$2:$G$4229,"*"&$A28&"*",Canon!$H$2:$H$4229,"<"&C$4,Canon!$I$2:$I$4229,">="&C$3)+COUNTIFS(Canon!$G$2:$G$4229,"*"&$A28&"*",Canon!$H$2:$H$4229,"<"&C$4,Canon!$I$2:$I$4229,"") -> 12 | D28: =COUNTIFS(Canon!$G$2:$G$4229,"*"&$A28&"*",Canon!$H$2:$H$4229,"<"&D$4,Canon!$I$2:$I$4229,">="&D$3)+COUNTIFS(Canon!$G$2:$G$4229,"*"&$A28&"*",Canon!$H$2:$H$4229,"<"&D$4,Canon!$I$2:$I$4229,"") -> 18 | E28: =COUNTIFS(Canon!$G$2:$G$4229,"*"&$A28&"*",Canon!$H$2:$H$4229,"<"&E$4,Canon!$I$2:$I$4229,">="&E$3)+COUNTIFS(Canon!$G$2:$G$4229,"*"&$A28&"*",Canon!$H$2:$H$4229,"<"&E$4,Canon!$I$2:$I$4229,"") -> 24 | F28: =COUNTIFS(Canon!$G$2:$G$4229,"*"&$A28&"*",Canon!$H$2:$H$4229,"<"&F$4,Canon!$I$2:$I$4229,">="&F$3)+COUNTIFS(Canon!$G$2:$G$4229,"*"&$A28&"*",Canon!$H$2:$H$4229,"<"&F$4,Canon!$I$2:$I$4229,"") -> 26 | G28: =COUNTIFS(Canon!$G$2:$G$4229,"*"&$A28&"*",Canon!$H$2:$H$4229,"<"&G$4,Canon!$I$2:$I$4229,">="&G$3)+COUNTIFS(Canon!$G$2:$G$4229,"*"&$A28&"*",Canon!$H$2:$H$4229,"<"&G$4,Canon!$I$2:$I$4229,"") -> 35 | H28: =COUNTIFS(Canon!$G$2:$G$4229,"*"&$A28&"*",Canon!$H$2:$H$4229,"<"&H$4,Canon!$I$2:$I$4229,">="&H$3)+COUNTIFS(Canon!$G$2:$G$4229,"*"&$A28&"*",Canon!$H$2:$H$4229,"<"&H$4,Canon!$I$2:$I$4229,"") -> 38 | I28: =COUNTIFS(Canon!$G$2:$G$4229,"*"&$A28&"*",Canon!$H$2:$H$4229,"<"&I$4,Canon!$I$2:$I$4229,">="&I$3)+COUNTIFS(Canon!$G$2:$G$4229,"*"&$A28&"*",Canon!$H$2:$H$4229,"<"&I$4,Canon!$I$2:$I$4229,"") -> 61 | J28: =COUNTIFS(Canon!$G$2:$G$4229,"*"&$A28&"*",Canon!$H$2:$H$4229,"<"&J$4,Canon!$I$2:$I$4229,">="&J$3)+COUNTIFS(Canon!$G$2:$G$4229,"*"&$A28&"*",Canon!$H$2:$H$4229,"<"&J$4,Canon!$I$2:$I$4229,"") -> 68 | ... M28: =COUNTIFS(Canon!$G$2:$G$4229,"*"&$A28&"*",Canon!$H$2:$H$4229,"<"&M$4,Canon!$I$2:$I$4229,">="&M$3)+COUNTIFS(Canon!$G$2:$G$4229,"*"&$A28&"*",Canon!$H$2:$H$4229,"<"&M$4,Canon!$I$2:$I$4229,"") -> 127
A29: AS-SAS | B29: South Asia | C29: =COUNTIFS(Canon!$G$2:$G$4229,"*"&$A29&"*",Canon!$H$2:$H$4229,"<"&C$4,Canon!$I$2:$I$4229,">="&C$3)+COUNTIFS(Canon!$G$2:$G$4229,"*"&$A29&"*",Canon!$H$2:$H$4229,"<"&C$4,Canon!$I$2:$I$4229,"") -> 4 | D29: =COUNTIFS(Canon!$G$2:$G$4229,"*"&$A29&"*",Canon!$H$2:$H$4229,"<"&D$4,Canon!$I$2:$I$4229,">="&D$3)+COUNTIFS(Canon!$G$2:$G$4229,"*"&$A29&"*",Canon!$H$2:$H$4229,"<"&D$4,Canon!$I$2:$I$4229,"") -> 16 | E29: =COUNTIFS(Canon!$G$2:$G$4229,"*"&$A29&"*",Canon!$H$2:$H$4229,"<"&E$4,Canon!$I$2:$I$4229,">="&E$3)+COUNTIFS(Canon!$G$2:$G$4229,"*"&$A29&"*",Canon!$H$2:$H$4229,"<"&E$4,Canon!$I$2:$I$4229,"") -> 49 | F29: =COUNTIFS(Canon!$G$2:$G$4229,"*"&$A29&"*",Canon!$H$2:$H$4229,"<"&F$4,Canon!$I$2:$I$4229,">="&F$3)+COUNTIFS(Canon!$G$2:$G$4229,"*"&$A29&"*",Canon!$H$2:$H$4229,"<"&F$4,Canon!$I$2:$I$4229,"") -> 61 | G29: =COUNTIFS(Canon!$G$2:$G$4229,"*"&$A29&"*",Canon!$H$2:$H$4229,"<"&G$4,Canon!$I$2:$I$4229,">="&G$3)+COUNTIFS(Canon!$G$2:$G$4229,"*"&$A29&"*",Canon!$H$2:$H$4229,"<"&G$4,Canon!$I$2:$I$4229,"") -> 90 | H29: =COUNTIFS(Canon!$G$2:$G$4229,"*"&$A29&"*",Canon!$H$2:$H$4229,"<"&H$4,Canon!$I$2:$I$4229,">="&H$3)+COUNTIFS(Canon!$G$2:$G$4229,"*"&$A29&"*",Canon!$H$2:$H$4229,"<"&H$4,Canon!$I$2:$I$4229,"") -> 93 | I29: =COUNTIFS(Canon!$G$2:$G$4229,"*"&$A29&"*",Canon!$H$2:$H$4229,"<"&I$4,Canon!$I$2:$I$4229,">="&I$3)+COUNTIFS(Canon!$G$2:$G$4229,"*"&$A29&"*",Canon!$H$2:$H$4229,"<"&I$4,Canon!$I$2:$I$4229,"") -> 114 | J29: =COUNTIFS(Canon!$G$2:$G$4229,"*"&$A29&"*",Canon!$H$2:$H$4229,"<"&J$4,Canon!$I$2:$I$4229,">="&J$3)+COUNTIFS(Canon!$G$2:$G$4229,"*"&$A29&"*",Canon!$H$2:$H$4229,"<"&J$4,Canon!$I$2:$I$4229,"") -> 138 | ... M29: =COUNTIFS(Canon!$G$2:$G$4229,"*"&$A29&"*",Canon!$H$2:$H$4229,"<"&M$4,Canon!$I$2:$I$4229,">="&M$3)+COUNTIFS(Canon!$G$2:$G$4229,"*"&$A29&"*",Canon!$H$2:$H$4229,"<"&M$4,Canon!$I$2:$I$4229,"") -> 222
A30: AS-HIM | B30: Himalaya and Tibet | C30: =COUNTIFS(Canon!$G$2:$G$4229,"*"&$A30&"*",Canon!$H$2:$H$4229,"<"&C$4,Canon!$I$2:$I$4229,">="&C$3)+COUNTIFS(Canon!$G$2:$G$4229,"*"&$A30&"*",Canon!$H$2:$H$4229,"<"&C$4,Canon!$I$2:$I$4229,"") -> 0 | D30: =COUNTIFS(Canon!$G$2:$G$4229,"*"&$A30&"*",Canon!$H$2:$H$4229,"<"&D$4,Canon!$I$2:$I$4229,">="&D$3)+COUNTIFS(Canon!$G$2:$G$4229,"*"&$A30&"*",Canon!$H$2:$H$4229,"<"&D$4,Canon!$I$2:$I$4229,"") -> 1 | E30: =COUNTIFS(Canon!$G$2:$G$4229,"*"&$A30&"*",Canon!$H$2:$H$4229,"<"&E$4,Canon!$I$2:$I$4229,">="&E$3)+COUNTIFS(Canon!$G$2:$G$4229,"*"&$A30&"*",Canon!$H$2:$H$4229,"<"&E$4,Canon!$I$2:$I$4229,"") -> 6 | F30: =COUNTIFS(Canon!$G$2:$G$4229,"*"&$A30&"*",Canon!$H$2:$H$4229,"<"&F$4,Canon!$I$2:$I$4229,">="&F$3)+COUNTIFS(Canon!$G$2:$G$4229,"*"&$A30&"*",Canon!$H$2:$H$4229,"<"&F$4,Canon!$I$2:$I$4229,"") -> 7 | G30: =COUNTIFS(Canon!$G$2:$G$4229,"*"&$A30&"*",Canon!$H$2:$H$4229,"<"&G$4,Canon!$I$2:$I$4229,">="&G$3)+COUNTIFS(Canon!$G$2:$G$4229,"*"&$A30&"*",Canon!$H$2:$H$4229,"<"&G$4,Canon!$I$2:$I$4229,"") -> 7 | H30: =COUNTIFS(Canon!$G$2:$G$4229,"*"&$A30&"*",Canon!$H$2:$H$4229,"<"&H$4,Canon!$I$2:$I$4229,">="&H$3)+COUNTIFS(Canon!$G$2:$G$4229,"*"&$A30&"*",Canon!$H$2:$H$4229,"<"&H$4,Canon!$I$2:$I$4229,"") -> 12 | I30: =COUNTIFS(Canon!$G$2:$G$4229,"*"&$A30&"*",Canon!$H$2:$H$4229,"<"&I$4,Canon!$I$2:$I$4229,">="&I$3)+COUNTIFS(Canon!$G$2:$G$4229,"*"&$A30&"*",Canon!$H$2:$H$4229,"<"&I$4,Canon!$I$2:$I$4229,"") -> 26 | J30: =COUNTIFS(Canon!$G$2:$G$4229,"*"&$A30&"*",Canon!$H$2:$H$4229,"<"&J$4,Canon!$I$2:$I$4229,">="&J$3)+COUNTIFS(Canon!$G$2:$G$4229,"*"&$A30&"*",Canon!$H$2:$H$4229,"<"&J$4,Canon!$I$2:$I$4229,"") -> 29 | ... M30: =COUNTIFS(Canon!$G$2:$G$4229,"*"&$A30&"*",Canon!$H$2:$H$4229,"<"&M$4,Canon!$I$2:$I$4229,">="&M$3)+COUNTIFS(Canon!$G$2:$G$4229,"*"&$A30&"*",Canon!$H$2:$H$4229,"<"&M$4,Canon!$I$2:$I$4229,"") -> 37 | N30: B01: Denisovan presence on the Tibetan Plateau (Baishiya Karst Cave) is a candidate node
A31: AS-MSE | B31: Mainland Southeast Asia | C31: =COUNTIFS(Canon!$G$2:$G$4229,"*"&$A31&"*",Canon!$H$2:$H$4229,"<"&C$4,Canon!$I$2:$I$4229,">="&C$3)+COUNTIFS(Canon!$G$2:$G$4229,"*"&$A31&"*",Canon!$H$2:$H$4229,"<"&C$4,Canon!$I$2:$I$4229,"") -> 2 | D31: =COUNTIFS(Canon!$G$2:$G$4229,"*"&$A31&"*",Canon!$H$2:$H$4229,"<"&D$4,Canon!$I$2:$I$4229,">="&D$3)+COUNTIFS(Canon!$G$2:$G$4229,"*"&$A31&"*",Canon!$H$2:$H$4229,"<"&D$4,Canon!$I$2:$I$4229,"") -> 8 | E31: =COUNTIFS(Canon!$G$2:$G$4229,"*"&$A31&"*",Canon!$H$2:$H$4229,"<"&E$4,Canon!$I$2:$I$4229,">="&E$3)+COUNTIFS(Canon!$G$2:$G$4229,"*"&$A31&"*",Canon!$H$2:$H$4229,"<"&E$4,Canon!$I$2:$I$4229,"") -> 15 | F31: =COUNTIFS(Canon!$G$2:$G$4229,"*"&$A31&"*",Canon!$H$2:$H$4229,"<"&F$4,Canon!$I$2:$I$4229,">="&F$3)+COUNTIFS(Canon!$G$2:$G$4229,"*"&$A31&"*",Canon!$H$2:$H$4229,"<"&F$4,Canon!$I$2:$I$4229,"") -> 20 | G31: =COUNTIFS(Canon!$G$2:$G$4229,"*"&$A31&"*",Canon!$H$2:$H$4229,"<"&G$4,Canon!$I$2:$I$4229,">="&G$3)+COUNTIFS(Canon!$G$2:$G$4229,"*"&$A31&"*",Canon!$H$2:$H$4229,"<"&G$4,Canon!$I$2:$I$4229,"") -> 39 | H31: =COUNTIFS(Canon!$G$2:$G$4229,"*"&$A31&"*",Canon!$H$2:$H$4229,"<"&H$4,Canon!$I$2:$I$4229,">="&H$3)+COUNTIFS(Canon!$G$2:$G$4229,"*"&$A31&"*",Canon!$H$2:$H$4229,"<"&H$4,Canon!$I$2:$I$4229,"") -> 52 | I31: =COUNTIFS(Canon!$G$2:$G$4229,"*"&$A31&"*",Canon!$H$2:$H$4229,"<"&I$4,Canon!$I$2:$I$4229,">="&I$3)+COUNTIFS(Canon!$G$2:$G$4229,"*"&$A31&"*",Canon!$H$2:$H$4229,"<"&I$4,Canon!$I$2:$I$4229,"") -> 59 | J31: =COUNTIFS(Canon!$G$2:$G$4229,"*"&$A31&"*",Canon!$H$2:$H$4229,"<"&J$4,Canon!$I$2:$I$4229,">="&J$3)+COUNTIFS(Canon!$G$2:$G$4229,"*"&$A31&"*",Canon!$H$2:$H$4229,"<"&J$4,Canon!$I$2:$I$4229,"") -> 64 | ... M31: =COUNTIFS(Canon!$G$2:$G$4229,"*"&$A31&"*",Canon!$H$2:$H$4229,"<"&M$4,Canon!$I$2:$I$4229,">="&M$3)+COUNTIFS(Canon!$G$2:$G$4229,"*"&$A31&"*",Canon!$H$2:$H$4229,"<"&M$4,Canon!$I$2:$I$4229,"") -> 55
A32: AS-ISE | B32: Island Southeast Asia | C32: =COUNTIFS(Canon!$G$2:$G$4229,"*"&$A32&"*",Canon!$H$2:$H$4229,"<"&C$4,Canon!$I$2:$I$4229,">="&C$3)+COUNTIFS(Canon!$G$2:$G$4229,"*"&$A32&"*",Canon!$H$2:$H$4229,"<"&C$4,Canon!$I$2:$I$4229,"") -> 6 | D32: =COUNTIFS(Canon!$G$2:$G$4229,"*"&$A32&"*",Canon!$H$2:$H$4229,"<"&D$4,Canon!$I$2:$I$4229,">="&D$3)+COUNTIFS(Canon!$G$2:$G$4229,"*"&$A32&"*",Canon!$H$2:$H$4229,"<"&D$4,Canon!$I$2:$I$4229,"") -> 12 | E32: =COUNTIFS(Canon!$G$2:$G$4229,"*"&$A32&"*",Canon!$H$2:$H$4229,"<"&E$4,Canon!$I$2:$I$4229,">="&E$3)+COUNTIFS(Canon!$G$2:$G$4229,"*"&$A32&"*",Canon!$H$2:$H$4229,"<"&E$4,Canon!$I$2:$I$4229,"") -> 19 | F32: =COUNTIFS(Canon!$G$2:$G$4229,"*"&$A32&"*",Canon!$H$2:$H$4229,"<"&F$4,Canon!$I$2:$I$4229,">="&F$3)+COUNTIFS(Canon!$G$2:$G$4229,"*"&$A32&"*",Canon!$H$2:$H$4229,"<"&F$4,Canon!$I$2:$I$4229,"") -> 20 | G32: =COUNTIFS(Canon!$G$2:$G$4229,"*"&$A32&"*",Canon!$H$2:$H$4229,"<"&G$4,Canon!$I$2:$I$4229,">="&G$3)+COUNTIFS(Canon!$G$2:$G$4229,"*"&$A32&"*",Canon!$H$2:$H$4229,"<"&G$4,Canon!$I$2:$I$4229,"") -> 30 | H32: =COUNTIFS(Canon!$G$2:$G$4229,"*"&$A32&"*",Canon!$H$2:$H$4229,"<"&H$4,Canon!$I$2:$I$4229,">="&H$3)+COUNTIFS(Canon!$G$2:$G$4229,"*"&$A32&"*",Canon!$H$2:$H$4229,"<"&H$4,Canon!$I$2:$I$4229,"") -> 36 | I32: =COUNTIFS(Canon!$G$2:$G$4229,"*"&$A32&"*",Canon!$H$2:$H$4229,"<"&I$4,Canon!$I$2:$I$4229,">="&I$3)+COUNTIFS(Canon!$G$2:$G$4229,"*"&$A32&"*",Canon!$H$2:$H$4229,"<"&I$4,Canon!$I$2:$I$4229,"") -> 49 | J32: =COUNTIFS(Canon!$G$2:$G$4229,"*"&$A32&"*",Canon!$H$2:$H$4229,"<"&J$4,Canon!$I$2:$I$4229,">="&J$3)+COUNTIFS(Canon!$G$2:$G$4229,"*"&$A32&"*",Canon!$H$2:$H$4229,"<"&J$4,Canon!$I$2:$I$4229,"") -> 51 | ... M32: =COUNTIFS(Canon!$G$2:$G$4229,"*"&$A32&"*",Canon!$H$2:$H$4229,"<"&M$4,Canon!$I$2:$I$4229,">="&M$3)+COUNTIFS(Canon!$G$2:$G$4229,"*"&$A32&"*",Canon!$H$2:$H$4229,"<"&M$4,Canon!$I$2:$I$4229,"") -> 74
A33: AS-CEN | B33: Central Asia and the steppe | C33: =COUNTIFS(Canon!$G$2:$G$4229,"*"&$A33&"*",Canon!$H$2:$H$4229,"<"&C$4,Canon!$I$2:$I$4229,">="&C$3)+COUNTIFS(Canon!$G$2:$G$4229,"*"&$A33&"*",Canon!$H$2:$H$4229,"<"&C$4,Canon!$I$2:$I$4229,"") -> 3 | D33: =COUNTIFS(Canon!$G$2:$G$4229,"*"&$A33&"*",Canon!$H$2:$H$4229,"<"&D$4,Canon!$I$2:$I$4229,">="&D$3)+COUNTIFS(Canon!$G$2:$G$4229,"*"&$A33&"*",Canon!$H$2:$H$4229,"<"&D$4,Canon!$I$2:$I$4229,"") -> 4 | E33: =COUNTIFS(Canon!$G$2:$G$4229,"*"&$A33&"*",Canon!$H$2:$H$4229,"<"&E$4,Canon!$I$2:$I$4229,">="&E$3)+COUNTIFS(Canon!$G$2:$G$4229,"*"&$A33&"*",Canon!$H$2:$H$4229,"<"&E$4,Canon!$I$2:$I$4229,"") -> 19 | F33: =COUNTIFS(Canon!$G$2:$G$4229,"*"&$A33&"*",Canon!$H$2:$H$4229,"<"&F$4,Canon!$I$2:$I$4229,">="&F$3)+COUNTIFS(Canon!$G$2:$G$4229,"*"&$A33&"*",Canon!$H$2:$H$4229,"<"&F$4,Canon!$I$2:$I$4229,"") -> 28 | G33: =COUNTIFS(Canon!$G$2:$G$4229,"*"&$A33&"*",Canon!$H$2:$H$4229,"<"&G$4,Canon!$I$2:$I$4229,">="&G$3)+COUNTIFS(Canon!$G$2:$G$4229,"*"&$A33&"*",Canon!$H$2:$H$4229,"<"&G$4,Canon!$I$2:$I$4229,"") -> 61 | H33: =COUNTIFS(Canon!$G$2:$G$4229,"*"&$A33&"*",Canon!$H$2:$H$4229,"<"&H$4,Canon!$I$2:$I$4229,">="&H$3)+COUNTIFS(Canon!$G$2:$G$4229,"*"&$A33&"*",Canon!$H$2:$H$4229,"<"&H$4,Canon!$I$2:$I$4229,"") -> 57 | I33: =COUNTIFS(Canon!$G$2:$G$4229,"*"&$A33&"*",Canon!$H$2:$H$4229,"<"&I$4,Canon!$I$2:$I$4229,">="&I$3)+COUNTIFS(Canon!$G$2:$G$4229,"*"&$A33&"*",Canon!$H$2:$H$4229,"<"&I$4,Canon!$I$2:$I$4229,"") -> 75 | J33: =COUNTIFS(Canon!$G$2:$G$4229,"*"&$A33&"*",Canon!$H$2:$H$4229,"<"&J$4,Canon!$I$2:$I$4229,">="&J$3)+COUNTIFS(Canon!$G$2:$G$4229,"*"&$A33&"*",Canon!$H$2:$H$4229,"<"&J$4,Canon!$I$2:$I$4229,"") -> 83 | ... M33: =COUNTIFS(Canon!$G$2:$G$4229,"*"&$A33&"*",Canon!$H$2:$H$4229,"<"&M$4,Canon!$I$2:$I$4229,">="&M$3)+COUNTIFS(Canon!$G$2:$G$4229,"*"&$A33&"*",Canon!$H$2:$H$4229,"<"&M$4,Canon!$I$2:$I$4229,"") -> 88
A34: AS-NTH | B34: North Asia and Siberia | C34: =COUNTIFS(Canon!$G$2:$G$4229,"*"&$A34&"*",Canon!$H$2:$H$4229,"<"&C$4,Canon!$I$2:$I$4229,">="&C$3)+COUNTIFS(Canon!$G$2:$G$4229,"*"&$A34&"*",Canon!$H$2:$H$4229,"<"&C$4,Canon!$I$2:$I$4229,"") -> 11 | D34: =COUNTIFS(Canon!$G$2:$G$4229,"*"&$A34&"*",Canon!$H$2:$H$4229,"<"&D$4,Canon!$I$2:$I$4229,">="&D$3)+COUNTIFS(Canon!$G$2:$G$4229,"*"&$A34&"*",Canon!$H$2:$H$4229,"<"&D$4,Canon!$I$2:$I$4229,"") -> 14 | E34: =COUNTIFS(Canon!$G$2:$G$4229,"*"&$A34&"*",Canon!$H$2:$H$4229,"<"&E$4,Canon!$I$2:$I$4229,">="&E$3)+COUNTIFS(Canon!$G$2:$G$4229,"*"&$A34&"*",Canon!$H$2:$H$4229,"<"&E$4,Canon!$I$2:$I$4229,"") -> 17 | F34: =COUNTIFS(Canon!$G$2:$G$4229,"*"&$A34&"*",Canon!$H$2:$H$4229,"<"&F$4,Canon!$I$2:$I$4229,">="&F$3)+COUNTIFS(Canon!$G$2:$G$4229,"*"&$A34&"*",Canon!$H$2:$H$4229,"<"&F$4,Canon!$I$2:$I$4229,"") -> 21 | G34: =COUNTIFS(Canon!$G$2:$G$4229,"*"&$A34&"*",Canon!$H$2:$H$4229,"<"&G$4,Canon!$I$2:$I$4229,">="&G$3)+COUNTIFS(Canon!$G$2:$G$4229,"*"&$A34&"*",Canon!$H$2:$H$4229,"<"&G$4,Canon!$I$2:$I$4229,"") -> 31 | H34: =COUNTIFS(Canon!$G$2:$G$4229,"*"&$A34&"*",Canon!$H$2:$H$4229,"<"&H$4,Canon!$I$2:$I$4229,">="&H$3)+COUNTIFS(Canon!$G$2:$G$4229,"*"&$A34&"*",Canon!$H$2:$H$4229,"<"&H$4,Canon!$I$2:$I$4229,"") -> 22 | I34: =COUNTIFS(Canon!$G$2:$G$4229,"*"&$A34&"*",Canon!$H$2:$H$4229,"<"&I$4,Canon!$I$2:$I$4229,">="&I$3)+COUNTIFS(Canon!$G$2:$G$4229,"*"&$A34&"*",Canon!$H$2:$H$4229,"<"&I$4,Canon!$I$2:$I$4229,"") -> 27 | J34: =COUNTIFS(Canon!$G$2:$G$4229,"*"&$A34&"*",Canon!$H$2:$H$4229,"<"&J$4,Canon!$I$2:$I$4229,">="&J$3)+COUNTIFS(Canon!$G$2:$G$4229,"*"&$A34&"*",Canon!$H$2:$H$4229,"<"&J$4,Canon!$I$2:$I$4229,"") -> 28 | ... M34: =COUNTIFS(Canon!$G$2:$G$4229,"*"&$A34&"*",Canon!$H$2:$H$4229,"<"&M$4,Canon!$I$2:$I$4229,">="&M$3)+COUNTIFS(Canon!$G$2:$G$4229,"*"&$A34&"*",Canon!$H$2:$H$4229,"<"&M$4,Canon!$I$2:$I$4229,"") -> 37
A35: WA-MES | B35: Mesopotamia | C35: =COUNTIFS(Canon!$G$2:$G$4229,"*"&$A35&"*",Canon!$H$2:$H$4229,"<"&C$4,Canon!$I$2:$I$4229,">="&C$3)+COUNTIFS(Canon!$G$2:$G$4229,"*"&$A35&"*",Canon!$H$2:$H$4229,"<"&C$4,Canon!$I$2:$I$4229,"") -> 6 | D35: =COUNTIFS(Canon!$G$2:$G$4229,"*"&$A35&"*",Canon!$H$2:$H$4229,"<"&D$4,Canon!$I$2:$I$4229,">="&D$3)+COUNTIFS(Canon!$G$2:$G$4229,"*"&$A35&"*",Canon!$H$2:$H$4229,"<"&D$4,Canon!$I$2:$I$4229,"") -> 19 | E35: =COUNTIFS(Canon!$G$2:$G$4229,"*"&$A35&"*",Canon!$H$2:$H$4229,"<"&E$4,Canon!$I$2:$I$4229,">="&E$3)+COUNTIFS(Canon!$G$2:$G$4229,"*"&$A35&"*",Canon!$H$2:$H$4229,"<"&E$4,Canon!$I$2:$I$4229,"") -> 67 | F35: =COUNTIFS(Canon!$G$2:$G$4229,"*"&$A35&"*",Canon!$H$2:$H$4229,"<"&F$4,Canon!$I$2:$I$4229,">="&F$3)+COUNTIFS(Canon!$G$2:$G$4229,"*"&$A35&"*",Canon!$H$2:$H$4229,"<"&F$4,Canon!$I$2:$I$4229,"") -> 63 | G35: =COUNTIFS(Canon!$G$2:$G$4229,"*"&$A35&"*",Canon!$H$2:$H$4229,"<"&G$4,Canon!$I$2:$I$4229,">="&G$3)+COUNTIFS(Canon!$G$2:$G$4229,"*"&$A35&"*",Canon!$H$2:$H$4229,"<"&G$4,Canon!$I$2:$I$4229,"") -> 72 | H35: =COUNTIFS(Canon!$G$2:$G$4229,"*"&$A35&"*",Canon!$H$2:$H$4229,"<"&H$4,Canon!$I$2:$I$4229,">="&H$3)+COUNTIFS(Canon!$G$2:$G$4229,"*"&$A35&"*",Canon!$H$2:$H$4229,"<"&H$4,Canon!$I$2:$I$4229,"") -> 55 | I35: =COUNTIFS(Canon!$G$2:$G$4229,"*"&$A35&"*",Canon!$H$2:$H$4229,"<"&I$4,Canon!$I$2:$I$4229,">="&I$3)+COUNTIFS(Canon!$G$2:$G$4229,"*"&$A35&"*",Canon!$H$2:$H$4229,"<"&I$4,Canon!$I$2:$I$4229,"") -> 81 | J35: =COUNTIFS(Canon!$G$2:$G$4229,"*"&$A35&"*",Canon!$H$2:$H$4229,"<"&J$4,Canon!$I$2:$I$4229,">="&J$3)+COUNTIFS(Canon!$G$2:$G$4229,"*"&$A35&"*",Canon!$H$2:$H$4229,"<"&J$4,Canon!$I$2:$I$4229,"") -> 83 | ... M35: =COUNTIFS(Canon!$G$2:$G$4229,"*"&$A35&"*",Canon!$H$2:$H$4229,"<"&M$4,Canon!$I$2:$I$4229,">="&M$3)+COUNTIFS(Canon!$G$2:$G$4229,"*"&$A35&"*",Canon!$H$2:$H$4229,"<"&M$4,Canon!$I$2:$I$4229,"") -> 83
A36: WA-IRN | B36: Iran | C36: =COUNTIFS(Canon!$G$2:$G$4229,"*"&$A36&"*",Canon!$H$2:$H$4229,"<"&C$4,Canon!$I$2:$I$4229,">="&C$3)+COUNTIFS(Canon!$G$2:$G$4229,"*"&$A36&"*",Canon!$H$2:$H$4229,"<"&C$4,Canon!$I$2:$I$4229,"") -> 2 | D36: =COUNTIFS(Canon!$G$2:$G$4229,"*"&$A36&"*",Canon!$H$2:$H$4229,"<"&D$4,Canon!$I$2:$I$4229,">="&D$3)+COUNTIFS(Canon!$G$2:$G$4229,"*"&$A36&"*",Canon!$H$2:$H$4229,"<"&D$4,Canon!$I$2:$I$4229,"") -> 10 | E36: =COUNTIFS(Canon!$G$2:$G$4229,"*"&$A36&"*",Canon!$H$2:$H$4229,"<"&E$4,Canon!$I$2:$I$4229,">="&E$3)+COUNTIFS(Canon!$G$2:$G$4229,"*"&$A36&"*",Canon!$H$2:$H$4229,"<"&E$4,Canon!$I$2:$I$4229,"") -> 38 | F36: =COUNTIFS(Canon!$G$2:$G$4229,"*"&$A36&"*",Canon!$H$2:$H$4229,"<"&F$4,Canon!$I$2:$I$4229,">="&F$3)+COUNTIFS(Canon!$G$2:$G$4229,"*"&$A36&"*",Canon!$H$2:$H$4229,"<"&F$4,Canon!$I$2:$I$4229,"") -> 34 | G36: =COUNTIFS(Canon!$G$2:$G$4229,"*"&$A36&"*",Canon!$H$2:$H$4229,"<"&G$4,Canon!$I$2:$I$4229,">="&G$3)+COUNTIFS(Canon!$G$2:$G$4229,"*"&$A36&"*",Canon!$H$2:$H$4229,"<"&G$4,Canon!$I$2:$I$4229,"") -> 61 | H36: =COUNTIFS(Canon!$G$2:$G$4229,"*"&$A36&"*",Canon!$H$2:$H$4229,"<"&H$4,Canon!$I$2:$I$4229,">="&H$3)+COUNTIFS(Canon!$G$2:$G$4229,"*"&$A36&"*",Canon!$H$2:$H$4229,"<"&H$4,Canon!$I$2:$I$4229,"") -> 50 | I36: =COUNTIFS(Canon!$G$2:$G$4229,"*"&$A36&"*",Canon!$H$2:$H$4229,"<"&I$4,Canon!$I$2:$I$4229,">="&I$3)+COUNTIFS(Canon!$G$2:$G$4229,"*"&$A36&"*",Canon!$H$2:$H$4229,"<"&I$4,Canon!$I$2:$I$4229,"") -> 72 | J36: =COUNTIFS(Canon!$G$2:$G$4229,"*"&$A36&"*",Canon!$H$2:$H$4229,"<"&J$4,Canon!$I$2:$I$4229,">="&J$3)+COUNTIFS(Canon!$G$2:$G$4229,"*"&$A36&"*",Canon!$H$2:$H$4229,"<"&J$4,Canon!$I$2:$I$4229,"") -> 98 | ... M36: =COUNTIFS(Canon!$G$2:$G$4229,"*"&$A36&"*",Canon!$H$2:$H$4229,"<"&M$4,Canon!$I$2:$I$4229,">="&M$3)+COUNTIFS(Canon!$G$2:$G$4229,"*"&$A36&"*",Canon!$H$2:$H$4229,"<"&M$4,Canon!$I$2:$I$4229,"") -> 84
A37: WA-LEV | B37: Levant | C37: =COUNTIFS(Canon!$G$2:$G$4229,"*"&$A37&"*",Canon!$H$2:$H$4229,"<"&C$4,Canon!$I$2:$I$4229,">="&C$3)+COUNTIFS(Canon!$G$2:$G$4229,"*"&$A37&"*",Canon!$H$2:$H$4229,"<"&C$4,Canon!$I$2:$I$4229,"") -> 19 | D37: =COUNTIFS(Canon!$G$2:$G$4229,"*"&$A37&"*",Canon!$H$2:$H$4229,"<"&D$4,Canon!$I$2:$I$4229,">="&D$3)+COUNTIFS(Canon!$G$2:$G$4229,"*"&$A37&"*",Canon!$H$2:$H$4229,"<"&D$4,Canon!$I$2:$I$4229,"") -> 27 | E37: =COUNTIFS(Canon!$G$2:$G$4229,"*"&$A37&"*",Canon!$H$2:$H$4229,"<"&E$4,Canon!$I$2:$I$4229,">="&E$3)+COUNTIFS(Canon!$G$2:$G$4229,"*"&$A37&"*",Canon!$H$2:$H$4229,"<"&E$4,Canon!$I$2:$I$4229,"") -> 38 | F37: =COUNTIFS(Canon!$G$2:$G$4229,"*"&$A37&"*",Canon!$H$2:$H$4229,"<"&F$4,Canon!$I$2:$I$4229,">="&F$3)+COUNTIFS(Canon!$G$2:$G$4229,"*"&$A37&"*",Canon!$H$2:$H$4229,"<"&F$4,Canon!$I$2:$I$4229,"") -> 55 | G37: =COUNTIFS(Canon!$G$2:$G$4229,"*"&$A37&"*",Canon!$H$2:$H$4229,"<"&G$4,Canon!$I$2:$I$4229,">="&G$3)+COUNTIFS(Canon!$G$2:$G$4229,"*"&$A37&"*",Canon!$H$2:$H$4229,"<"&G$4,Canon!$I$2:$I$4229,"") -> 71 | H37: =COUNTIFS(Canon!$G$2:$G$4229,"*"&$A37&"*",Canon!$H$2:$H$4229,"<"&H$4,Canon!$I$2:$I$4229,">="&H$3)+COUNTIFS(Canon!$G$2:$G$4229,"*"&$A37&"*",Canon!$H$2:$H$4229,"<"&H$4,Canon!$I$2:$I$4229,"") -> 66 | I37: =COUNTIFS(Canon!$G$2:$G$4229,"*"&$A37&"*",Canon!$H$2:$H$4229,"<"&I$4,Canon!$I$2:$I$4229,">="&I$3)+COUNTIFS(Canon!$G$2:$G$4229,"*"&$A37&"*",Canon!$H$2:$H$4229,"<"&I$4,Canon!$I$2:$I$4229,"") -> 62 | J37: =COUNTIFS(Canon!$G$2:$G$4229,"*"&$A37&"*",Canon!$H$2:$H$4229,"<"&J$4,Canon!$I$2:$I$4229,">="&J$3)+COUNTIFS(Canon!$G$2:$G$4229,"*"&$A37&"*",Canon!$H$2:$H$4229,"<"&J$4,Canon!$I$2:$I$4229,"") -> 67 | ... M37: =COUNTIFS(Canon!$G$2:$G$4229,"*"&$A37&"*",Canon!$H$2:$H$4229,"<"&M$4,Canon!$I$2:$I$4229,">="&M$3)+COUNTIFS(Canon!$G$2:$G$4229,"*"&$A37&"*",Canon!$H$2:$H$4229,"<"&M$4,Canon!$I$2:$I$4229,"") -> 67
A38: WA-ARB | B38: Arabia and the Gulf | C38: =COUNTIFS(Canon!$G$2:$G$4229,"*"&$A38&"*",Canon!$H$2:$H$4229,"<"&C$4,Canon!$I$2:$I$4229,">="&C$3)+COUNTIFS(Canon!$G$2:$G$4229,"*"&$A38&"*",Canon!$H$2:$H$4229,"<"&C$4,Canon!$I$2:$I$4229,"") -> 1 | D38: =COUNTIFS(Canon!$G$2:$G$4229,"*"&$A38&"*",Canon!$H$2:$H$4229,"<"&D$4,Canon!$I$2:$I$4229,">="&D$3)+COUNTIFS(Canon!$G$2:$G$4229,"*"&$A38&"*",Canon!$H$2:$H$4229,"<"&D$4,Canon!$I$2:$I$4229,"") -> 6 | E38: =COUNTIFS(Canon!$G$2:$G$4229,"*"&$A38&"*",Canon!$H$2:$H$4229,"<"&E$4,Canon!$I$2:$I$4229,">="&E$3)+COUNTIFS(Canon!$G$2:$G$4229,"*"&$A38&"*",Canon!$H$2:$H$4229,"<"&E$4,Canon!$I$2:$I$4229,"") -> 25 | F38: =COUNTIFS(Canon!$G$2:$G$4229,"*"&$A38&"*",Canon!$H$2:$H$4229,"<"&F$4,Canon!$I$2:$I$4229,">="&F$3)+COUNTIFS(Canon!$G$2:$G$4229,"*"&$A38&"*",Canon!$H$2:$H$4229,"<"&F$4,Canon!$I$2:$I$4229,"") -> 25 | G38: =COUNTIFS(Canon!$G$2:$G$4229,"*"&$A38&"*",Canon!$H$2:$H$4229,"<"&G$4,Canon!$I$2:$I$4229,">="&G$3)+COUNTIFS(Canon!$G$2:$G$4229,"*"&$A38&"*",Canon!$H$2:$H$4229,"<"&G$4,Canon!$I$2:$I$4229,"") -> 33 | H38: =COUNTIFS(Canon!$G$2:$G$4229,"*"&$A38&"*",Canon!$H$2:$H$4229,"<"&H$4,Canon!$I$2:$I$4229,">="&H$3)+COUNTIFS(Canon!$G$2:$G$4229,"*"&$A38&"*",Canon!$H$2:$H$4229,"<"&H$4,Canon!$I$2:$I$4229,"") -> 32 | I38: =COUNTIFS(Canon!$G$2:$G$4229,"*"&$A38&"*",Canon!$H$2:$H$4229,"<"&I$4,Canon!$I$2:$I$4229,">="&I$3)+COUNTIFS(Canon!$G$2:$G$4229,"*"&$A38&"*",Canon!$H$2:$H$4229,"<"&I$4,Canon!$I$2:$I$4229,"") -> 40 | J38: =COUNTIFS(Canon!$G$2:$G$4229,"*"&$A38&"*",Canon!$H$2:$H$4229,"<"&J$4,Canon!$I$2:$I$4229,">="&J$3)+COUNTIFS(Canon!$G$2:$G$4229,"*"&$A38&"*",Canon!$H$2:$H$4229,"<"&J$4,Canon!$I$2:$I$4229,"") -> 42 | ... M38: =COUNTIFS(Canon!$G$2:$G$4229,"*"&$A38&"*",Canon!$H$2:$H$4229,"<"&M$4,Canon!$I$2:$I$4229,">="&M$3)+COUNTIFS(Canon!$G$2:$G$4229,"*"&$A38&"*",Canon!$H$2:$H$4229,"<"&M$4,Canon!$I$2:$I$4229,"") -> 51
A39: WA-ANA | B39: Anatolia | C39: =COUNTIFS(Canon!$G$2:$G$4229,"*"&$A39&"*",Canon!$H$2:$H$4229,"<"&C$4,Canon!$I$2:$I$4229,">="&C$3)+COUNTIFS(Canon!$G$2:$G$4229,"*"&$A39&"*",Canon!$H$2:$H$4229,"<"&C$4,Canon!$I$2:$I$4229,"") -> 11 | D39: =COUNTIFS(Canon!$G$2:$G$4229,"*"&$A39&"*",Canon!$H$2:$H$4229,"<"&D$4,Canon!$I$2:$I$4229,">="&D$3)+COUNTIFS(Canon!$G$2:$G$4229,"*"&$A39&"*",Canon!$H$2:$H$4229,"<"&D$4,Canon!$I$2:$I$4229,"") -> 23 | E39: =COUNTIFS(Canon!$G$2:$G$4229,"*"&$A39&"*",Canon!$H$2:$H$4229,"<"&E$4,Canon!$I$2:$I$4229,">="&E$3)+COUNTIFS(Canon!$G$2:$G$4229,"*"&$A39&"*",Canon!$H$2:$H$4229,"<"&E$4,Canon!$I$2:$I$4229,"") -> 29 | F39: =COUNTIFS(Canon!$G$2:$G$4229,"*"&$A39&"*",Canon!$H$2:$H$4229,"<"&F$4,Canon!$I$2:$I$4229,">="&F$3)+COUNTIFS(Canon!$G$2:$G$4229,"*"&$A39&"*",Canon!$H$2:$H$4229,"<"&F$4,Canon!$I$2:$I$4229,"") -> 45 | G39: =COUNTIFS(Canon!$G$2:$G$4229,"*"&$A39&"*",Canon!$H$2:$H$4229,"<"&G$4,Canon!$I$2:$I$4229,">="&G$3)+COUNTIFS(Canon!$G$2:$G$4229,"*"&$A39&"*",Canon!$H$2:$H$4229,"<"&G$4,Canon!$I$2:$I$4229,"") -> 56 | H39: =COUNTIFS(Canon!$G$2:$G$4229,"*"&$A39&"*",Canon!$H$2:$H$4229,"<"&H$4,Canon!$I$2:$I$4229,">="&H$3)+COUNTIFS(Canon!$G$2:$G$4229,"*"&$A39&"*",Canon!$H$2:$H$4229,"<"&H$4,Canon!$I$2:$I$4229,"") -> 52 | I39: =COUNTIFS(Canon!$G$2:$G$4229,"*"&$A39&"*",Canon!$H$2:$H$4229,"<"&I$4,Canon!$I$2:$I$4229,">="&I$3)+COUNTIFS(Canon!$G$2:$G$4229,"*"&$A39&"*",Canon!$H$2:$H$4229,"<"&I$4,Canon!$I$2:$I$4229,"") -> 54 | J39: =COUNTIFS(Canon!$G$2:$G$4229,"*"&$A39&"*",Canon!$H$2:$H$4229,"<"&J$4,Canon!$I$2:$I$4229,">="&J$3)+COUNTIFS(Canon!$G$2:$G$4229,"*"&$A39&"*",Canon!$H$2:$H$4229,"<"&J$4,Canon!$I$2:$I$4229,"") -> 76 | ... M39: =COUNTIFS(Canon!$G$2:$G$4229,"*"&$A39&"*",Canon!$H$2:$H$4229,"<"&M$4,Canon!$I$2:$I$4229,">="&M$3)+COUNTIFS(Canon!$G$2:$G$4229,"*"&$A39&"*",Canon!$H$2:$H$4229,"<"&M$4,Canon!$I$2:$I$4229,"") -> 70
A40: WA-CAU | B40: Caucasus | C40: =COUNTIFS(Canon!$G$2:$G$4229,"*"&$A40&"*",Canon!$H$2:$H$4229,"<"&C$4,Canon!$I$2:$I$4229,">="&C$3)+COUNTIFS(Canon!$G$2:$G$4229,"*"&$A40&"*",Canon!$H$2:$H$4229,"<"&C$4,Canon!$I$2:$I$4229,"") -> 9 | D40: =COUNTIFS(Canon!$G$2:$G$4229,"*"&$A40&"*",Canon!$H$2:$H$4229,"<"&D$4,Canon!$I$2:$I$4229,">="&D$3)+COUNTIFS(Canon!$G$2:$G$4229,"*"&$A40&"*",Canon!$H$2:$H$4229,"<"&D$4,Canon!$I$2:$I$4229,"") -> 12 | E40: =COUNTIFS(Canon!$G$2:$G$4229,"*"&$A40&"*",Canon!$H$2:$H$4229,"<"&E$4,Canon!$I$2:$I$4229,">="&E$3)+COUNTIFS(Canon!$G$2:$G$4229,"*"&$A40&"*",Canon!$H$2:$H$4229,"<"&E$4,Canon!$I$2:$I$4229,"") -> 18 | F40: =COUNTIFS(Canon!$G$2:$G$4229,"*"&$A40&"*",Canon!$H$2:$H$4229,"<"&F$4,Canon!$I$2:$I$4229,">="&F$3)+COUNTIFS(Canon!$G$2:$G$4229,"*"&$A40&"*",Canon!$H$2:$H$4229,"<"&F$4,Canon!$I$2:$I$4229,"") -> 19 | G40: =COUNTIFS(Canon!$G$2:$G$4229,"*"&$A40&"*",Canon!$H$2:$H$4229,"<"&G$4,Canon!$I$2:$I$4229,">="&G$3)+COUNTIFS(Canon!$G$2:$G$4229,"*"&$A40&"*",Canon!$H$2:$H$4229,"<"&G$4,Canon!$I$2:$I$4229,"") -> 26 | H40: =COUNTIFS(Canon!$G$2:$G$4229,"*"&$A40&"*",Canon!$H$2:$H$4229,"<"&H$4,Canon!$I$2:$I$4229,">="&H$3)+COUNTIFS(Canon!$G$2:$G$4229,"*"&$A40&"*",Canon!$H$2:$H$4229,"<"&H$4,Canon!$I$2:$I$4229,"") -> 22 | I40: =COUNTIFS(Canon!$G$2:$G$4229,"*"&$A40&"*",Canon!$H$2:$H$4229,"<"&I$4,Canon!$I$2:$I$4229,">="&I$3)+COUNTIFS(Canon!$G$2:$G$4229,"*"&$A40&"*",Canon!$H$2:$H$4229,"<"&I$4,Canon!$I$2:$I$4229,"") -> 23 | J40: =COUNTIFS(Canon!$G$2:$G$4229,"*"&$A40&"*",Canon!$H$2:$H$4229,"<"&J$4,Canon!$I$2:$I$4229,">="&J$3)+COUNTIFS(Canon!$G$2:$G$4229,"*"&$A40&"*",Canon!$H$2:$H$4229,"<"&J$4,Canon!$I$2:$I$4229,"") -> 32 | ... M40: =COUNTIFS(Canon!$G$2:$G$4229,"*"&$A40&"*",Canon!$H$2:$H$4229,"<"&M$4,Canon!$I$2:$I$4229,">="&M$3)+COUNTIFS(Canon!$G$2:$G$4229,"*"&$A40&"*",Canon!$H$2:$H$4229,"<"&M$4,Canon!$I$2:$I$4229,"") -> 35
A41: EU-GRR | B41: Greek and Roman Mediterranean | C41: =COUNTIFS(Canon!$G$2:$G$4229,"*"&$A41&"*",Canon!$H$2:$H$4229,"<"&C$4,Canon!$I$2:$I$4229,">="&C$3)+COUNTIFS(Canon!$G$2:$G$4229,"*"&$A41&"*",Canon!$H$2:$H$4229,"<"&C$4,Canon!$I$2:$I$4229,"") -> 1 | D41: =COUNTIFS(Canon!$G$2:$G$4229,"*"&$A41&"*",Canon!$H$2:$H$4229,"<"&D$4,Canon!$I$2:$I$4229,">="&D$3)+COUNTIFS(Canon!$G$2:$G$4229,"*"&$A41&"*",Canon!$H$2:$H$4229,"<"&D$4,Canon!$I$2:$I$4229,"") -> 6 | E41: =COUNTIFS(Canon!$G$2:$G$4229,"*"&$A41&"*",Canon!$H$2:$H$4229,"<"&E$4,Canon!$I$2:$I$4229,">="&E$3)+COUNTIFS(Canon!$G$2:$G$4229,"*"&$A41&"*",Canon!$H$2:$H$4229,"<"&E$4,Canon!$I$2:$I$4229,"") -> 22 | F41: =COUNTIFS(Canon!$G$2:$G$4229,"*"&$A41&"*",Canon!$H$2:$H$4229,"<"&F$4,Canon!$I$2:$I$4229,">="&F$3)+COUNTIFS(Canon!$G$2:$G$4229,"*"&$A41&"*",Canon!$H$2:$H$4229,"<"&F$4,Canon!$I$2:$I$4229,"") -> 53 | G41: =COUNTIFS(Canon!$G$2:$G$4229,"*"&$A41&"*",Canon!$H$2:$H$4229,"<"&G$4,Canon!$I$2:$I$4229,">="&G$3)+COUNTIFS(Canon!$G$2:$G$4229,"*"&$A41&"*",Canon!$H$2:$H$4229,"<"&G$4,Canon!$I$2:$I$4229,"") -> 101 | H41: =COUNTIFS(Canon!$G$2:$G$4229,"*"&$A41&"*",Canon!$H$2:$H$4229,"<"&H$4,Canon!$I$2:$I$4229,">="&H$3)+COUNTIFS(Canon!$G$2:$G$4229,"*"&$A41&"*",Canon!$H$2:$H$4229,"<"&H$4,Canon!$I$2:$I$4229,"") -> 74 | I41: =COUNTIFS(Canon!$G$2:$G$4229,"*"&$A41&"*",Canon!$H$2:$H$4229,"<"&I$4,Canon!$I$2:$I$4229,">="&I$3)+COUNTIFS(Canon!$G$2:$G$4229,"*"&$A41&"*",Canon!$H$2:$H$4229,"<"&I$4,Canon!$I$2:$I$4229,"") -> 58 | J41: =COUNTIFS(Canon!$G$2:$G$4229,"*"&$A41&"*",Canon!$H$2:$H$4229,"<"&J$4,Canon!$I$2:$I$4229,">="&J$3)+COUNTIFS(Canon!$G$2:$G$4229,"*"&$A41&"*",Canon!$H$2:$H$4229,"<"&J$4,Canon!$I$2:$I$4229,"") -> 64 | ... M41: =COUNTIFS(Canon!$G$2:$G$4229,"*"&$A41&"*",Canon!$H$2:$H$4229,"<"&M$4,Canon!$I$2:$I$4229,">="&M$3)+COUNTIFS(Canon!$G$2:$G$4229,"*"&$A41&"*",Canon!$H$2:$H$4229,"<"&M$4,Canon!$I$2:$I$4229,"") -> 56
A42: EU-BYZ | B42: Byzantium and the Balkans | C42: =COUNTIFS(Canon!$G$2:$G$4229,"*"&$A42&"*",Canon!$H$2:$H$4229,"<"&C$4,Canon!$I$2:$I$4229,">="&C$3)+COUNTIFS(Canon!$G$2:$G$4229,"*"&$A42&"*",Canon!$H$2:$H$4229,"<"&C$4,Canon!$I$2:$I$4229,"") -> 3 | D42: =COUNTIFS(Canon!$G$2:$G$4229,"*"&$A42&"*",Canon!$H$2:$H$4229,"<"&D$4,Canon!$I$2:$I$4229,">="&D$3)+COUNTIFS(Canon!$G$2:$G$4229,"*"&$A42&"*",Canon!$H$2:$H$4229,"<"&D$4,Canon!$I$2:$I$4229,"") -> 16 | E42: =COUNTIFS(Canon!$G$2:$G$4229,"*"&$A42&"*",Canon!$H$2:$H$4229,"<"&E$4,Canon!$I$2:$I$4229,">="&E$3)+COUNTIFS(Canon!$G$2:$G$4229,"*"&$A42&"*",Canon!$H$2:$H$4229,"<"&E$4,Canon!$I$2:$I$4229,"") -> 13 | F42: =COUNTIFS(Canon!$G$2:$G$4229,"*"&$A42&"*",Canon!$H$2:$H$4229,"<"&F$4,Canon!$I$2:$I$4229,">="&F$3)+COUNTIFS(Canon!$G$2:$G$4229,"*"&$A42&"*",Canon!$H$2:$H$4229,"<"&F$4,Canon!$I$2:$I$4229,"") -> 13 | G42: =COUNTIFS(Canon!$G$2:$G$4229,"*"&$A42&"*",Canon!$H$2:$H$4229,"<"&G$4,Canon!$I$2:$I$4229,">="&G$3)+COUNTIFS(Canon!$G$2:$G$4229,"*"&$A42&"*",Canon!$H$2:$H$4229,"<"&G$4,Canon!$I$2:$I$4229,"") -> 18 | H42: =COUNTIFS(Canon!$G$2:$G$4229,"*"&$A42&"*",Canon!$H$2:$H$4229,"<"&H$4,Canon!$I$2:$I$4229,">="&H$3)+COUNTIFS(Canon!$G$2:$G$4229,"*"&$A42&"*",Canon!$H$2:$H$4229,"<"&H$4,Canon!$I$2:$I$4229,"") -> 24 | I42: =COUNTIFS(Canon!$G$2:$G$4229,"*"&$A42&"*",Canon!$H$2:$H$4229,"<"&I$4,Canon!$I$2:$I$4229,">="&I$3)+COUNTIFS(Canon!$G$2:$G$4229,"*"&$A42&"*",Canon!$H$2:$H$4229,"<"&I$4,Canon!$I$2:$I$4229,"") -> 37 | J42: =COUNTIFS(Canon!$G$2:$G$4229,"*"&$A42&"*",Canon!$H$2:$H$4229,"<"&J$4,Canon!$I$2:$I$4229,">="&J$3)+COUNTIFS(Canon!$G$2:$G$4229,"*"&$A42&"*",Canon!$H$2:$H$4229,"<"&J$4,Canon!$I$2:$I$4229,"") -> 40 | ... M42: =COUNTIFS(Canon!$G$2:$G$4229,"*"&$A42&"*",Canon!$H$2:$H$4229,"<"&M$4,Canon!$I$2:$I$4229,">="&M$3)+COUNTIFS(Canon!$G$2:$G$4229,"*"&$A42&"*",Canon!$H$2:$H$4229,"<"&M$4,Canon!$I$2:$I$4229,"") -> 31
... A49: OC-MEL | B49: Melanesia | C49: =COUNTIFS(Canon!$G$2:$G$4229,"*"&$A49&"*",Canon!$H$2:$H$4229,"<"&C$4,Canon!$I$2:$I$4229,">="&C$3)+COUNTIFS(Canon!$G$2:$G$4229,"*"&$A49&"*",Canon!$H$2:$H$4229,"<"&C$4,Canon!$I$2:$I$4229,"") -> 4 | D49: =COUNTIFS(Canon!$G$2:$G$4229,"*"&$A49&"*",Canon!$H$2:$H$4229,"<"&D$4,Canon!$I$2:$I$4229,">="&D$3)+COUNTIFS(Canon!$G$2:$G$4229,"*"&$A49&"*",Canon!$H$2:$H$4229,"<"&D$4,Canon!$I$2:$I$4229,"") -> 7 | E49: =COUNTIFS(Canon!$G$2:$G$4229,"*"&$A49&"*",Canon!$H$2:$H$4229,"<"&E$4,Canon!$I$2:$I$4229,">="&E$3)+COUNTIFS(Canon!$G$2:$G$4229,"*"&$A49&"*",Canon!$H$2:$H$4229,"<"&E$4,Canon!$I$2:$I$4229,"") -> 10 | F49: =COUNTIFS(Canon!$G$2:$G$4229,"*"&$A49&"*",Canon!$H$2:$H$4229,"<"&F$4,Canon!$I$2:$I$4229,">="&F$3)+COUNTIFS(Canon!$G$2:$G$4229,"*"&$A49&"*",Canon!$H$2:$H$4229,"<"&F$4,Canon!$I$2:$I$4229,"") -> 18 | G49: =COUNTIFS(Canon!$G$2:$G$4229,"*"&$A49&"*",Canon!$H$2:$H$4229,"<"&G$4,Canon!$I$2:$I$4229,">="&G$3)+COUNTIFS(Canon!$G$2:$G$4229,"*"&$A49&"*",Canon!$H$2:$H$4229,"<"&G$4,Canon!$I$2:$I$4229,"") -> 23 | H49: =COUNTIFS(Canon!$G$2:$G$4229,"*"&$A49&"*",Canon!$H$2:$H$4229,"<"&H$4,Canon!$I$2:$I$4229,">="&H$3)+COUNTIFS(Canon!$G$2:$G$4229,"*"&$A49&"*",Canon!$H$2:$H$4229,"<"&H$4,Canon!$I$2:$I$4229,"") -> 15 | I49: =COUNTIFS(Canon!$G$2:$G$4229,"*"&$A49&"*",Canon!$H$2:$H$4229,"<"&I$4,Canon!$I$2:$I$4229,">="&I$3)+COUNTIFS(Canon!$G$2:$G$4229,"*"&$A49&"*",Canon!$H$2:$H$4229,"<"&I$4,Canon!$I$2:$I$4229,"") -> 16 | J49: =COUNTIFS(Canon!$G$2:$G$4229,"*"&$A49&"*",Canon!$H$2:$H$4229,"<"&J$4,Canon!$I$2:$I$4229,">="&J$3)+COUNTIFS(Canon!$G$2:$G$4229,"*"&$A49&"*",Canon!$H$2:$H$4229,"<"&J$4,Canon!$I$2:$I$4229,"") -> 16 | ... M49: =COUNTIFS(Canon!$G$2:$G$4229,"*"&$A49&"*",Canon!$H$2:$H$4229,"<"&M$4,Canon!$I$2:$I$4229,">="&M$3)+COUNTIFS(Canon!$G$2:$G$4229,"*"&$A49&"*",Canon!$H$2:$H$4229,"<"&M$4,Canon!$I$2:$I$4229,"") -> 43
A50: OC-MIC | B50: Micronesia | C50: =COUNTIFS(Canon!$G$2:$G$4229,"*"&$A50&"*",Canon!$H$2:$H$4229,"<"&C$4,Canon!$I$2:$I$4229,">="&C$3)+COUNTIFS(Canon!$G$2:$G$4229,"*"&$A50&"*",Canon!$H$2:$H$4229,"<"&C$4,Canon!$I$2:$I$4229,"") -> 0 | D50: =COUNTIFS(Canon!$G$2:$G$4229,"*"&$A50&"*",Canon!$H$2:$H$4229,"<"&D$4,Canon!$I$2:$I$4229,">="&D$3)+COUNTIFS(Canon!$G$2:$G$4229,"*"&$A50&"*",Canon!$H$2:$H$4229,"<"&D$4,Canon!$I$2:$I$4229,"") -> 0 | E50: =COUNTIFS(Canon!$G$2:$G$4229,"*"&$A50&"*",Canon!$H$2:$H$4229,"<"&E$4,Canon!$I$2:$I$4229,">="&E$3)+COUNTIFS(Canon!$G$2:$G$4229,"*"&$A50&"*",Canon!$H$2:$H$4229,"<"&E$4,Canon!$I$2:$I$4229,"") -> 2 | F50: =COUNTIFS(Canon!$G$2:$G$4229,"*"&$A50&"*",Canon!$H$2:$H$4229,"<"&F$4,Canon!$I$2:$I$4229,">="&F$3)+COUNTIFS(Canon!$G$2:$G$4229,"*"&$A50&"*",Canon!$H$2:$H$4229,"<"&F$4,Canon!$I$2:$I$4229,"") -> 4 | G50: =COUNTIFS(Canon!$G$2:$G$4229,"*"&$A50&"*",Canon!$H$2:$H$4229,"<"&G$4,Canon!$I$2:$I$4229,">="&G$3)+COUNTIFS(Canon!$G$2:$G$4229,"*"&$A50&"*",Canon!$H$2:$H$4229,"<"&G$4,Canon!$I$2:$I$4229,"") -> 7 | H50: =COUNTIFS(Canon!$G$2:$G$4229,"*"&$A50&"*",Canon!$H$2:$H$4229,"<"&H$4,Canon!$I$2:$I$4229,">="&H$3)+COUNTIFS(Canon!$G$2:$G$4229,"*"&$A50&"*",Canon!$H$2:$H$4229,"<"&H$4,Canon!$I$2:$I$4229,"") -> 7 | I50: =COUNTIFS(Canon!$G$2:$G$4229,"*"&$A50&"*",Canon!$H$2:$H$4229,"<"&I$4,Canon!$I$2:$I$4229,">="&I$3)+COUNTIFS(Canon!$G$2:$G$4229,"*"&$A50&"*",Canon!$H$2:$H$4229,"<"&I$4,Canon!$I$2:$I$4229,"") -> 9 | J50: =COUNTIFS(Canon!$G$2:$G$4229,"*"&$A50&"*",Canon!$H$2:$H$4229,"<"&J$4,Canon!$I$2:$I$4229,">="&J$3)+COUNTIFS(Canon!$G$2:$G$4229,"*"&$A50&"*",Canon!$H$2:$H$4229,"<"&J$4,Canon!$I$2:$I$4229,"") -> 17 | ... M50: =COUNTIFS(Canon!$G$2:$G$4229,"*"&$A50&"*",Canon!$H$2:$H$4229,"<"&M$4,Canon!$I$2:$I$4229,">="&M$3)+COUNTIFS(Canon!$G$2:$G$4229,"*"&$A50&"*",Canon!$H$2:$H$4229,"<"&M$4,Canon!$I$2:$I$4229,"") -> 17 | N50: B01–B02: Micronesia settled c. 1500 BCE; no people yet
A51: OC-POL | B51: Polynesia | C51: =COUNTIFS(Canon!$G$2:$G$4229,"*"&$A51&"*",Canon!$H$2:$H$4229,"<"&C$4,Canon!$I$2:$I$4229,">="&C$3)+COUNTIFS(Canon!$G$2:$G$4229,"*"&$A51&"*",Canon!$H$2:$H$4229,"<"&C$4,Canon!$I$2:$I$4229,"") -> 3 | D51: =COUNTIFS(Canon!$G$2:$G$4229,"*"&$A51&"*",Canon!$H$2:$H$4229,"<"&D$4,Canon!$I$2:$I$4229,">="&D$3)+COUNTIFS(Canon!$G$2:$G$4229,"*"&$A51&"*",Canon!$H$2:$H$4229,"<"&D$4,Canon!$I$2:$I$4229,"") -> 6 | E51: =COUNTIFS(Canon!$G$2:$G$4229,"*"&$A51&"*",Canon!$H$2:$H$4229,"<"&E$4,Canon!$I$2:$I$4229,">="&E$3)+COUNTIFS(Canon!$G$2:$G$4229,"*"&$A51&"*",Canon!$H$2:$H$4229,"<"&E$4,Canon!$I$2:$I$4229,"") -> 10 | F51: =COUNTIFS(Canon!$G$2:$G$4229,"*"&$A51&"*",Canon!$H$2:$H$4229,"<"&F$4,Canon!$I$2:$I$4229,">="&F$3)+COUNTIFS(Canon!$G$2:$G$4229,"*"&$A51&"*",Canon!$H$2:$H$4229,"<"&F$4,Canon!$I$2:$I$4229,"") -> 17 | G51: =COUNTIFS(Canon!$G$2:$G$4229,"*"&$A51&"*",Canon!$H$2:$H$4229,"<"&G$4,Canon!$I$2:$I$4229,">="&G$3)+COUNTIFS(Canon!$G$2:$G$4229,"*"&$A51&"*",Canon!$H$2:$H$4229,"<"&G$4,Canon!$I$2:$I$4229,"") -> 26 | H51: =COUNTIFS(Canon!$G$2:$G$4229,"*"&$A51&"*",Canon!$H$2:$H$4229,"<"&H$4,Canon!$I$2:$I$4229,">="&H$3)+COUNTIFS(Canon!$G$2:$G$4229,"*"&$A51&"*",Canon!$H$2:$H$4229,"<"&H$4,Canon!$I$2:$I$4229,"") -> 19 | I51: =COUNTIFS(Canon!$G$2:$G$4229,"*"&$A51&"*",Canon!$H$2:$H$4229,"<"&I$4,Canon!$I$2:$I$4229,">="&I$3)+COUNTIFS(Canon!$G$2:$G$4229,"*"&$A51&"*",Canon!$H$2:$H$4229,"<"&I$4,Canon!$I$2:$I$4229,"") -> 19 | J51: =COUNTIFS(Canon!$G$2:$G$4229,"*"&$A51&"*",Canon!$H$2:$H$4229,"<"&J$4,Canon!$I$2:$I$4229,">="&J$3)+COUNTIFS(Canon!$G$2:$G$4229,"*"&$A51&"*",Canon!$H$2:$H$4229,"<"&J$4,Canon!$I$2:$I$4229,"") -> 44 | ... M51: =COUNTIFS(Canon!$G$2:$G$4229,"*"&$A51&"*",Canon!$H$2:$H$4229,"<"&M$4,Canon!$I$2:$I$4229,">="&M$3)+COUNTIFS(Canon!$G$2:$G$4229,"*"&$A51&"*",Canon!$H$2:$H$4229,"<"&M$4,Canon!$I$2:$I$4229,"") -> 69
B53: Empty cells | C53: =COUNTIF(C6:M51,0) -> 6
B54: Thin cells (1–2) | C54: =COUNTIFS(C6:M51,">0",C6:M51,"<3") -> 13

Sheet Functions x worlds
A1: Object types per function and world (formulas on Canon; a type can serve several functions and worlds)
A2: Function | B2: F1.6 | C2: F1.7 | D2: F1.8 | E2: F1.9 | F2: F1.9a | G2: F1.10 | H2: F1.11 | I2: F1.12 | J2: F1.12a | K2: F1.13 | L2: THEME | M2: All
A3: shelter | B3: =SUMPRODUCT((Canon!$D$2:$D$4229="object-type")*ISNUMBER(SEARCH(";F1.6;",";"&SUBSTITUTE(Canon!$F$2:$F$4229," ","")&";"))*ISNUMBER(SEARCH("shelter",Canon!$N$2:$N$4229))) -> 9 | C3: =SUMPRODUCT((Canon!$D$2:$D$4229="object-type")*ISNUMBER(SEARCH(";F1.7;",";"&SUBSTITUTE(Canon!$F$2:$F$4229," ","")&";"))*ISNUMBER(SEARCH("shelter",Canon!$N$2:$N$4229))) -> 11 | D3: =SUMPRODUCT((Canon!$D$2:$D$4229="object-type")*ISNUMBER(SEARCH(";F1.8;",";"&SUBSTITUTE(Canon!$F$2:$F$4229," ","")&";"))*ISNUMBER(SEARCH("shelter",Canon!$N$2:$N$4229))) -> 9 | E3: =SUMPRODUCT((Canon!$D$2:$D$4229="object-type")*ISNUMBER(SEARCH(";F1.9;",";"&SUBSTITUTE(Canon!$F$2:$F$4229," ","")&";"))*ISNUMBER(SEARCH("shelter",Canon!$N$2:$N$4229))) -> 3 | F3: =SUMPRODUCT((Canon!$D$2:$D$4229="object-type")*ISNUMBER(SEARCH(";F1.9a;",";"&SUBSTITUTE(Canon!$F$2:$F$4229," ","")&";"))*ISNUMBER(SEARCH("shelter",Canon!$N$2:$N$4229))) -> 2 | G3: =SUMPRODUCT((Canon!$D$2:$D$4229="object-type")*ISNUMBER(SEARCH(";F1.10;",";"&SUBSTITUTE(Canon!$F$2:$F$4229," ","")&";"))*ISNUMBER(SEARCH("shelter",Canon!$N$2:$N$4229))) -> 9 | H3: =SUMPRODUCT((Canon!$D$2:$D$4229="object-type")*ISNUMBER(SEARCH(";F1.11;",";"&SUBSTITUTE(Canon!$F$2:$F$4229," ","")&";"))*ISNUMBER(SEARCH("shelter",Canon!$N$2:$N$4229))) -> 5 | I3: =SUMPRODUCT((Canon!$D$2:$D$4229="object-type")*ISNUMBER(SEARCH(";F1.12;",";"&SUBSTITUTE(Canon!$F$2:$F$4229," ","")&";"))*ISNUMBER(SEARCH("shelter",Canon!$N$2:$N$4229))) -> 3 | J3: =SUMPRODUCT((Canon!$D$2:$D$4229="object-type")*ISNUMBER(SEARCH(";F1.12a;",";"&SUBSTITUTE(Canon!$F$2:$F$4229," ","")&";"))*ISNUMBER(SEARCH("shelter",Canon!$N$2:$N$4229))) -> 3 | K3: =SUMPRODUCT((Canon!$D$2:$D$4229="object-type")*ISNUMBER(SEARCH(";F1.13;",";"&SUBSTITUTE(Canon!$F$2:$F$4229," ","")&";"))*ISNUMBER(SEARCH("shelter",Canon!$N$2:$N$4229))) -> 1 | L3: =SUMPRODUCT((Canon!$D$2:$D$4229="object-type")*ISNUMBER(SEARCH(";THEME;",";"&SUBSTITUTE(Canon!$F$2:$F$4229," ","")&";"))*ISNUMBER(SEARCH("shelter",Canon!$N$2:$N$4229))) -> 10 | M3: =COUNTIFS(Canon!$D$2:$D$4229,"object-type",Canon!$N$2:$N$4229,"*shelter*") -> 38
A4: clothing and adornment | B4: =SUMPRODUCT((Canon!$D$2:$D$4229="object-type")*ISNUMBER(SEARCH(";F1.6;",";"&SUBSTITUTE(Canon!$F$2:$F$4229," ","")&";"))*ISNUMBER(SEARCH("clothing and adornment",Canon!$N$2:$N$4229))) -> 11 | C4: =SUMPRODUCT((Canon!$D$2:$D$4229="object-type")*ISNUMBER(SEARCH(";F1.7;",";"&SUBSTITUTE(Canon!$F$2:$F$4229," ","")&";"))*ISNUMBER(SEARCH("clothing and adornment",Canon!$N$2:$N$4229))) -> 12 | D4: =SUMPRODUCT((Canon!$D$2:$D$4229="object-type")*ISNUMBER(SEARCH(";F1.8;",";"&SUBSTITUTE(Canon!$F$2:$F$4229," ","")&";"))*ISNUMBER(SEARCH("clothing and adornment",Canon!$N$2:$N$4229))) -> 4 | E4: =SUMPRODUCT((Canon!$D$2:$D$4229="object-type")*ISNUMBER(SEARCH(";F1.9;",";"&SUBSTITUTE(Canon!$F$2:$F$4229," ","")&";"))*ISNUMBER(SEARCH("clothing and adornment",Canon!$N$2:$N$4229))) -> 6 | F4: =SUMPRODUCT((Canon!$D$2:$D$4229="object-type")*ISNUMBER(SEARCH(";F1.9a;",";"&SUBSTITUTE(Canon!$F$2:$F$4229," ","")&";"))*ISNUMBER(SEARCH("clothing and adornment",Canon!$N$2:$N$4229))) -> 0 | G4: =SUMPRODUCT((Canon!$D$2:$D$4229="object-type")*ISNUMBER(SEARCH(";F1.10;",";"&SUBSTITUTE(Canon!$F$2:$F$4229," ","")&";"))*ISNUMBER(SEARCH("clothing and adornment",Canon!$N$2:$N$4229))) -> 6 | H4: =SUMPRODUCT((Canon!$D$2:$D$4229="object-type")*ISNUMBER(SEARCH(";F1.11;",";"&SUBSTITUTE(Canon!$F$2:$F$4229," ","")&";"))*ISNUMBER(SEARCH("clothing and adornment",Canon!$N$2:$N$4229))) -> 3 | I4: =SUMPRODUCT((Canon!$D$2:$D$4229="object-type")*ISNUMBER(SEARCH(";F1.12;",";"&SUBSTITUTE(Canon!$F$2:$F$4229," ","")&";"))*ISNUMBER(SEARCH("clothing and adornment",Canon!$N$2:$N$4229))) -> 4 | J4: =SUMPRODUCT((Canon!$D$2:$D$4229="object-type")*ISNUMBER(SEARCH(";F1.12a;",";"&SUBSTITUTE(Canon!$F$2:$F$4229," ","")&";"))*ISNUMBER(SEARCH("clothing and adornment",Canon!$N$2:$N$4229))) -> 4 | K4: =SUMPRODUCT((Canon!$D$2:$D$4229="object-type")*ISNUMBER(SEARCH(";F1.13;",";"&SUBSTITUTE(Canon!$F$2:$F$4229," ","")&";"))*ISNUMBER(SEARCH("clothing and adornment",Canon!$N$2:$N$4229))) -> 5 | L4: =SUMPRODUCT((Canon!$D$2:$D$4229="object-type")*ISNUMBER(SEARCH(";THEME;",";"&SUBSTITUTE(Canon!$F$2:$F$4229," ","")&";"))*ISNUMBER(SEARCH("clothing and adornment",Canon!$N$2:$N$4229))) -> 18 | M4: =COUNTIFS(Canon!$D$2:$D$4229,"object-type",Canon!$N$2:$N$4229,"*clothing and adornment*") -> 53
A5: food and storage | B5: =SUMPRODUCT((Canon!$D$2:$D$4229="object-type")*ISNUMBER(SEARCH(";F1.6;",";"&SUBSTITUTE(Canon!$F$2:$F$4229," ","")&";"))*ISNUMBER(SEARCH("food and storage",Canon!$N$2:$N$4229))) -> 5 | C5: =SUMPRODUCT((Canon!$D$2:$D$4229="object-type")*ISNUMBER(SEARCH(";F1.7;",";"&SUBSTITUTE(Canon!$F$2:$F$4229," ","")&";"))*ISNUMBER(SEARCH("food and storage",Canon!$N$2:$N$4229))) -> 8 | D5: =SUMPRODUCT((Canon!$D$2:$D$4229="object-type")*ISNUMBER(SEARCH(";F1.8;",";"&SUBSTITUTE(Canon!$F$2:$F$4229," ","")&";"))*ISNUMBER(SEARCH("food and storage",Canon!$N$2:$N$4229))) -> 6 | E5: =SUMPRODUCT((Canon!$D$2:$D$4229="object-type")*ISNUMBER(SEARCH(";F1.9;",";"&SUBSTITUTE(Canon!$F$2:$F$4229," ","")&";"))*ISNUMBER(SEARCH("food and storage",Canon!$N$2:$N$4229))) -> 1 | F5: =SUMPRODUCT((Canon!$D$2:$D$4229="object-type")*ISNUMBER(SEARCH(";F1.9a;",";"&SUBSTITUTE(Canon!$F$2:$F$4229," ","")&";"))*ISNUMBER(SEARCH("food and storage",Canon!$N$2:$N$4229))) -> 1 | G5: =SUMPRODUCT((Canon!$D$2:$D$4229="object-type")*ISNUMBER(SEARCH(";F1.10;",";"&SUBSTITUTE(Canon!$F$2:$F$4229," ","")&";"))*ISNUMBER(SEARCH("food and storage",Canon!$N$2:$N$4229))) -> 3 | H5: =SUMPRODUCT((Canon!$D$2:$D$4229="object-type")*ISNUMBER(SEARCH(";F1.11;",";"&SUBSTITUTE(Canon!$F$2:$F$4229," ","")&";"))*ISNUMBER(SEARCH("food and storage",Canon!$N$2:$N$4229))) -> 4 | I5: =SUMPRODUCT((Canon!$D$2:$D$4229="object-type")*ISNUMBER(SEARCH(";F1.12;",";"&SUBSTITUTE(Canon!$F$2:$F$4229," ","")&";"))*ISNUMBER(SEARCH("food and storage",Canon!$N$2:$N$4229))) -> 4 | J5: =SUMPRODUCT((Canon!$D$2:$D$4229="object-type")*ISNUMBER(SEARCH(";F1.12a;",";"&SUBSTITUTE(Canon!$F$2:$F$4229," ","")&";"))*ISNUMBER(SEARCH("food and storage",Canon!$N$2:$N$4229))) -> 1 | K5: =SUMPRODUCT((Canon!$D$2:$D$4229="object-type")*ISNUMBER(SEARCH(";F1.13;",";"&SUBSTITUTE(Canon!$F$2:$F$4229," ","")&";"))*ISNUMBER(SEARCH("food and storage",Canon!$N$2:$N$4229))) -> 4 | L5: =SUMPRODUCT((Canon!$D$2:$D$4229="object-type")*ISNUMBER(SEARCH(";THEME;",";"&SUBSTITUTE(Canon!$F$2:$F$4229," ","")&";"))*ISNUMBER(SEARCH("food and storage",Canon!$N$2:$N$4229))) -> 15 | M5: =COUNTIFS(Canon!$D$2:$D$4229,"object-type",Canon!$N$2:$N$4229,"*food and storage*") -> 40
A6: tools | B6: =SUMPRODUCT((Canon!$D$2:$D$4229="object-type")*ISNUMBER(SEARCH(";F1.6;",";"&SUBSTITUTE(Canon!$F$2:$F$4229," ","")&";"))*ISNUMBER(SEARCH("tools",Canon!$N$2:$N$4229))) -> 0 | C6: =SUMPRODUCT((Canon!$D$2:$D$4229="object-type")*ISNUMBER(SEARCH(";F1.7;",";"&SUBSTITUTE(Canon!$F$2:$F$4229," ","")&";"))*ISNUMBER(SEARCH("tools",Canon!$N$2:$N$4229))) -> 4 | D6: =SUMPRODUCT((Canon!$D$2:$D$4229="object-type")*ISNUMBER(SEARCH(";F1.8;",";"&SUBSTITUTE(Canon!$F$2:$F$4229," ","")&";"))*ISNUMBER(SEARCH("tools",Canon!$N$2:$N$4229))) -> 5 | E6: =SUMPRODUCT((Canon!$D$2:$D$4229="object-type")*ISNUMBER(SEARCH(";F1.9;",";"&SUBSTITUTE(Canon!$F$2:$F$4229," ","")&";"))*ISNUMBER(SEARCH("tools",Canon!$N$2:$N$4229))) -> 0 | F6: =SUMPRODUCT((Canon!$D$2:$D$4229="object-type")*ISNUMBER(SEARCH(";F1.9a;",";"&SUBSTITUTE(Canon!$F$2:$F$4229," ","")&";"))*ISNUMBER(SEARCH("tools",Canon!$N$2:$N$4229))) -> 0 | G6: =SUMPRODUCT((Canon!$D$2:$D$4229="object-type")*ISNUMBER(SEARCH(";F1.10;",";"&SUBSTITUTE(Canon!$F$2:$F$4229," ","")&";"))*ISNUMBER(SEARCH("tools",Canon!$N$2:$N$4229))) -> 3 | H6: =SUMPRODUCT((Canon!$D$2:$D$4229="object-type")*ISNUMBER(SEARCH(";F1.11;",";"&SUBSTITUTE(Canon!$F$2:$F$4229," ","")&";"))*ISNUMBER(SEARCH("tools",Canon!$N$2:$N$4229))) -> 4 | I6: =SUMPRODUCT((Canon!$D$2:$D$4229="object-type")*ISNUMBER(SEARCH(";F1.12;",";"&SUBSTITUTE(Canon!$F$2:$F$4229," ","")&";"))*ISNUMBER(SEARCH("tools",Canon!$N$2:$N$4229))) -> 2 | J6: =SUMPRODUCT((Canon!$D$2:$D$4229="object-type")*ISNUMBER(SEARCH(";F1.12a;",";"&SUBSTITUTE(Canon!$F$2:$F$4229," ","")&";"))*ISNUMBER(SEARCH("tools",Canon!$N$2:$N$4229))) -> 1 | K6: =SUMPRODUCT((Canon!$D$2:$D$4229="object-type")*ISNUMBER(SEARCH(";F1.13;",";"&SUBSTITUTE(Canon!$F$2:$F$4229," ","")&";"))*ISNUMBER(SEARCH("tools",Canon!$N$2:$N$4229))) -> 1 | L6: =SUMPRODUCT((Canon!$D$2:$D$4229="object-type")*ISNUMBER(SEARCH(";THEME;",";"&SUBSTITUTE(Canon!$F$2:$F$4229," ","")&";"))*ISNUMBER(SEARCH("tools",Canon!$N$2:$N$4229))) -> 35 | M6: =COUNTIFS(Canon!$D$2:$D$4229,"object-type",Canon!$N$2:$N$4229,"*tools*") -> 49
A7: record and writing | B7: =SUMPRODUCT((Canon!$D$2:$D$4229="object-type")*ISNUMBER(SEARCH(";F1.6;",";"&SUBSTITUTE(Canon!$F$2:$F$4229," ","")&";"))*ISNUMBER(SEARCH("record and writing",Canon!$N$2:$N$4229))) -> 7 | C7: =SUMPRODUCT((Canon!$D$2:$D$4229="object-type")*ISNUMBER(SEARCH(";F1.7;",";"&SUBSTITUTE(Canon!$F$2:$F$4229," ","")&";"))*ISNUMBER(SEARCH("record and writing",Canon!$N$2:$N$4229))) -> 5 | D7: =SUMPRODUCT((Canon!$D$2:$D$4229="object-type")*ISNUMBER(SEARCH(";F1.8;",";"&SUBSTITUTE(Canon!$F$2:$F$4229," ","")&";"))*ISNUMBER(SEARCH("record and writing",Canon!$N$2:$N$4229))) -> 6 | E7: =SUMPRODUCT((Canon!$D$2:$D$4229="object-type")*ISNUMBER(SEARCH(";F1.9;",";"&SUBSTITUTE(Canon!$F$2:$F$4229," ","")&";"))*ISNUMBER(SEARCH("record and writing",Canon!$N$2:$N$4229))) -> 3 | F7: =SUMPRODUCT((Canon!$D$2:$D$4229="object-type")*ISNUMBER(SEARCH(";F1.9a;",";"&SUBSTITUTE(Canon!$F$2:$F$4229," ","")&";"))*ISNUMBER(SEARCH("record and writing",Canon!$N$2:$N$4229))) -> 4 | G7: =SUMPRODUCT((Canon!$D$2:$D$4229="object-type")*ISNUMBER(SEARCH(";F1.10;",";"&SUBSTITUTE(Canon!$F$2:$F$4229," ","")&";"))*ISNUMBER(SEARCH("record and writing",Canon!$N$2:$N$4229))) -> 4 | H7: =SUMPRODUCT((Canon!$D$2:$D$4229="object-type")*ISNUMBER(SEARCH(";F1.11;",";"&SUBSTITUTE(Canon!$F$2:$F$4229," ","")&";"))*ISNUMBER(SEARCH("record and writing",Canon!$N$2:$N$4229))) -> 5 | I7: =SUMPRODUCT((Canon!$D$2:$D$4229="object-type")*ISNUMBER(SEARCH(";F1.12;",";"&SUBSTITUTE(Canon!$F$2:$F$4229," ","")&";"))*ISNUMBER(SEARCH("record and writing",Canon!$N$2:$N$4229))) -> 2 | J7: =SUMPRODUCT((Canon!$D$2:$D$4229="object-type")*ISNUMBER(SEARCH(";F1.12a;",";"&SUBSTITUTE(Canon!$F$2:$F$4229," ","")&";"))*ISNUMBER(SEARCH("record and writing",Canon!$N$2:$N$4229))) -> 0 | K7: =SUMPRODUCT((Canon!$D$2:$D$4229="object-type")*ISNUMBER(SEARCH(";F1.13;",";"&SUBSTITUTE(Canon!$F$2:$F$4229," ","")&";"))*ISNUMBER(SEARCH("record and writing",Canon!$N$2:$N$4229))) -> 0 | L7: =SUMPRODUCT((Canon!$D$2:$D$4229="object-type")*ISNUMBER(SEARCH(";THEME;",";"&SUBSTITUTE(Canon!$F$2:$F$4229," ","")&";"))*ISNUMBER(SEARCH("record and writing",Canon!$N$2:$N$4229))) -> 26 | M7: =COUNTIFS(Canon!$D$2:$D$4229,"object-type",Canon!$N$2:$N$4229,"*record and writing*") -> 56
A8: exchange and value | B8: =SUMPRODUCT((Canon!$D$2:$D$4229="object-type")*ISNUMBER(SEARCH(";F1.6;",";"&SUBSTITUTE(Canon!$F$2:$F$4229," ","")&";"))*ISNUMBER(SEARCH("exchange and value",Canon!$N$2:$N$4229))) -> 9 | C8: =SUMPRODUCT((Canon!$D$2:$D$4229="object-type")*ISNUMBER(SEARCH(";F1.7;",";"&SUBSTITUTE(Canon!$F$2:$F$4229," ","")&";"))*ISNUMBER(SEARCH("exchange and value",Canon!$N$2:$N$4229))) -> 7 | D8: =SUMPRODUCT((Canon!$D$2:$D$4229="object-type")*ISNUMBER(SEARCH(";F1.8;",";"&SUBSTITUTE(Canon!$F$2:$F$4229," ","")&";"))*ISNUMBER(SEARCH("exchange and value",Canon!$N$2:$N$4229))) -> 5 | E8: =SUMPRODUCT((Canon!$D$2:$D$4229="object-type")*ISNUMBER(SEARCH(";F1.9;",";"&SUBSTITUTE(Canon!$F$2:$F$4229," ","")&";"))*ISNUMBER(SEARCH("exchange and value",Canon!$N$2:$N$4229))) -> 6 | F8: =SUMPRODUCT((Canon!$D$2:$D$4229="object-type")*ISNUMBER(SEARCH(";F1.9a;",";"&SUBSTITUTE(Canon!$F$2:$F$4229," ","")&";"))*ISNUMBER(SEARCH("exchange and value",Canon!$N$2:$N$4229))) -> 4 | G8: =SUMPRODUCT((Canon!$D$2:$D$4229="object-type")*ISNUMBER(SEARCH(";F1.10;",";"&SUBSTITUTE(Canon!$F$2:$F$4229," ","")&";"))*ISNUMBER(SEARCH("exchange and value",Canon!$N$2:$N$4229))) -> 4 | H8: =SUMPRODUCT((Canon!$D$2:$D$4229="object-type")*ISNUMBER(SEARCH(";F1.11;",";"&SUBSTITUTE(Canon!$F$2:$F$4229," ","")&";"))*ISNUMBER(SEARCH("exchange and value",Canon!$N$2:$N$4229))) -> 1 | I8: =SUMPRODUCT((Canon!$D$2:$D$4229="object-type")*ISNUMBER(SEARCH(";F1.12;",";"&SUBSTITUTE(Canon!$F$2:$F$4229," ","")&";"))*ISNUMBER(SEARCH("exchange and value",Canon!$N$2:$N$4229))) -> 7 | J8: =SUMPRODUCT((Canon!$D$2:$D$4229="object-type")*ISNUMBER(SEARCH(";F1.12a;",";"&SUBSTITUTE(Canon!$F$2:$F$4229," ","")&";"))*ISNUMBER(SEARCH("exchange and value",Canon!$N$2:$N$4229))) -> 2 | K8: =SUMPRODUCT((Canon!$D$2:$D$4229="object-type")*ISNUMBER(SEARCH(";F1.13;",";"&SUBSTITUTE(Canon!$F$2:$F$4229," ","")&";"))*ISNUMBER(SEARCH("exchange and value",Canon!$N$2:$N$4229))) -> 12 | L8: =SUMPRODUCT((Canon!$D$2:$D$4229="object-type")*ISNUMBER(SEARCH(";THEME;",";"&SUBSTITUTE(Canon!$F$2:$F$4229," ","")&";"))*ISNUMBER(SEARCH("exchange and value",Canon!$N$2:$N$4229))) -> 21 | M8: =COUNTIFS(Canon!$D$2:$D$4229,"object-type",Canon!$N$2:$N$4229,"*exchange and value*") -> 58
A9: ritual and belief | B9: =SUMPRODUCT((Canon!$D$2:$D$4229="object-type")*ISNUMBER(SEARCH(";F1.6;",";"&SUBSTITUTE(Canon!$F$2:$F$4229," ","")&";"))*ISNUMBER(SEARCH("ritual and belief",Canon!$N$2:$N$4229))) -> 24 | C9: =SUMPRODUCT((Canon!$D$2:$D$4229="object-type")*ISNUMBER(SEARCH(";F1.7;",";"&SUBSTITUTE(Canon!$F$2:$F$4229," ","")&";"))*ISNUMBER(SEARCH("ritual and belief",Canon!$N$2:$N$4229))) -> 15 | D9: =SUMPRODUCT((Canon!$D$2:$D$4229="object-type")*ISNUMBER(SEARCH(";F1.8;",";"&SUBSTITUTE(Canon!$F$2:$F$4229," ","")&";"))*ISNUMBER(SEARCH("ritual and belief",Canon!$N$2:$N$4229))) -> 10 | E9: =SUMPRODUCT((Canon!$D$2:$D$4229="object-type")*ISNUMBER(SEARCH(";F1.9;",";"&SUBSTITUTE(Canon!$F$2:$F$4229," ","")&";"))*ISNUMBER(SEARCH("ritual and belief",Canon!$N$2:$N$4229))) -> 10 | F9: =SUMPRODUCT((Canon!$D$2:$D$4229="object-type")*ISNUMBER(SEARCH(";F1.9a;",";"&SUBSTITUTE(Canon!$F$2:$F$4229," ","")&";"))*ISNUMBER(SEARCH("ritual and belief",Canon!$N$2:$N$4229))) -> 3 | G9: =SUMPRODUCT((Canon!$D$2:$D$4229="object-type")*ISNUMBER(SEARCH(";F1.10;",";"&SUBSTITUTE(Canon!$F$2:$F$4229," ","")&";"))*ISNUMBER(SEARCH("ritual and belief",Canon!$N$2:$N$4229))) -> 13 | H9: =SUMPRODUCT((Canon!$D$2:$D$4229="object-type")*ISNUMBER(SEARCH(";F1.11;",";"&SUBSTITUTE(Canon!$F$2:$F$4229," ","")&";"))*ISNUMBER(SEARCH("ritual and belief",Canon!$N$2:$N$4229))) -> 7 | I9: =SUMPRODUCT((Canon!$D$2:$D$4229="object-type")*ISNUMBER(SEARCH(";F1.12;",";"&SUBSTITUTE(Canon!$F$2:$F$4229," ","")&";"))*ISNUMBER(SEARCH("ritual and belief",Canon!$N$2:$N$4229))) -> 13 | J9: =SUMPRODUCT((Canon!$D$2:$D$4229="object-type")*ISNUMBER(SEARCH(";F1.12a;",";"&SUBSTITUTE(Canon!$F$2:$F$4229," ","")&";"))*ISNUMBER(SEARCH("ritual and belief",Canon!$N$2:$N$4229))) -> 1 | K9: =SUMPRODUCT((Canon!$D$2:$D$4229="object-type")*ISNUMBER(SEARCH(";F1.13;",";"&SUBSTITUTE(Canon!$F$2:$F$4229," ","")&";"))*ISNUMBER(SEARCH("ritual and belief",Canon!$N$2:$N$4229))) -> 2 | L9: =SUMPRODUCT((Canon!$D$2:$D$4229="object-type")*ISNUMBER(SEARCH(";THEME;",";"&SUBSTITUTE(Canon!$F$2:$F$4229," ","")&";"))*ISNUMBER(SEARCH("ritual and belief",Canon!$N$2:$N$4229))) -> 19 | M9: =COUNTIFS(Canon!$D$2:$D$4229,"object-type",Canon!$N$2:$N$4229,"*ritual and belief*") -> 95
A10: rule and display | B10: =SUMPRODUCT((Canon!$D$2:$D$4229="object-type")*ISNUMBER(SEARCH(";F1.6;",";"&SUBSTITUTE(Canon!$F$2:$F$4229," ","")&";"))*ISNUMBER(SEARCH("rule and display",Canon!$N$2:$N$4229))) -> 12 | C10: =SUMPRODUCT((Canon!$D$2:$D$4229="object-type")*ISNUMBER(SEARCH(";F1.7;",";"&SUBSTITUTE(Canon!$F$2:$F$4229," ","")&";"))*ISNUMBER(SEARCH("rule and display",Canon!$N$2:$N$4229))) -> 12 | D10: =SUMPRODUCT((Canon!$D$2:$D$4229="object-type")*ISNUMBER(SEARCH(";F1.8;",";"&SUBSTITUTE(Canon!$F$2:$F$4229," ","")&";"))*ISNUMBER(SEARCH("rule and display",Canon!$N$2:$N$4229))) -> 6 | E10: =SUMPRODUCT((Canon!$D$2:$D$4229="object-type")*ISNUMBER(SEARCH(";F1.9;",";"&SUBSTITUTE(Canon!$F$2:$F$4229," ","")&";"))*ISNUMBER(SEARCH("rule and display",Canon!$N$2:$N$4229))) -> 5 | F10: =SUMPRODUCT((Canon!$D$2:$D$4229="object-type")*ISNUMBER(SEARCH(";F1.9a;",";"&SUBSTITUTE(Canon!$F$2:$F$4229," ","")&";"))*ISNUMBER(SEARCH("rule and display",Canon!$N$2:$N$4229))) -> 2 | G10: =SUMPRODUCT((Canon!$D$2:$D$4229="object-type")*ISNUMBER(SEARCH(";F1.10;",";"&SUBSTITUTE(Canon!$F$2:$F$4229," ","")&";"))*ISNUMBER(SEARCH("rule and display",Canon!$N$2:$N$4229))) -> 7 | H10: =SUMPRODUCT((Canon!$D$2:$D$4229="object-type")*ISNUMBER(SEARCH(";F1.11;",";"&SUBSTITUTE(Canon!$F$2:$F$4229," ","")&";"))*ISNUMBER(SEARCH("rule and display",Canon!$N$2:$N$4229))) -> 3 | I10: =SUMPRODUCT((Canon!$D$2:$D$4229="object-type")*ISNUMBER(SEARCH(";F1.12;",";"&SUBSTITUTE(Canon!$F$2:$F$4229," ","")&";"))*ISNUMBER(SEARCH("rule and display",Canon!$N$2:$N$4229))) -> 4 | J10: =SUMPRODUCT((Canon!$D$2:$D$4229="object-type")*ISNUMBER(SEARCH(";F1.12a;",";"&SUBSTITUTE(Canon!$F$2:$F$4229," ","")&";"))*ISNUMBER(SEARCH("rule and display",Canon!$N$2:$N$4229))) -> 2 | K10: =SUMPRODUCT((Canon!$D$2:$D$4229="object-type")*ISNUMBER(SEARCH(";F1.13;",";"&SUBSTITUTE(Canon!$F$2:$F$4229," ","")&";"))*ISNUMBER(SEARCH("rule and display",Canon!$N$2:$N$4229))) -> 1 | L10: =SUMPRODUCT((Canon!$D$2:$D$4229="object-type")*ISNUMBER(SEARCH(";THEME;",";"&SUBSTITUTE(Canon!$F$2:$F$4229," ","")&";"))*ISNUMBER(SEARCH("rule and display",Canon!$N$2:$N$4229))) -> 34 | M10: =COUNTIFS(Canon!$D$2:$D$4229,"object-type",Canon!$N$2:$N$4229,"*rule and display*") -> 74
A11: war | B11: =SUMPRODUCT((Canon!$D$2:$D$4229="object-type")*ISNUMBER(SEARCH(";F1.6;",";"&SUBSTITUTE(Canon!$F$2:$F$4229," ","")&";"))*ISNUMBER(SEARCH("war",Canon!$N$2:$N$4229))) -> 3 | C11: =SUMPRODUCT((Canon!$D$2:$D$4229="object-type")*ISNUMBER(SEARCH(";F1.7;",";"&SUBSTITUTE(Canon!$F$2:$F$4229," ","")&";"))*ISNUMBER(SEARCH("war",Canon!$N$2:$N$4229))) -> 1 | D11: =SUMPRODUCT((Canon!$D$2:$D$4229="object-type")*ISNUMBER(SEARCH(";F1.8;",";"&SUBSTITUTE(Canon!$F$2:$F$4229," ","")&";"))*ISNUMBER(SEARCH("war",Canon!$N$2:$N$4229))) -> 3 | E11: =SUMPRODUCT((Canon!$D$2:$D$4229="object-type")*ISNUMBER(SEARCH(";F1.9;",";"&SUBSTITUTE(Canon!$F$2:$F$4229," ","")&";"))*ISNUMBER(SEARCH("war",Canon!$N$2:$N$4229))) -> 1 | F11: =SUMPRODUCT((Canon!$D$2:$D$4229="object-type")*ISNUMBER(SEARCH(";F1.9a;",";"&SUBSTITUTE(Canon!$F$2:$F$4229," ","")&";"))*ISNUMBER(SEARCH("war",Canon!$N$2:$N$4229))) -> 0 | G11: =SUMPRODUCT((Canon!$D$2:$D$4229="object-type")*ISNUMBER(SEARCH(";F1.10;",";"&SUBSTITUTE(Canon!$F$2:$F$4229," ","")&";"))*ISNUMBER(SEARCH("war",Canon!$N$2:$N$4229))) -> 2 | H11: =SUMPRODUCT((Canon!$D$2:$D$4229="object-type")*ISNUMBER(SEARCH(";F1.11;",";"&SUBSTITUTE(Canon!$F$2:$F$4229," ","")&";"))*ISNUMBER(SEARCH("war",Canon!$N$2:$N$4229))) -> 1 | I11: =SUMPRODUCT((Canon!$D$2:$D$4229="object-type")*ISNUMBER(SEARCH(";F1.12;",";"&SUBSTITUTE(Canon!$F$2:$F$4229," ","")&";"))*ISNUMBER(SEARCH("war",Canon!$N$2:$N$4229))) -> 2 | J11: =SUMPRODUCT((Canon!$D$2:$D$4229="object-type")*ISNUMBER(SEARCH(";F1.12a;",";"&SUBSTITUTE(Canon!$F$2:$F$4229," ","")&";"))*ISNUMBER(SEARCH("war",Canon!$N$2:$N$4229))) -> 3 | K11: =SUMPRODUCT((Canon!$D$2:$D$4229="object-type")*ISNUMBER(SEARCH(";F1.13;",";"&SUBSTITUTE(Canon!$F$2:$F$4229," ","")&";"))*ISNUMBER(SEARCH("war",Canon!$N$2:$N$4229))) -> 0 | L11: =SUMPRODUCT((Canon!$D$2:$D$4229="object-type")*ISNUMBER(SEARCH(";THEME;",";"&SUBSTITUTE(Canon!$F$2:$F$4229," ","")&";"))*ISNUMBER(SEARCH("war",Canon!$N$2:$N$4229))) -> 17 | M11: =COUNTIFS(Canon!$D$2:$D$4229,"object-type",Canon!$N$2:$N$4229,"*war*") -> 29
A12: play and music | B12: =SUMPRODUCT((Canon!$D$2:$D$4229="object-type")*ISNUMBER(SEARCH(";F1.6;",";"&SUBSTITUTE(Canon!$F$2:$F$4229," ","")&";"))*ISNUMBER(SEARCH("play and music",Canon!$N$2:$N$4229))) -> 6 | C12: =SUMPRODUCT((Canon!$D$2:$D$4229="object-type")*ISNUMBER(SEARCH(";F1.7;",";"&SUBSTITUTE(Canon!$F$2:$F$4229," ","")&";"))*ISNUMBER(SEARCH("play and music",Canon!$N$2:$N$4229))) -> 6 | D12: =SUMPRODUCT((Canon!$D$2:$D$4229="object-type")*ISNUMBER(SEARCH(";F1.8;",";"&SUBSTITUTE(Canon!$F$2:$F$4229," ","")&";"))*ISNUMBER(SEARCH("play and music",Canon!$N$2:$N$4229))) -> 4 | E12: =SUMPRODUCT((Canon!$D$2:$D$4229="object-type")*ISNUMBER(SEARCH(";F1.9;",";"&SUBSTITUTE(Canon!$F$2:$F$4229," ","")&";"))*ISNUMBER(SEARCH("play and music",Canon!$N$2:$N$4229))) -> 3 | F12: =SUMPRODUCT((Canon!$D$2:$D$4229="object-type")*ISNUMBER(SEARCH(";F1.9a;",";"&SUBSTITUTE(Canon!$F$2:$F$4229," ","")&";"))*ISNUMBER(SEARCH("play and music",Canon!$N$2:$N$4229))) -> 2 | G12: =SUMPRODUCT((Canon!$D$2:$D$4229="object-type")*ISNUMBER(SEARCH(";F1.10;",";"&SUBSTITUTE(Canon!$F$2:$F$4229," ","")&";"))*ISNUMBER(SEARCH("play and music",Canon!$N$2:$N$4229))) -> 2 | H12: =SUMPRODUCT((Canon!$D$2:$D$4229="object-type")*ISNUMBER(SEARCH(";F1.11;",";"&SUBSTITUTE(Canon!$F$2:$F$4229," ","")&";"))*ISNUMBER(SEARCH("play and music",Canon!$N$2:$N$4229))) -> 4 | I12: =SUMPRODUCT((Canon!$D$2:$D$4229="object-type")*ISNUMBER(SEARCH(";F1.12;",";"&SUBSTITUTE(Canon!$F$2:$F$4229," ","")&";"))*ISNUMBER(SEARCH("play and music",Canon!$N$2:$N$4229))) -> 3 | J12: =SUMPRODUCT((Canon!$D$2:$D$4229="object-type")*ISNUMBER(SEARCH(";F1.12a;",";"&SUBSTITUTE(Canon!$F$2:$F$4229," ","")&";"))*ISNUMBER(SEARCH("play and music",Canon!$N$2:$N$4229))) -> 1 | K12: =SUMPRODUCT((Canon!$D$2:$D$4229="object-type")*ISNUMBER(SEARCH(";F1.13;",";"&SUBSTITUTE(Canon!$F$2:$F$4229," ","")&";"))*ISNUMBER(SEARCH("play and music",Canon!$N$2:$N$4229))) -> 0 | L12: =SUMPRODUCT((Canon!$D$2:$D$4229="object-type")*ISNUMBER(SEARCH(";THEME;",";"&SUBSTITUTE(Canon!$F$2:$F$4229," ","")&";"))*ISNUMBER(SEARCH("play and music",Canon!$N$2:$N$4229))) -> 25 | M12: =COUNTIFS(Canon!$D$2:$D$4229,"object-type",Canon!$N$2:$N$4229,"*play and music*") -> 49
A13: care and access | B13: =SUMPRODUCT((Canon!$D$2:$D$4229="object-type")*ISNUMBER(SEARCH(";F1.6;",";"&SUBSTITUTE(Canon!$F$2:$F$4229," ","")&";"))*ISNUMBER(SEARCH("care and access",Canon!$N$2:$N$4229))) -> 4 | C13: =SUMPRODUCT((Canon!$D$2:$D$4229="object-type")*ISNUMBER(SEARCH(";F1.7;",";"&SUBSTITUTE(Canon!$F$2:$F$4229," ","")&";"))*ISNUMBER(SEARCH("care and access",Canon!$N$2:$N$4229))) -> 2 | D13: =SUMPRODUCT((Canon!$D$2:$D$4229="object-type")*ISNUMBER(SEARCH(";F1.8;",";"&SUBSTITUTE(Canon!$F$2:$F$4229," ","")&";"))*ISNUMBER(SEARCH("care and access",Canon!$N$2:$N$4229))) -> 0 | E13: =SUMPRODUCT((Canon!$D$2:$D$4229="object-type")*ISNUMBER(SEARCH(";F1.9;",";"&SUBSTITUTE(Canon!$F$2:$F$4229," ","")&";"))*ISNUMBER(SEARCH("care and access",Canon!$N$2:$N$4229))) -> 1 | F13: =SUMPRODUCT((Canon!$D$2:$D$4229="object-type")*ISNUMBER(SEARCH(";F1.9a;",";"&SUBSTITUTE(Canon!$F$2:$F$4229," ","")&";"))*ISNUMBER(SEARCH("care and access",Canon!$N$2:$N$4229))) -> 1 | G13: =SUMPRODUCT((Canon!$D$2:$D$4229="object-type")*ISNUMBER(SEARCH(";F1.10;",";"&SUBSTITUTE(Canon!$F$2:$F$4229," ","")&";"))*ISNUMBER(SEARCH("care and access",Canon!$N$2:$N$4229))) -> 3 | H13: =SUMPRODUCT((Canon!$D$2:$D$4229="object-type")*ISNUMBER(SEARCH(";F1.11;",";"&SUBSTITUTE(Canon!$F$2:$F$4229," ","")&";"))*ISNUMBER(SEARCH("care and access",Canon!$N$2:$N$4229))) -> 1 | I13: =SUMPRODUCT((Canon!$D$2:$D$4229="object-type")*ISNUMBER(SEARCH(";F1.12;",";"&SUBSTITUTE(Canon!$F$2:$F$4229," ","")&";"))*ISNUMBER(SEARCH("care and access",Canon!$N$2:$N$4229))) -> 0 | J13: =SUMPRODUCT((Canon!$D$2:$D$4229="object-type")*ISNUMBER(SEARCH(";F1.12a;",";"&SUBSTITUTE(Canon!$F$2:$F$4229," ","")&";"))*ISNUMBER(SEARCH("care and access",Canon!$N$2:$N$4229))) -> 2 | K13: =SUMPRODUCT((Canon!$D$2:$D$4229="object-type")*ISNUMBER(SEARCH(";F1.13;",";"&SUBSTITUTE(Canon!$F$2:$F$4229," ","")&";"))*ISNUMBER(SEARCH("care and access",Canon!$N$2:$N$4229))) -> 0 | L13: =SUMPRODUCT((Canon!$D$2:$D$4229="object-type")*ISNUMBER(SEARCH(";THEME;",";"&SUBSTITUTE(Canon!$F$2:$F$4229," ","")&";"))*ISNUMBER(SEARCH("care and access",Canon!$N$2:$N$4229))) -> 28 | M13: =COUNTIFS(Canon!$D$2:$D$4229,"object-type",Canon!$N$2:$N$4229,"*care and access*") -> 36
A14: transport | B14: =SUMPRODUCT((Canon!$D$2:$D$4229="object-type")*ISNUMBER(SEARCH(";F1.6;",";"&SUBSTITUTE(Canon!$F$2:$F$4229," ","")&";"))*ISNUMBER(SEARCH("transport",Canon!$N$2:$N$4229))) -> 3 | C14: =SUMPRODUCT((Canon!$D$2:$D$4229="object-type")*ISNUMBER(SEARCH(";F1.7;",";"&SUBSTITUTE(Canon!$F$2:$F$4229," ","")&";"))*ISNUMBER(SEARCH("transport",Canon!$N$2:$N$4229))) -> 8 | D14: =SUMPRODUCT((Canon!$D$2:$D$4229="object-type")*ISNUMBER(SEARCH(";F1.8;",";"&SUBSTITUTE(Canon!$F$2:$F$4229," ","")&";"))*ISNUMBER(SEARCH("transport",Canon!$N$2:$N$4229))) -> 3 | E14: =SUMPRODUCT((Canon!$D$2:$D$4229="object-type")*ISNUMBER(SEARCH(";F1.9;",";"&SUBSTITUTE(Canon!$F$2:$F$4229," ","")&";"))*ISNUMBER(SEARCH("transport",Canon!$N$2:$N$4229))) -> 1 | F14: =SUMPRODUCT((Canon!$D$2:$D$4229="object-type")*ISNUMBER(SEARCH(";F1.9a;",";"&SUBSTITUTE(Canon!$F$2:$F$4229," ","")&";"))*ISNUMBER(SEARCH("transport",Canon!$N$2:$N$4229))) -> 0 | G14: =SUMPRODUCT((Canon!$D$2:$D$4229="object-type")*ISNUMBER(SEARCH(";F1.10;",";"&SUBSTITUTE(Canon!$F$2:$F$4229," ","")&";"))*ISNUMBER(SEARCH("transport",Canon!$N$2:$N$4229))) -> 3 | H14: =SUMPRODUCT((Canon!$D$2:$D$4229="object-type")*ISNUMBER(SEARCH(";F1.11;",";"&SUBSTITUTE(Canon!$F$2:$F$4229," ","")&";"))*ISNUMBER(SEARCH("transport",Canon!$N$2:$N$4229))) -> 3 | I14: =SUMPRODUCT((Canon!$D$2:$D$4229="object-type")*ISNUMBER(SEARCH(";F1.12;",";"&SUBSTITUTE(Canon!$F$2:$F$4229," ","")&";"))*ISNUMBER(SEARCH("transport",Canon!$N$2:$N$4229))) -> 3 | J14: =SUMPRODUCT((Canon!$D$2:$D$4229="object-type")*ISNUMBER(SEARCH(";F1.12a;",";"&SUBSTITUTE(Canon!$F$2:$F$4229," ","")&";"))*ISNUMBER(SEARCH("transport",Canon!$N$2:$N$4229))) -> 4 | K14: =SUMPRODUCT((Canon!$D$2:$D$4229="object-type")*ISNUMBER(SEARCH(";F1.13;",";"&SUBSTITUTE(Canon!$F$2:$F$4229," ","")&";"))*ISNUMBER(SEARCH("transport",Canon!$N$2:$N$4229))) -> 4 | L14: =SUMPRODUCT((Canon!$D$2:$D$4229="object-type")*ISNUMBER(SEARCH(";THEME;",";"&SUBSTITUTE(Canon!$F$2:$F$4229," ","")&";"))*ISNUMBER(SEARCH("transport",Canon!$N$2:$N$4229))) -> 21 | M14: =COUNTIFS(Canon!$D$2:$D$4229,"object-type",Canon!$N$2:$N$4229,"*transport*") -> 41

Sheet Canon
A1: id | B1: name | C1: other_names | D1: kind | E1: family | F1: world | G1: sub_regions | H1: start | I1: end | J1: date_note | K1: making_significance | L1: materials_techniques | M1: object_types | N1: functions | O1: defined_by | P1: leaves_out | Q1: sensitivity | R1: free_sources | S1: tier | T1: units | U1: confidence | V1: notes
A2: GAP001 | B2: Early Christian art | C2: Late Antique Christian art | D2: style | E2: Ideas | F2: F1.11;F1.9a | G2: EU-GRR;WA-LEV;AF-EGY | H2: 200 | I2: 600 | J2: approx.; boundaries debated | K2: Christian communities adapted Roman workshop practice (fresco, sarcophagus carving, mosaic and the basilica hall) to new uses. | L2: fresco;mosaic;marble carving;ivory carving | M2: catacomb paintings;sarcophagi;basilicas;ivories | N2: ritual and belief | O2: art historians | P2: Jewish, Coptic and Syriac traditions working alongside | Q2: funerary | R2: Met Open Access (CC0);Cleveland Museum of Art Open Access (CC0);Art Institute of Chicago (CC0);Wikimedia Commons | S2: R3 | T2: F1.16;F1.11 | U2: high | V2: benchmark: AP-250 nos. 48, 49; Smarthistory Reframing ch. "Building new Romes". links: BEL011; STY083; POL120
A3: GAP002 | B3: Mannerism | C3: maniera | D3: style | E3: Ideas | F3: F1.11 | G3: EU-WCE | H3: 1520 | I3: 1600 | J3: approx.; label applied later from Vasari's "maniera" | K3: Painters, sculptors and goldsmiths in Florence, Rome and at Fontainebleau cultivated elongated figures and virtuoso artifice, a manner carried by prints and courts. | L3: oil painting;bronze casting;goldsmithing;engraving | M3: altarpieces;portraits;bronzes;table ornaments | N3: ritual and belief;rule and display | O3: 19th- and 20th-century art historians, after Vasari | P3: workshop assistants; the Northern and colonial versions | Q3: none | R3: Met Open Access (CC0);Cleveland Museum of Art Open Access (CC0);Art Institute of Chicago (CC0);Wikimedia Commons | S3: R3 | T3: F1.3 | U3: high | V3: benchmark: AP-250 no. 78; Heilbrunn keyword "Mannerism" and essay "Mannerism: Bronzino (1503–1572) and his Contemporaries". links: STY019; SCH001
A4: GAP003 | B4: Dutch Golden Age painting | C4: Dutch seventeenth-century painting | D4: style | E4: Ideas | F4: F1.11 | G4: EU-BLC | H4: 1600 | I4: 1700 | J4: approx. | K4: Painters in the Dutch Republic sold still lifes, landscapes and genre scenes on an open market, not mainly to church or court commissions. | L4: oil painting;etching | M4: paintings;prints | N4: rule and display | O4: 19th-century historians | P4: the colonial trade and slavery that financed much of the market | Q4: human-flow | R4: Met Open Access (CC0);Cleveland Museum of Art Open Access (CC0);Art Institute of Chicago (CC0);Wikimedia Commons | S4: R3 | T4: F1.17 | U4: high | V4: benchmark: AP-250 nos. 87, 92, 96; Heilbrunn keyword "Dutch Golden Age". The market-as-patron point is the F1.17 lesson. links: POL129; INS038
A5: GAP004 | B5: Casta painting | C5: pinturas de castas | D5: style | E5: Ideas | F5: F1.7 | G5: AM-LAT | H5: 1710 | I5: 1800 | J5: approx. | K5: Painters in New Spain made series that sorted families of mixed ancestry into a colonial hierarchy of race, often for European buyers. | L5: oil on canvas | M5: painting series | N5: record and writing;rule and display | O5: art historians | P5: how the people depicted named themselves | Q5: none | R5: Wikimedia Commons (per-item licence);collection search link-out | S5: R3 | T5: F1.3;F1.24 | U5: high | V5: benchmark: AP-250 no. 97; Smarthistory Reframing ch. "The art of the viceroyalty of New Spain". links: POL069
A6: GAP005 | B6: Namban art | C6: Nanban | D6: style | E6: Ideas | F6: F1.8;F1.13 | G6: AS-JPN | H6: 1570 | I6: 1640 | J6: approx.; ends with the expulsion of the Portuguese (1639) | K6: Japanese painters and lacquerers made screens and objects that showed or served Portuguese traders and Jesuits, some made for export to Europe. | L6: lacquer;gold leaf;mother-of-pearl inlay;painting on paper | M6: folding screens;lacquer chests;lecterns | N6: ritual and belief;exchange and value | O6: Japanese usage ("southern barbarian"); historians | P6: the enslaved and servant Africans and South Asians who appear in the screens | Q6: human-flow | R6: Met Open Access (CC0);Cleveland Museum of Art Open Access (CC0);Art Institute of Chicago (CC0);Wikimedia Commons | S6: R3 | T6: F1.13;F1.14 | U6: high | V6: benchmark: Smarthistory Reframing ch. "Portuguese contacts and exchanges, c. 1400–1800". POL136 mentions "Namban goods" but no node exists. links: POL136; TEC138
A7: GAP006 | B7: Romanticism | C7: Romantic movement | D7: movement | E7: Ideas | F7: F1.11 | G7: EU-WCE;EU-BLC;EU-IBE | H7: 1790 | I7: 1850 | J7: approx. | K7: Writers, painters and architects across Europe turned to feeling, nature, the medieval and the national past, a turn that fed the Gothic Revival and interest in folk traditions. | L7: oil painting;lithography;etching | M7: history paintings;prints;illustrated books | N7: rule and display | O7: participants in part (the Schlegels' "romantisch") and later historians | P7: the colonial and orientalist sources it drew on | Q7: none | R7: Met Open Access (CC0);Cleveland Museum of Art Open Access (CC0);Art Institute of Chicago (CC0);Wikimedia Commons | S7: R3 | T7: F1.3;F1.20 | U7: high | V7: benchmark: AP-250 nos. 106, 108, 111; Heilbrunn keyword and essay "Romanticism". links: STY027; STY040
A8: GAP007 | B8: Realism (nineteenth-century France) | C8: Réalisme | D8: movement | E8: Ideas | F8: F1.11 | G8: EU-WCE | H8: 1848 | I8: 1880 | J8: approx.; Courbet's "Pavilion of Realism", 1855 | K8: Painters and printmakers took labourers, peasants and ordinary life as subjects, making work itself a subject of art. | L8: oil painting;lithography | M8: paintings;caricature prints | N8: record and writing | O8: Courbet and critics such as Champfleury | P8: the workers depicted, who had no say in how | Q8: none | R8: Met Open Access (CC0);Cleveland Museum of Art Open Access (CC0);Art Institute of Chicago (CC0);Wikimedia Commons | S8: R3 | T8: F1.23;F1.3 | U8: high | V8: benchmark: AP-250 nos. 113, 114; Heilbrunn essay "Nineteenth-Century French Realism"
A9: GAP008 | B9: Post-Impressionism | D9: style | E9: Ideas | F9: F1.11 | G9: EU-WCE | H9: 1886 | I9: 1905 | J9: approx.; label coined by Roger Fry for a 1910 London exhibition | K9: A label given afterwards to painters such as Cézanne, van Gogh, Gauguin and Seurat, whose different methods moved painting away from recording light. | L9: oil painting;divided colour | M9: paintings | O9: Roger Fry (1910) | P9: the Japanese prints and Pacific objects several of them drew on | Q9: none | R9: Met Open Access (CC0);Cleveland Museum of Art Open Access (CC0);Art Institute of Chicago (CC0);Wikimedia Commons | S9: R3 | T9: F1.3;F1.20 | U9: high | V9: benchmark: AP-250 nos. 120, 125; Heilbrunn keyword and essay "Post-Impressionism". links: STY030; STY062
A10: GAP009 | B10: Symbolism | C10: Symbolist movement | D10: movement | E10: Ideas | F10: F1.11 | G10: EU-WCE;EU-BLC | H10: 1886 | I10: 1910 | J10: approx.; Moréas's manifesto, 1886 | K10: Poets, painters and designers favoured dream, myth and suggestion over description; its motifs passed into Art Nouveau graphics and interiors. | L10: oil painting;lithography;tempera | M10: paintings;posters;book design | O10: its members (Moréas's manifesto) | Q10: none | R10: Met Open Access (CC0);Cleveland Museum of Art Open Access (CC0);Art Institute of Chicago (CC0);Wikimedia Commons | S10: R3 | T10: F1.20 | U10: high | V10: benchmark: AP-250 no. 122; Heilbrunn keyword and essay "Symbolism". links: STY036; MOV009
A11: GAP010 | B11: Expressionism (German) | C11: Die Brücke; Der Blaue Reiter | D11: movement | E11: Ideas | F11: F1.11 | G11: EU-WCE | H11: 1905 | I11: 1925 | J11: Die Brücke founded Dresden 1905; Der Blaue Reiter Munich 1911 | K11: Artists' groups in Dresden, Berlin and Munich revived the woodcut and used distorted form and strong colour; two of the Blaue Reiter circle later taught at the Bauhaus. | L11: woodcut;oil painting | M11: woodcuts;paintings;posters;almanacs | O11: members named their groups; "Expressionism" is a critics' term | P11: the African and Oceanic objects in ethnographic museums they drew on | Q11: none | R11: Met Open Access (CC0);Cleveland Museum of Art Open Access (CC0);Art Institute of Chicago (CC0);Wikimedia Commons | S11: R3 | T11: F1.20;F1.2 | U11: high | V11: benchmark: AP-250 nos. 132, 133, 134; Heilbrunn keywords "Expressionism", "Der Blaue Reiter". The Bauhaus link is Kandinsky and Klee. links: INS057; STY062
A12: GAP011 | B12: Fauvism | C12: Les Fauves | D12: style | E12: Ideas | F12: F1.11 | G12: EU-WCE | H12: 1905 | I12: 1908 | J12: named by the critic Louis Vauxcelles at the 1905 Salon d'Automne | K12: Painters around Matisse and Derain used unmixed, non-descriptive colour, briefly and without a programme. | L12: oil painting | M12: paintings | O12: a critic (Vauxcelles) | Q12: none | R12: Met Open Access (CC0);Cleveland Museum of Art Open Access (CC0);Art Institute of Chicago (CC0);Wikimedia Commons | S12: R3 | T12: F1.20 | U12: high | V12: benchmark: AP-250 no. 131; Heilbrunn essay "Fauvism"
A13: GAP012 | B13: Pictorialism | C13: Photo-Secession | D13: movement | E13: Ideas | F13: F1.11;F1.7 | G13: EU-WCE;AM-EWD | H13: 1885 | I13: 1920 | J13: approx.; Photo-Secession founded New York 1902 | K13: Photographers used soft focus and hand-worked printing processes to argue that photography could be art. | L13: platinum print;gum bichromate;photogravure | M13: photographs;journals | N13: record and writing | O13: its members | Q13: none | R13: Met Open Access (CC0);Cleveland Museum of Art Open Access (CC0);Art Institute of Chicago (CC0);Wikimedia Commons | S13: R3 | T13: F1.4;F1.3 | U13: high | V13: benchmark: AP-250 no. 127; Heilbrunn essays "International Pictorialism", "Pictorialism in America". links: TEC196
A14: GAP013 | B14: Chicago School (architecture) | C14: Commercial style | D14: style | E14: Ideas | F14: F1.7 | G14: AM-EWD | H14: 1880 | I14: 1910 | J14: approx.; rebuilding after the 1871 fire | K14: Architects and engineers developed tall office buildings on steel frames with large windows. | L14: steel frame;terracotta cladding;plate glass;passenger elevators | M14: office buildings;department stores | N14: shelter;exchange and value | O14: historians | P14: the ironworkers and immigrant building labour | Q14: none | R14: Wikimedia Commons;Library of Congress (HABS, public domain where marked) | S14: R3 | T14: F1.19 | U14: high | V14: benchmark: AP-250 no. 124; Heilbrunn keyword "Chicago School". Sullivan (1896) is in primary_texts. links: MAT119
A15: GAP014 | B15: Abstract Expressionism | C15: New York School | D15: movement | E15: Ideas | F15: F1.7 | G15: AM-EWD | H15: 1943 | I15: 1960 | J15: approx. | K15: New York painters made large gestural and stained colour-field canvases, which MoMA's international programme toured abroad (1958–59). | L15: oil and enamel paint;staining raw canvas | M15: paintings | O15: critics (Robert Coates, 1946) | P15: women and Black painters of the circle long left out of its histories | Q15: none | R15: collection search link-out only (works in copyright);Wikimedia Commons (per-item licence) | S15: R3 | T15: F1.20;F1.19a | U15: high | V15: benchmark: AP-250 nos. 145, 149; Heilbrunn keywords "Abstract Expressionism", "Color Field". Cold War use is argued; keep the claim to the tour. links: INS081
A16: GAP015 | B16: Minimalism | C16: Minimal art | D16: style | E16: Ideas | F16: F1.7 | G16: AM-EWD | H16: 1960 | I16: 1975 | J16: approx. | K16: Artists used industrial materials and outside fabricators, a model of authorship later common in design and architecture. | L16: steel;aluminium;fluorescent tubes;fabrication | M16: sculpture;installations | O16: critics | P16: the fabricators who made the works | Q16: none | R16: collection search link-out only (works in copyright);Wikimedia Commons (per-item licence) | S16: R3 | T16: F1.20;F1.23 | U16: medium | V16: benchmark: Heilbrunn keyword "Minimalism"; AP-250 no. 225 is often read against it (interpretive)
A17: GAP016 | B17: Land art | C17: Earthworks | D17: movement | E17: Ideas | F17: F1.7 | G17: AM-WST | H17: 1967 | I17: 1980 | J17: approx. | K17: Artists made works from earth, rock and water at landscape scale, outside the gallery. | L17: earthmoving;rock;salt | M17: earthworks | O17: critics and the artists | P17: the Indigenous lands and far older earthworks (mounds, geoglyphs) they sit among | Q17: none | R17: collection search link-out only (works in copyright);Wikimedia Commons (per-item licence) | S17: R3 | T17: F1.22 | U17: high | V17: benchmark: AP-250 no. 151; Heilbrunn keyword "Earthworks / Land Art"; Smarthistory Reframing ch. "Re-Mapping Land Art". links: TEC169; INV133
A18: GAP017 | B18: Fluxus | D18: movement | E18: Ideas | F18: THEME | G18: AM-EWD;EU-WCE;AS-JPN | H18: 1962 | I18: 1978 | J18: approx.; named by George Maciunas | K18: An international network made event scores, multiples and boxed editions, with Maciunas designing much of its graphics. | L18: offset printing;boxed multiples | M18: editions;scores;posters | N18: play and music | O18: its members | Q18: none | R18: collection search link-out only (works in copyright);Wikimedia Commons (per-item licence) | S18: R3 | T18: F1.4;F1.21 | U18: medium | V18: benchmark: AP-250 no. 238 (Paik); Heilbrunn keyword "Fluxus"
A19: GAP018 | B19: Plains hide painting and ledger art | C19: ledger drawing | D19: style | E19: Ideas | F19: F1.7 | G19: AM-WST | H19: 1800 | I19: 1930 | J19: approx.; hide painting is older; ledger drawing c. 1860s–1930s | K19: Plains men painted war and winter-count records on hides and later drew them in account books, including Cheyenne and Kiowa prisoners held at Fort Marion (1875–78). | L19: earth and mineral pigments on hide;pencil and crayon on ledger paper | M19: painted robes;tipi covers;ledger books | N19: record and writing;war | O19: museums and historians | P19: women's geometric hide painting, less collected | Q19: Indigenous-community;human-flow | R19: Smithsonian Open Access (CC0 where marked);Met Open Access (CC0);Wikimedia Commons | S19: R3 | T19: F1.5;F1.29 | U19: high | V19: benchmark: AP-250 no. 165; Heilbrunn keywords "Sioux Art", "Dakota Art". Fort Marion prisoners were moved by force, hence human-flow. links: SCH009; OBT150; TEC175
A20: GAP019 | B20: Academic art | C20: academicism | D20: style | E20: Ideas | F20: F1.11;THEME | G20: EU-WCE;GL | H20: 1648 | I20: 1900 | J20: approx.; from the founding of the Paris academy | K20: Academies trained artists by drawing from casts and life and ranked the genres, with history painting at the top and the crafts outside. | L20: drawing from casts and life;oil painting | M20: history paintings;academic studies | N20: rule and display | O20: the academies themselves | P20: craftspeople; women, long barred from life classes | Q20: none | R20: Met Open Access (CC0);Cleveland Museum of Art Open Access (CC0);Art Institute of Chicago (CC0);Wikimedia Commons | S20: R3 | T20: F1.3 | U20: high | V20: benchmark: Heilbrunn keyword "Academic Painting" and essay "The Salon and the Royal Academy in the Nineteenth Century". links: INS049; INS050; INS011
A21: GAP020 | B21: Yugoslav socialist modernism | C21: Nonaligned modernism (Videkanić) | D21: style | E21: Ideas | F21: F1.11 | G21: EU-BYZ | H21: 1948 | I21: 1980 | J21: after the 1948 Tito–Stalin split | K21: Yugoslav architects, designers and artists developed a modernism distinct from Soviet models, tied to workers' self-management and to exchange with Non-Aligned states. | L21: reinforced concrete;industrial design;graphic design | M21: memorials;housing;hotels;posters | N21: shelter;rule and display | O21: historians (MoMA 2018; Videkanić 2020) | P21: differences between the republics inside Yugoslavia | Q21: none | R21: collection search link-out only (works in copyright);Wikimedia Commons (per-item licence) | S21: R3 | T21: F1.20 | U21: medium | V21: benchmark: MoMA "Toward a Concrete Utopia: Architecture in Yugoslavia 1948–1980" (2018); Videkanić, Nonaligned Modernism (McGill-Queen's, 2020). links: STY158; POL151
A22: GAP021 | B22: Korean ink-painting movement | C22: Sumukhwa movement | D22: movement | E22: Ideas | F22: F1.8 | G22: AS-KOR | H22: 1980 | I22: 1995 | J22: approx.; led by Song Su-nam and others at Hongik University (to verify) | K22: Korean painters renewed ink on paper as a contemporary medium in the 1980s. | L22: ink stick and brush;hanji | M22: paintings | O22: its participants and critics | Q22: none | R22: collection search link-out only (works in copyright);Wikimedia Commons (per-item licence) | S22: R3 | T22: F1.20 | U22: low | V22: benchmark: AP-250 no. 227. Dates and membership to verify. links: TEC209; PRA093
A23: GAP022 | B23: Niuean hiapo | C23: hiapo | D23: style | E23: Ideas | F23: F1.12 | G23: OC-POL | H23: 1850 | I23: 1900 | J23: approx.; revival efforts from the late 20th century | K23: Niuean makers painted barkcloth freehand with fine linear designs, some with figures and inscriptions. | L23: barkcloth;freehand painting | M23: barkcloth | N23: clothing and adornment;exchange and value | O23: museums; Niuean makers | Q23: Indigenous-community | R23: community-published site;collection search link-out only | S23: R3 | T23: F1.12;F1.18 | U23: medium | V23: benchmark: AP-250 no. 219. links: OBT047; MAT068
A24: GAP023 | B24: Stained glass | D24: technique | E24: Things | F24: F1.11 | G24: EU-WCE;EU-BLC | H24: 900 | J24: coloured window glass is older; painted figurative windows from c. 10th century | K24: Glaziers set pieces of coloured and painted glass in lead cames to make windows, a large workshop industry of Gothic building. | L24: pot-metal glass;vitreous paint;silver stain;lead cames | M24: windows | N24: ritual and belief | O24: Theophilus (12th century) describes the process | Q24: none | R24: Met Open Access (CC0);Cleveland Museum of Art Open Access (CC0);Art Institute of Chicago (CC0);Wikimedia Commons;Europeana (per-item licence) | S24: R2 | T24: F1.11;F1.28 | U24: high | V24: benchmark: AP-250 no. 60; Heilbrunn essay "Stained Glass in Medieval Europe" and material keyword "Stained Glass". Theophilus is TXT in primary_texts. links: STY013; MKR032; MKR076
A25: GAP024 | B25: Manuscript illumination | C25: book illumination | D25: technique | E25: Things | F25: THEME | G25: GL | H25: 400 | J25: illuminated books from late antiquity on | K25: Scribes and painters decorated handwritten books with gold, pigments and ornament in monastic, court and later commercial workshops. | L25: parchment;gold leaf;mineral pigments;binding | M25: codices;Gospels;books of hours | N25: ritual and belief;record and writing | O25: art historians | P25: the lay and women illuminators of commercial workshops | Q25: none | R25: Met Open Access (CC0);Cleveland Museum of Art Open Access (CC0);Art Institute of Chicago (CC0);Wikimedia Commons;Europeana (per-item licence) | S25: R2 | T25: F1.28;F1.17 | U25: high | V25: benchmark: AP-250 nos. 50, 55, 61, 64; Heilbrunn essays "The Art of the Book in the Middle Ages", "Manuscript Illumination in Northern Europe". links: MKR060; SCH046; OBT132; TEC174
A26: GAP025 | B26: Enconchado | D26: technique | E26: Things | F26: F1.7;F1.13 | G26: AM-LAT | H26: 1650 | I26: 1750 | J26: approx. | K26: Painters in New Spain set mother-of-pearl into paintings, a technique associated with Asian lacquer arriving on the Manila galleons. | L26: mother-of-pearl;oil paint;varnish | M26: paintings;folding screens | N26: ritual and belief;rule and display | O26: art historians | Q26: none | R26: Wikimedia Commons (per-item licence);collection search link-out | S26: R3 | T26: F1.13;F1.14 | U26: high | V26: benchmark: AP-250 no. 95. NET036 names enconchado in prose but no node exists. links: NET036; MAT083
A27: GAP026 | B27: Islamic geometric pattern construction | C27: girih; geometric strapwork | D27: technique | E27: Things | F27: F1.10 | G27: WA-IRN;WA-ANA;AF-MAG;AS-CEN;AS-SAS | H27: 900 | J27: approx.; systematic star-and-polygon patterns from the 10th–11th centuries | K27: Artisans laid out interlacing star-and-polygon patterns with compass and straightedge and repeated them in wood, tile, stucco and metal. | L27: compass and straightedge;tile mosaic;carving;inlay | M27: tilework;carved panels;metalwork;book covers | N27: ritual and belief;rule and display | O27: art historians and mathematicians | P27: the builders' own manuals, mostly lost | Q27: none | R27: Met Open Access (CC0);Cleveland Museum of Art Open Access (CC0);Art Institute of Chicago (CC0);Wikimedia Commons;Archnet (terms per item) | S27: R2 | T27: F1.15;F1.10 | U27: high | V27: benchmark: Heilbrunn essay "Geometric Patterns in Islamic Art". Whether girih was laid out from tile modules is argued; do not state it. links: TEC168; PRA009; PRA155
A28: GAP027 | B28: Photomontage | D28: technique | E28: Things | F28: THEME | G28: EU-EER;EU-WCE | H28: 1918 | J28: approx.; Berlin Dada and Soviet Constructivists c. 1918–20 | K28: Artists and designers cut and combined photographs for posters, books and magazines. | L28: cut photographs;rephotography;offset printing | M28: posters;book covers;magazine spreads | N28: record and writing;rule and display | O28: its practitioners | Q28: none | R28: collection search link-out only (works in copyright);Wikimedia Commons (per-item licence) | S28: R3 | T28: F1.20;F1.19a | U28: high | V28: benchmark: AP-250 no. 137; Heilbrunn keyword "Collage". links: MOV019; MOV014
A29: GAP028 | B29: Hot-metal typesetting | C29: Linotype; Monotype | D29: technique | E29: Things | F29: THEME | G29: GL | H29: 1886 | I29: 1980 | J29: Linotype in use from 1886; displaced by photo and digital setting by c. 1980 | K29: Keyboard-operated machines cast whole lines or single letters from molten type metal, industrialising newspaper and book setting. | L29: type metal;matrices;keyboards | M29: newspapers;books | N29: record and writing | O29: historians of printing | P29: the hand compositors displaced; scripts that did not fit machines built for Latin type | Q29: none | R29: Wikimedia Commons;Internet Archive (public-domain manuals) | S29: R3 | T29: F1.19;F1.21 | U29: high | V29: benchmark: JDH virtual issue "Typographic Histories"; Shehab and Nawar, A History of Arab Graphic Design (adapting Arabic to Latin-script technologies, per Brooklyn Rail review). links: TEC195; OBT134
A30: GAP029 | B30: Machine-learning generative models | C30: generative AI | D30: technique | E30: Things | F30: THEME | G30: GL | H30: 2014 | J30: generative adversarial networks 2014; public text-to-image tools 2022 | K30: Statistical models trained on large collections of images and texts generate new images, texts and layouts from prompts, raising questions of credit and consent over training data. | L30: training datasets;neural networks;prompts | M30: images;texts;layouts | N30: record and writing | O30: computer scientists and companies | P30: the makers whose work formed the training data; data-labelling workers | Q30: none | R30: none identified; link out to official site | S30: R3 | T30: F1.5;F1.21;F1.14;F1.23 | U30: medium | V30: benchmark: JDH, Talley, "Digital Design History" (2026) names algorithms and AI as producing-mediating actors; Science and Industry Museum on Jacquard punched cards and computing. Recurrence chain: drawloom, Jacquard, computer, generative model. links: TEC090; OBT109; MOV036
A31: GAP030 | B31: chair | C31: seat with a back | D31: object-type | E31: Things | F31: THEME | G31: GL | H31: -2600 | J31: Egyptian chairs from the Old Kingdom; many societies sat on floors, mats or stools instead | K31: A raised seat with a back that marks rank in many societies and is much used in histories of modern design. | L31: joinery;bentwood;tubular steel;moulded plywood;plastics | M31: chairs;armchairs | N31: rule and display;care and access | O31: museum typology | P31: floor-seated and stool-using cultures that a chair-led canon treats as absent | Q31: none | R31: Met Open Access (CC0);Cleveland Museum of Art Open Access (CC0);Art Institute of Chicago (CC0);Wikimedia Commons;Europeana (per-item licence) | S31: R2 | T31: F1.19;F1.20;F1.22a | U31: high | V31: benchmark: Heilbrunn keyword "Chair" and essays "French Furniture in the Eighteenth Century: Seat Furniture", "Shaker Furniture", "Charles Eames and Ray Eames". Canon names chairs only inside material rows. links: INS062; MAT116; MAT115; OBT021; OBT022
A32: GAP031 | B32: table and desk | D32: object-type | E32: Things | F32: THEME | G32: GL | J32: ancient; forms vary by region | K32: A raised surface for eating, writing, work or display. | L32: joinery;turning;veneer | M32: dining tables;desks;low tables | N32: food and storage;record and writing | O32: museum typology | P32: floor-level eating and working cultures | Q32: none | R32: Met Open Access (CC0);Cleveland Museum of Art Open Access (CC0);Art Institute of Chicago (CC0);Wikimedia Commons | S32: R3 | T32: F1.22a | U32: medium | V32: benchmark: Heilbrunn keywords "Table", "Desk"
A33: GAP032 | B33: bed | C33: bedstead | D33: object-type | E33: Things | F33: THEME | G33: GL | J33: raised beds attested in Egypt from the early third millennium BCE; mats, platforms and hammocks elsewhere | K33: A raised or framed place to sleep, often among the most valuable household furnishings and part of a marriage settlement. | L33: joinery;carving;textile hangings | M33: beds;bed hangings | N33: shelter;care and access | O33: museum typology | Q33: none | R33: Met Open Access (CC0);Cleveland Museum of Art Open Access (CC0);Art Institute of Chicago (CC0);Wikimedia Commons | S33: R3 | T33: F1.22a | U33: medium | V33: benchmark: Heilbrunn keyword "Bed"; essay "Nuptial Furnishings in the Italian Renaissance". links: OBT018; OBT020
A34: GAP033 | B34: case furniture (chest and cabinet) | C34: cassone; commode; cabinet on stand | D34: object-type | E34: Things | F34: THEME | G34: GL | J34: ancient; forms vary | K34: Boxes, chests and cabinets for storing and displaying valuables, from marriage chests to collectors' cabinets. | L34: joinery;veneer;marquetry;lacquer | M34: chests;cabinets;commodes | N34: food and storage;rule and display | O34: museum typology | Q34: none | R34: Met Open Access (CC0);Cleveland Museum of Art Open Access (CC0);Art Institute of Chicago (CC0);Wikimedia Commons | S34: R3 | T34: F1.22a;F1.24 | U34: high | V34: benchmark: Heilbrunn essay "French Furniture in the Eighteenth Century: Case Furniture"; keywords "Cabinet", "Chest", "Commode". links: TEC139; OBT086
A35: GAP034 | B35: folding screen | C35: byōbu; biombo; Coromandel screen | D35: object-type | E35: Things | F35: F1.8;F1.7;F1.13 | G35: AS-JPN;AS-CHN;AS-KOR;AM-LAT | H35: 700 | J35: Japanese byōbu from the Nara period; earlier in China; biombos in New Spain from c. 1600 | K35: Hinged painted, lacquered or inlaid panels divided rooms and carried images, and travelled from Japan to New Spain as biombos. | L35: paper and wood hinges;painting;lacquer;inlay | M35: byōbu;biombos;Coromandel screens | N35: shelter;rule and display | O35: museums | Q35: none | R35: Met Open Access (CC0);Cleveland Museum of Art Open Access (CC0);Art Institute of Chicago (CC0);Wikimedia Commons | S35: R2 | T35: F1.13;F1.14 | U35: high | V35: benchmark: AP-250 no. 94; Heilbrunn essay "Interiors Imagined: Folding Screens, Garments, and Clothing Stands". OBT136 "screen" is the digital display, not this. links: NET036; OBT136
A36: GAP035 | B36: hand fan | C36: folding fan; uchiwa; ōgi | D36: object-type | E36: Things | F36: THEME | G36: GL | J36: rigid fans are ancient in Egypt and China; the folding fan is usually traced to Japan, c. 9th–10th century | K36: Rigid or folding fans cooled the body, signalled rank and carried painting and print across Asia and Europe. | L36: paper;silk;bamboo;ivory;feathers | M36: fans | N36: clothing and adornment;rule and display | O36: museums | Q36: none | R36: Met Open Access (CC0);Cleveland Museum of Art Open Access (CC0);Art Institute of Chicago (CC0);Wikimedia Commons | S36: R3 | T36: F1.13 | U36: medium | V36: benchmark: Heilbrunn keyword "Fan". Folding-fan origin to verify
A37: GAP036 | B37: netsuke | D37: object-type | E37: Things | F37: F1.8 | G37: AS-JPN | H37: 1600 | I37: 1900 | J37: approx.; mainly Edo period | K37: Small carved toggles held pouches and inrō on the kimono sash, and became collectors' objects in Europe after the 1860s. | L37: ivory carving;wood carving;lacquer | M37: toggles | N37: clothing and adornment | O37: Japanese usage; collectors | P37: the many unsigned carvers | Q37: none | R37: Met Open Access (CC0);Cleveland Museum of Art Open Access (CC0);Art Institute of Chicago (CC0);Wikimedia Commons | S37: R2 | T37: F1.22a;F1.24 | U37: high | V37: benchmark: Heilbrunn essay "Netsuke: From Fashion Fobs to Coveted Collectibles". links: OBT034; MAT074
A38: GAP037 | B38: chahar bagh | C38: charbagh; four-part garden | D38: object-type | E38: Things | F38: F1.10;F1.9 | G38: WA-IRN;AS-SAS;AS-CEN | H38: -550 | J38: Pasargadae (Achaemenid) is often cited as the earliest; the form is best documented in Timurid, Safavid and Mughal gardens | K38: A walled garden divided into four by water channels, used for palaces and tombs from Iran to Mughal India. | L38: water channels;irrigation;planting | M38: gardens;garden tombs | N38: rule and display;ritual and belief | O38: Persian usage; historians | P38: the gardeners and water engineers | Q38: none | R38: Wikimedia Commons;Archnet (terms per item) | S38: R2 | T38: F1.10;F1.16 | U38: medium | V38: benchmark: AP-250 no. 209 (Taj Mahal gardens); Heilbrunn keyword "Garden". Start date is the contested part. links: POL197; TEC220
A39: GAP038 | B39: dry landscape garden | C39: karesansui | D39: object-type | E39: Things | F39: F1.8 | G39: AS-JPN | H39: 1400 | J39: approx.; flourished in Muromachi-period Zen temples | K39: Gardeners set stones and raked gravel to evoke landscape, mostly in Zen temple precincts. | L39: stone setting;raked gravel;moss | M39: temple gardens | N39: ritual and belief | O39: Japanese garden treatises; historians | P39: the kawaramono garden workers, a stigmatised group who did much of the work | Q39: none | R39: Wikimedia Commons | S39: R3 | T39: F1.16;F1.23 | U39: high | V39: benchmark: AP-250 no. 207 (Ryoan-ji). links: BEL024; POL182
A40: GAP039 | B40: Chinese scholar's garden | C40: literati garden | D40: object-type | E40: Things | F40: F1.8 | G40: AS-CHN | H40: 1368 | J40: tradition older; surviving Suzhou gardens mainly Ming and Qing | K40: Owners and designers composed rocks, water, pavilions and planting into small walled landscapes for retreat and display. | L40: rockwork;timber pavilions;water | M40: gardens;scholar's rocks | N40: rule and display | O40: Chinese garden writing (Ji Cheng, Yuanye, c. 1631); historians | P40: the rock-setters and craftsmen | Q40: none | R40: Met Open Access (CC0, scholar's rocks);Wikimedia Commons | S40: R3 | T40: F1.8 | U40: high | V40: benchmark: Heilbrunn essay "Chinese Gardens and Collectors' Rocks". links: STY136
A41: GAP040 | B41: English landscape garden | C41: jardin anglais | D41: style | E41: Ideas | F41: F1.11 | G41: EU-BLC | H41: 1720 | I41: 1800 | J41: approx. | K41: Landowners and designers reshaped estates into apparently natural parkland with lakes, clumps of trees and sunken walls (ha-has). | L41: earthmoving;planting;water engineering | M41: parks;follies;ha-has | N41: rule and display | O41: historians | P41: estate labourers and enclosed commons; slavery-derived wealth behind some estates | Q41: human-flow | R41: Wikimedia Commons;Europeana (per-item licence) | S41: R3 | T41: F1.17;F1.22 | U41: high | V41: benchmark: Heilbrunn essays "Gardens of Western Europe, 1600–1800", "From Geometric to Informal Gardens in the Eighteenth Century"
A42: GAP041 | B42: French formal garden | C42: jardin à la française | D42: style | E42: Ideas | F42: F1.11 | G42: EU-WCE | H42: 1600 | I42: 1715 | J42: approx. | K42: Garden designers laid out parterres, axes and basins by geometry and hydraulics, as at Versailles. | L42: surveying;hydraulics;clipped planting | M42: parterres;fountains;canals | N42: rule and display | O42: historians | P42: the labourers and soldiers who dug the waterworks | Q42: none | R42: Wikimedia Commons;Europeana (per-item licence) | S42: R3 | T42: F1.17 | U42: high | V42: benchmark: AP-250 no. 93; Heilbrunn essay "From Italy to France: Gardens in the Court of Louis XIV and After". links: DYN085
A43: GAP042 | B43: stupa | C43: chorten; dagoba; chedi | D43: object-type | E43: Things | F43: F1.9;F1.8 | G43: AS-SAS;AS-HIM;AS-MSE;AS-ISE;AS-CHN | H43: -300 | J43: approx.; earliest monumental stupas associated with the Maurya period | K43: A mound-shaped monument enclosing relics, built and enlarged across Buddhist Asia and developed into the chorten and pagoda. | L43: brick;stone masonry;plaster;relic deposits | M43: stupas;chortens;pagodas | N43: ritual and belief | O43: Buddhist traditions; archaeologists | Q43: sacred | R43: Met Open Access (CC0, reliquaries);Wikimedia Commons | S43: R2 | T43: F1.16 | U43: high | V43: benchmark: AP-250 nos. 192, 198. OBT180 names the stupa only as a reliquary context. links: BEL021; BEL022; POL186
A44: GAP043 | B44: ziggurat | D44: object-type | E44: Things | F44: F1.9a | G44: WA-MES;WA-IRN | H44: -2100 | I44: -500 | J44: Ur-Nammu's ziggurat at Ur c. 2100 BCE; raised temple platforms earlier (Ubaid, Uruk) | K44: Stepped mud-brick temple platforms built in Mesopotamian and Elamite cities. | L44: mud brick;fired brick;bitumen | M44: temple platforms | N44: ritual and belief | O44: Akkadian term; archaeologists | P44: the labourers | Q44: none | R44: Wikimedia Commons;Met Open Access (CC0) | S44: R3 | T44: F1.5;F1.9a | U44: high | V44: benchmark: AP-250 no. 12; Heilbrunn essay "Ur: The Ziggurat". links: TEC154; MAT108; ARC054
A45: GAP044 | B45: basilica | D45: object-type | E45: Things | F45: F1.11 | G45: EU-GRR;WA-LEV;AF-MAG | H45: -200 | J45: Roman civic basilicas from the 2nd century BCE; Christian use from the 4th century CE | K45: A long hall with aisles and an apse, a Roman civic type adopted for Christian churches. | L45: brick;stone;timber roofs;mosaic | M45: halls;churches | N45: rule and display;ritual and belief | O45: architectural historians | Q45: none | R45: Wikimedia Commons;Europeana (per-item licence) | S45: R3 | T45: F1.11 | U45: high | V45: benchmark: AP-250 no. 49 (Santa Sabina)
A46: GAP045 | B46: steel-frame skyscraper | C46: high-rise | D46: object-type | E46: Things | F46: F1.7;THEME | G46: AM-EWD;GL | H46: 1885 | J46: Chicago's Home Insurance Building (1884–85) is often cited; "first" is argued | K46: Tall buildings carried on steel skeletons with elevators, developed in Chicago and New York. | L46: steel frame;elevators;curtain walls | M46: office towers | N46: shelter;exchange and value | O46: architectural historians | P46: the steelworkers, many of them immigrant or Indigenous (Mohawk ironworkers in New York) | Q46: none | R46: Wikimedia Commons;Library of Congress (public domain where marked) | S46: R3 | T46: F1.19 | U46: high | V46: benchmark: AP-250 nos. 124, 146. links: MAT119; GAP013
A47: GAP046 | B47: orrery | D47: object-type | E47: Things | F47: F1.11 | G47: EU-BLC | H47: 1704 | J47: Tompion and Graham, c. 1704–13; named after the Earl of Orrery | K47: A geared model of the solar system used to teach astronomy, made by instrument makers' workshops. | L47: brass;clockwork gearing | M47: orreries;planetaria | N47: record and writing | O47: instrument makers | Q47: none | R47: Science Museum Group collection (link out);Wikimedia Commons | S47: R3 | T47: F1.19 | U47: high | V47: benchmark: AP-250 no. 100; Heilbrunn keyword "Scientific Instrument". links: INV019; OBT156
A48: GAP047 | B48: watch | C48: pocket watch; wristwatch | D48: object-type | E48: Things | F48: F1.11;THEME | G48: EU-WCE;GL | H48: 1500 | J48: approx.; spring-driven portable timepieces from the early 16th century | K48: Spring-driven portable timepieces, made first in southern Germany and later in Geneva, London and the Swiss Jura. | L48: springs;gears;enamel;engraving | M48: watches | N48: tools;clothing and adornment | O48: museums; makers | Q48: none | R48: Met Open Access (CC0);Cleveland Museum of Art Open Access (CC0);Art Institute of Chicago (CC0);Wikimedia Commons | S48: R2 | T48: F1.19;F1.29 | U48: high | V48: benchmark: Heilbrunn essay "Seventeenth-Century European Watches" and keyword "Timepiece". links: PRA166; OBT146; DIA010
A49: GAP048 | B49: keyboard instruments (harpsichord and piano) | C49: virginal; fortepiano | D49: object-type | E49: Things | F49: F1.11 | G49: EU-WCE | H49: 1400 | J49: harpsichord from the 15th century; Cristofori's piano c. 1700 | K49: Stringed keyboard instruments built by specialist workshops, from harpsichords to Cristofori's piano and factory-made uprights. | L49: wood;wire strings;ivory and ebony keys;iron frames | M49: harpsichords;virginals;pianos | N49: play and music | O49: museums; makers | P49: the ivory trade behind the keys | Q49: none | R49: Met Open Access (CC0) | S49: R2 | T49: F1.4;F1.19 | U49: high | V49: benchmark: Heilbrunn essays "The Piano: The Pianofortes of Bartolomeo Cristofori", "Flemish Harpsichords and Virginals", "Renaissance Keyboards". links: MAT074; NET014
A50: GAP049 | B50: violin | C50: violin family | D50: object-type | E50: Things | F50: F1.11 | G50: EU-WCE | H50: 1530 | J50: approx.; earliest violins in northern Italy c. 1530s | K50: Bowed instruments whose form was settled in the workshops of Cremona and Brescia. | L50: spruce;maple;varnish;gut strings | M50: violins;violas;cellos | N50: play and music | O50: makers; museums | Q50: none | R50: Met Open Access (CC0) | S50: R2 | T50: F1.4;F1.29 | U50: high | V50: benchmark: Heilbrunn essays "Renaissance Violins", "Violin Makers: Nicolò Amati and Antonio Stradivari". links: PRA171
A51: GAP050 | B51: guitar | C51: vihuela | D51: object-type | E51: Things | F51: F1.11;THEME | G51: EU-IBE;GL | H51: 1500 | J51: approx.; vihuela and early guitars in 16th-century Spain | K51: Plucked string instruments developed in Spain and later made in factories and electric forms worldwide. | L51: wood;gut and steel strings;electric pickups | M51: guitars | N51: play and music | O51: museums | Q51: none | R51: Met Open Access (CC0) | S51: R3 | T51: F1.4;F1.21 | U51: medium | V51: benchmark: Heilbrunn essays "The Guitar", "The Spanish Guitar", "Archtop Guitars and Mandolins"
A52: GAP051 | B52: telephone | D52: object-type | E52: Things | F52: THEME | G52: GL | H52: 1876 | J52: Bell's US patent 1876; priority is disputed | K52: A device for voice at a distance whose handsets and cases became a major industrial-design commission. | L52: metal;Bakelite;electrical components | M52: telephones;handsets | N52: tools | O52: historians of technology | P52: the switchboard operators, mostly women | Q52: none | R52: Smithsonian Open Access (CC0 where marked);Wikimedia Commons | S52: R3 | T52: F1.21;F1.19 | U52: high | V52: benchmark: Global Design History ch. 7, Golec, "Telephones, globalization, and the production of locality in the 1920s". links: MAT113
A53: GAP052 | B53: typeface | C53: font | D53: object-type | E53: Things | F53: THEME | G53: GL | H53: 1450 | J53: approx.; cast metal type from the mid-15th century; digital fonts from the 1980s | K53: A designed set of letterforms for reproduction, cut in metal, drawn for hot-metal and photo systems, then coded as fonts. | L53: punchcutting;matrices;digital outlines | M53: type;fonts;specimen books | N53: record and writing | O53: typographers and foundries | P53: non-Latin scripts adapted to Latin-script technologies | Q53: none | R53: Wikimedia Commons;Internet Archive (public-domain specimen books) | S53: R2 | T53: F1.5;F1.21 | U53: high | V53: benchmark: JDH virtual issue "Typographic Histories: Three Decades of Research"; Shehab and Nawar (2020). links: TEC192; STY114; INS073
A54: GAP053 | B54: kiswa | C54: kiswah | D54: object-type | E54: Things | F54: F1.10 | G54: WA-ARB;AF-EGY | J54: the covering tradition predates Islam; made in Egypt for centuries, later in a dedicated workshop in Mecca (dates to verify) | K54: The black silk covering of the Kaaba, woven and embroidered with calligraphy in gold and silver-wrapped thread and renewed each year. | L54: silk;gold and silver-wrapped thread;embroidery;calligraphy | M54: kiswa;belt band;door curtain | N54: ritual and belief | O54: its makers and Islamic authorities | Q54: sacred | R54: collection search link-out;Wikimedia Commons (per-item licence) | S54: R3 | T54: F1.16 | U54: high | V54: benchmark: AP-250 no. 183. links: MKR055; TEC112; TEC208
A55: GAP054 | B55: Kongo crucifix | C55: nkangi kiditu | D55: object-type | E55: Things | F55: F1.6 | G55: AF-CEN | H55: 1500 | I55: 1900 | J55: approx.; after the Kongo court adopted Christianity (1491) | K55: Cast brass crucifixes made in the Kingdom of Kongo, with Kongo features and meanings. | L55: lost-wax casting;brass;wood | M55: crucifixes | N55: ritual and belief;rule and display | O55: Kongo users; historians | Q55: sacred | R55: Met Open Access (CC0);Wikimedia Commons | S55: R2 | T55: F1.16;F1.14 | U55: high | V55: benchmark: Heilbrunn essay "African Christianity in Kongo"; Met essay "Christianity and Kongo Visual Culture" (2025). CIV013 and POL020 mention crucifixes but no node exists. links: CIV013; POL020; BEL045
A56: GAP055 | B56: ndop | C56: Kuba royal portrait figure | D56: object-type | E56: Things | F56: F1.6 | G56: AF-CEN | H56: 1700 | I56: 1900 | J56: approx.; dating of individual figures is debated | K56: Carved figures of Kuba kings, each identified by an emblem (ibol), kept as royal memorials. | L56: wood carving;camwood | M56: figures | N56: rule and display;ritual and belief | O56: the Kuba court; museums | Q56: ancestral | R56: collection search link-out;Wikimedia Commons (per-item licence) | S56: R3 | T56: F1.6;F1.24 | U56: medium | V56: benchmark: AP-250 no. 171. links: POL022
A57: GAP056 | B57: ikenga | D57: object-type | E57: Things | F57: F1.6 | G57: AF-GUI | J57: surviving examples mostly 19th–20th century | K57: Horned shrine figures owned by Igbo men as the seat of personal achievement. | L57: wood carving | M57: shrine figures | N57: ritual and belief | O57: Igbo owners | Q57: sacred | R57: collection search link-out;Wikimedia Commons (per-item licence) | S57: R3 | T57: F1.16 | U57: high | V57: benchmark: AP-250 no. 176. The canon has only archaeological Igbo-Ukwu (ARC034)
A58: GAP057 | B58: byeri reliquary guardian | C58: nsekh-o-byeri | D58: object-type | E58: Things | F58: F1.6 | G58: AF-CEN | J58: surviving examples mostly 19th century | K58: Carved figures set on bark boxes holding the bones of lineage ancestors among the Fang, heavily collected by European artists and dealers in the early 20th century. | L58: wood carving;bark containers | M58: reliquary figures | N58: ritual and belief | O58: Fang lineages | Q58: ancestral;funerary;sacred | R58: collection search link-out | S58: R3 | T58: F1.16;F1.20;F1.24 | U58: high | V58: benchmark: AP-250 no. 179. links: OBT180; STY062
A59: GAP058 | B59: sowei (Sande society helmet mask) | C59: bundu mask; ndoli jowei | D59: object-type | E59: Things | F59: F1.6 | G59: AF-GUI | J59: surviving examples mostly 19th–20th century | K59: Helmet masks carved by men and owned and danced by women of the Sande society of the Mende and neighbouring peoples, among the few African masks worn by women. | L59: wood carving;black dye | M59: helmet masks | N59: ritual and belief | O59: the Sande society | Q59: sacred;living-community | R59: collection search link-out;Wikimedia Commons (per-item licence) | S59: R3 | T59: F1.18;F1.16 | U59: high | V59: benchmark: AP-250 no. 175. links: OBT181
A60: GAP059 | B60: bandolier bag | C60: gashkibidaagan (Ojibwe) | D60: object-type | E60: Things | F60: F1.7 | G60: AM-EWD | H60: 1800 | J60: approx. | K60: Large beaded shoulder bags made mainly by Anishinaabe, Lenape and other Great Lakes and Woodlands women, with European glass beads and trade cloth. | L60: glass beads;wool cloth;leather | M60: shoulder bags | N60: clothing and adornment;rule and display | O60: makers and museums | Q60: Indigenous-community | R60: Smithsonian Open Access (CC0 where marked);Met Open Access (CC0);Wikimedia Commons | S60: R3 | T60: F1.18;F1.13 | U60: high | V60: benchmark: AP-250 no. 163. links: TEC111; NET015
A61: GAP060 | B61: transformation mask | D61: object-type | E61: Things | F61: F1.7 | G61: AM-NWC | J61: surviving examples mostly 19th century | K61: Hinged masks that open during a dance to reveal a second face, carved by Kwakwaka'wakw and other Northwest Coast artists. | L61: carved and painted cedar;string hinges | M61: masks | N61: ritual and belief | O61: makers; museums | P61: the potlatch ban (1885–1951), under which many masks were confiscated | Q61: sacred;Indigenous-community;conflict-looting | R61: community-published site;collection search link-out only | S61: R3 | T61: F1.16;F1.24 | U61: high | V61: benchmark: AP-250 no. 164. links: OBT181; MAT096
A62: GAP061 | B62: staff god (Rarotonga) | C62: atua rakau | D62: object-type | E62: Things | F62: F1.12 | G62: OC-POL | H62: 1780 | I62: 1830 | J62: approx.; most surviving examples were collected by missionaries in the 1820s–30s | K62: Carved wooden staff figures wrapped in barkcloth, many given up to or taken by London Missionary Society missionaries at conversion. | L62: wood carving;barkcloth;feathers;sennit | M62: staff figures | N62: ritual and belief | O62: makers; missionaries | Q62: sacred;Indigenous-community | R62: community-published site;collection search link-out only | S62: R3 | T62: F1.16;F1.24 | U62: medium | V62: benchmark: AP-250 no. 216. A case for the missions theme
A63: GAP062 | B63: Nukuoro deity figure | C63: tino aitu | D63: object-type | E63: Things | F63: F1.12 | G63: OC-MIC;OC-POL | J63: surviving examples 18th–19th century | K63: Smoothly carved wooden figures from Nukuoro, a Polynesian-speaking atoll in Micronesia. | L63: wood carving | M63: figures | N63: ritual and belief | O63: museums | Q63: sacred;Indigenous-community | R63: community-published site;collection search link-out only | S63: R3 | T63: F1.16 | U63: medium | V63: benchmark: AP-250 no. 217
A64: GAP063 | B64: Torres Strait turtle-shell mask | D64: object-type | E64: Things | F64: F1.12 | G64: OC-AUS;OC-MEL | J64: surviving examples mostly 19th century | K64: Masks built from heated and shaped plates of turtle shell, a technique distinctive to Torres Strait Islanders. | L64: turtle shell;wood;fibre;feathers;shell | M64: masks | N64: ritual and belief | O64: Torres Strait Islander communities; museums | Q64: sacred;Indigenous-community | R64: community-published site;collection search link-out only | S64: R3 | T64: F1.12 | U64: high | V64: benchmark: AP-250 no. 218. links: MAT079; MOV106
A65: GAP064 | B65: Froebel gifts | C65: Fröbelgaben | D65: object-type | E65: Things | F65: F1.11;THEME | G65: EU-WCE;GL | H65: 1837 | J65: Froebel's first kindergarten 1837–40 | K65: Sets of wooden blocks, tiles and folding papers designed for Froebel's kindergartens, argued by some to have shaped modern designers' training. | L65: turned and cut wood;paper | M65: building blocks;tiles;folding papers | N65: play and music | O65: Friedrich Froebel and the kindergarten movement | P65: the women kindergarten teachers who spread the method | Q65: none | R65: Wikimedia Commons;Internet Archive (public-domain manuals) | S65: R3 | T65: F1.20;F1.22a | U65: medium | V65: benchmark: MoMA "Century of the Child: Growing by Design, 1900–2000" (2012), Froebel among the listed makers; source: Brosterman, Inventing Kindergarten (1997), whose modernism thesis is contested. links: OBT246
A66: GAP065 | B66: children's picture book | D66: object-type | E66: Things | F66: THEME | G66: GL | H66: 1658 | J66: Comenius, Orbis Pictus (1658), is often cited as the first | K66: Illustrated books made for children to learn from and enjoy, a large field of commissioned illustration and printing. | L66: woodcut;lithography;offset printing | M66: picture books | N66: play and music;record and writing | O66: publishers; historians | Q66: none | R66: Internet Archive (public-domain editions);Wikimedia Commons | S66: R3 | T66: F1.22a;F1.21 | U66: medium | V66: benchmark: MoMA "Century of the Child" (books among its categories). links: OBT133
A67: GAP066 | B67: souvenir | C67: tourist art; airport art | D67: object-type | E67: Things | F67: THEME | G67: GL | J67: pilgrim tokens are ancient; the souvenir trade expands with the Grand Tour and mass tourism (19th–20th century) | K67: Objects made or sold for visitors to take home, from pilgrim badges and Grand Tour models to airport art, often adapting a local form to a buyer's idea of it. | L67: casting;carving;printing | M67: badges;models;carvings;postcards | N67: exchange and value | O67: Graburn (1976) named "tourist art" as a category | P67: the makers' names, rarely recorded | Q67: none | R67: Met Open Access (CC0);Cleveland Museum of Art Open Access (CC0);Art Institute of Chicago (CC0);Wikimedia Commons | S67: R2 | T67: F1.17;F1.22a;F1.2 | U67: high | V67: benchmark: Heilbrunn essay "The Grand Tour"; source: Graburn (ed.), Ethnic and Tourist Arts (1976). links: STY177; STY178; SCH012; OBT119; OBT259
A68: GAP067 | B68: Grand Tour | D68: network | E68: Connections | F68: F1.11;F1.13 | G68: EU-WCE;EU-GRR;EU-BLC | H68: 1660 | I68: 1840 | J68: approx. | K68: Wealthy northern European travellers toured Italy and bought paintings, antiquities, casts, prints and souvenirs, sustaining workshops in Rome, Naples and Florence. | L68: copying;cast-making;micromosaic;view painting | M68: view paintings;micromosaics;casts;restored antiquities | N68: exchange and value | O68: historians; the travellers' own term | P68: the Italian workshop makers; later tours to Greece, Egypt and the Levant | Q68: none | R68: Met Open Access (CC0);Cleveland Museum of Art Open Access (CC0);Art Institute of Chicago (CC0);Wikimedia Commons;Europeana (per-item licence) | S68: R2 | T68: F1.14;F1.24 | U68: high | V68: benchmark: Heilbrunn essay "The Grand Tour"; AP-250 no. 34 (Roman copy) for the copying strand. links: GAP066
A69: GAP068 | B69: Non-Aligned cultural exchange | D69: network | E69: Connections | F69: F1.13;THEME | G69: GL | H69: 1955 | I69: 1990 | J69: Bandung Conference 1955; Non-Aligned Movement founded in Belgrade 1961 | K69: Exhibitions, art colonies, scholarships and news pools linked artists of Yugoslavia and newly independent states in Africa and Asia outside the two Cold War blocs. | L69: exhibitions;art colonies;scholarships | M69: prints;paintings;exhibition catalogues | N69: rule and display | O69: historians (Videkanić 2020) | Q69: none | R69: collection search link-out only (works in copyright);Wikimedia Commons (per-item licence) | S69: R3 | T69: F1.20;F1.13 | U69: medium | V69: benchmark: Videkanić, Nonaligned Modernism (2020), via ARTMargins review. links: POL239; POL240; EVT022
A70: GAP069 | B70: Old Edgefield stoneware potters | C70: Edgefield District potters | D70: maker-community | E70: People | F70: F1.7 | G70: AM-EWD | H70: 1810 | I70: 1865 | J70: approx.; enslaved labour until emancipation in 1865 | K70: Enslaved African American potters in Edgefield District, South Carolina, made alkaline-glazed stoneware storage jars; one of them, David Drake, inscribed some with verses and dates. | L70: alkaline glaze;wheel throwing | M70: storage jars;face vessels | N70: food and storage | O70: museums (Met and MFA Boston, 2022) and descendant communities | P70: most of the potters' names | Q70: human-flow;living-community | R70: Met Open Access (CC0 where marked);collection search link-out | S70: R2 | T70: F1.23;F1.7 | U70: high | V70: benchmark: Met exhibition "Hear Me Now: The Black Potters of Old Edgefield" (2022–23); Heilbrunn essay "The Transatlantic Slave Trade". links: NET035; TEC022
A71: GAP070 | B71: Japanese American incarceration-camp makers | C71: gaman | D71: maker-community | E71: People | F71: F1.7;F1.19a | G71: AM-WST | H71: 1942 | I71: 1946 | J71: camps 1942–46 | K71: Japanese Americans forcibly removed to camps made furniture, tools, toys, instruments and ornaments from scrap and found materials. | L71: scrap wood;shells;found materials;carving | M71: furniture;toys;games;teapots;pins | N71: shelter;play and music;tools | O71: Smithsonian American Art Museum, "The Art of Gaman" (2010), and families | Q71: human-flow;living-community | R71: Smithsonian American Art Museum (link out);Densho (terms to verify) | S71: R3 | T71: F1.19a;F1.23 | U71: high | V71: benchmark: SAAM "The Art of Gaman" (2010–11); JDH special issue "Material Displacements" (2021) for the theme
A72: GAP071 | B72: Plantation | C72: plantation system | D72: institution | E72: People | F72: F1.7;F1.13;F1.9 | G72: AM-CAR;AM-EWD;AM-LAT;AS-ISE | H72: 1500 | J72: approx.; Atlantic sugar plantations from the 15th–16th centuries; plantation economies continue | K72: Estates growing sugar, cotton, indigo, tobacco and later rubber and tea for export on enslaved, indentured or coerced labour, with workshops of enslaved smiths, carpenters and potters. | L72: cane mills;boiling houses;cotton gins;workshops | M72: sugar;cotton;indigo;Colono ware | N72: food and storage;exchange and value | O72: historians | P72: the enslaved makers as named people | Q72: human-flow | R72: SlaveVoyages (historical data public domain; estimates CC BY-NC);Library of Congress (public domain where marked);Wikimedia Commons | S72: R2 | T72: F1.23;F1.13;F1.22 | U72: high | V72: benchmark: Heilbrunn essay "The Transatlantic Slave Trade"; Met "Hear Me Now" (2022). Canon mentions plantations in network rows but has no node. links: NET035; NET057; NET056; ARC201; DIA009
A73: GAP072 | B73: Haute couture system | C73: Chambre Syndicale de la Haute Couture | D73: institution | E73: People | F73: F1.11;THEME | G73: EU-WCE | H73: 1868 | J73: a predecessor trade body from 1868; the name Chambre Syndicale de la Haute Couture from 1911 (to verify) | K73: Paris dressmaking houses organised seasonal collections, models and licensed copies, setting a calendar of fashion change. | L73: cutting and sewing;embroidery by specialist ateliers | M73: gowns;toiles;patterns | N73: clothing and adornment | O73: the Paris trade body | P73: seamstresses, embroiderers and suppliers named only through the houses | Q73: none | R73: Met Open Access (CC0);Europeana (per-item licence) | S73: R2 | T73: F1.18;F1.21;F1.14 | U73: medium | V73: benchmark: Heilbrunn essays "Haute Couture", "Charles Frederick Worth and the House of Worth"; Global Design History ch. 5 "The globalization of the fashion city"; JDH special issue "Interrogating Intellectual Property Rights in Fashion and Design" (2017)
A74: GAP073 | B74: Department store | D74: institution | E74: People | F74: THEME | G74: EU-WCE;GL | H74: 1852 | J74: the expansion of Le Bon Marché, Paris, from 1852 is often cited | K74: Large shops with fixed prices, display windows and departments that staged goods for consumers and commissioned designers. | L74: display;advertising;catalogues | M74: shop interiors;window displays;catalogues | N74: exchange and value | O74: historians | P74: the shop workers and seamstresses behind the counters | Q74: none | R74: Wikimedia Commons;Internet Archive (catalogues) | S74: R3 | T74: F1.21 | U74: medium | V74: benchmark: JDH special issue "Design, Commercial Expansion and Business History" (1999)
A75: GAP074 | B75: Royal Academy of Arts | D75: institution | E75: People | F75: F1.11 | G75: EU-BLC | H75: 1768 | J75: founded 1768 | K75: A London academy that trained painters, sculptors and architects and ran annual exhibitions, while leaving most crafts out and admitting few women to full membership until the 20th century. | L75: drawing from casts and life | M75: exhibitions | N75: rule and display | O75: its royal charter | P75: craftspeople; women | Q75: none | R75: Wikimedia Commons;collection search link-out | S75: R3 | T75: F1.3;F1.17 | U75: high | V75: benchmark: Heilbrunn essay "The Salon and the Royal Academy in the Nineteenth Century"; JDH special issue "Dangerous Liaisons: Relationships between Design, Craft and Art" (2004) for the theme
A76: GAP075 | B76: Académie royale de peinture et de sculpture | D76: institution | E76: People | F76: F1.11 | G76: EU-WCE | H76: 1648 | I76: 1793 | J76: founded 1648; suppressed 1793 | K76: The French royal academy ranked the genres and ran the Salon, separating academic art from guild craft. | L76: drawing from casts and life | M76: exhibitions;lectures | N76: rule and display | O76: the French crown | P76: guild painters of the Académie de Saint-Luc | Q76: none | R76: Wikimedia Commons;collection search link-out | S76: R3 | T76: F1.3;F1.17 | U76: high | V76: benchmark: Heilbrunn essays "The Salon and the Royal Academy", "The French Academy in Rome". links: INS050; MKR064
A77: GAP076 | B77: Kunstgewerbeschule (school of applied arts) | C77: Kunstgewerbeschulen | D77: institution | E77: People | F77: F1.11 | G77: EU-WCE;EU-EER | H77: 1867 | J77: Vienna's school opened 1867–68 beside the Austrian Museum of Art and Industry | K77: Schools attached to applied-arts museums in German-speaking Europe trained designers for industry; Weimar's school was one of the two merged into the Bauhaus in 1919. | L77: drawing;workshop training | M77: patterns;prototypes | N77: tools | O77: the states that founded them | Q77: none | R77: Wikimedia Commons;Europeana (per-item licence) | S77: R3 | T77: F1.19;F1.20 | U77: medium | V77: benchmark: Heilbrunn essay "Design Reform"; Margolin ch. 11 "The Age of Exhibitions: Europe Outside Great Britain". links: INS057; MKR077; INS052
A78: GAP077 | B78: Industrial design consultancy | C78: industrial design office | D78: institution | E78: People | F78: F1.7;THEME | G78: AM-EWD;GL | H78: 1926 | J78: approx.; independent offices in the United States from the late 1920s | K78: Independent offices sold styling and product planning to manufacturers, making the industrial designer a named professional. | L78: clay models;renderings | M78: appliances;vehicles;packaging | N78: tools | O78: historians; the designers | P78: the in-house draughtsmen and modellers | Q78: none | R78: Smithsonian Open Access (CC0 where marked);collection search link-out | S78: R3 | T78: F1.17;F1.21 | U78: medium | V78: benchmark: Margolin vol. 2 ch. 28 "The United States, 1917–1941"; JDH special issue "Ghosts of the Profession" (2008). links: INS064; INS066
A79: GAP078 | B79: ICSID (World Design Organization) | C79: International Council of Societies of Industrial Design | D79: institution | E79: People | F79: THEME | G79: GL | H79: 1957 | J79: founded 1957; renamed World Design Organization 2017 | K79: An international federation of industrial-design societies that promoted design as a profession and published its definitions. | O79: its member societies | Q79: none | R79: none identified; link out to official site | S79: R3 | T79: F1.17;F1.20 | U79: high | V79: benchmark: JDH special issue "Ghosts of the Profession" (2008) and virtual issue "Histories of Design Pedagogy" for the profession theme
A80: GAP079 | B80: VNIITE | C80: All-Union Research Institute of Technical Aesthetics | D80: institution | E80: People | F80: F1.11 | G80: EU-EER | H80: 1962 | I80: 1992 | J80: founded 1962; end date after the Soviet collapse to verify | K80: The Soviet state design research institute, which developed "technical aesthetics" for consumer and industrial goods. | L80: design research;prototyping | M80: prototypes;standards;journals | N80: tools | O80: the Soviet state | Q80: none | R80: Wikimedia Commons;collection search link-out | S80: R3 | T80: F1.20;F1.17 | U80: medium | V80: benchmark: JDH special issue "Design, Stalin and the Thaw" (1997); Margolin ch. 20 and 27 cover the Soviet Union to 1940 only. links: POL151; STY158
A81: GAP080 | B81: Amt für industrielle Formgestaltung | C81: Office for Industrial Design (GDR) | D81: institution | E81: People | F81: F1.11 | G81: EU-WCE | H81: 1972 | I81: 1990 | J81: 1972 to reunification | K81: East Germany's state design office, which set design policy for state industry. | M81: consumer goods;prototypes | N81: tools | O81: the GDR state | Q81: none | R81: collection search link-out | S81: R3 | T81: F1.20;F1.17 | U81: medium | V81: benchmark: JDH special issue "Design, Stalin and the Thaw" (1997) for the socialist-design theme. Details to verify
A82: GAP081 | B82: Good Design Award (G Mark) | C82: G Mark | D82: institution | E82: People | F82: F1.8 | G82: AS-JPN | H82: 1957 | J82: set up 1957 by the Ministry of International Trade and Industry | K82: A Japanese state design-selection system, set up partly in response to foreign complaints that Japanese firms copied Western designs. | M82: consumer goods | N82: exchange and value | O82: the Japanese state | Q82: none | R82: collection search link-out | S82: R3 | T82: F1.14;F1.17 | U82: high | V82: benchmark: JDH special issue "Transnational Modern Design Histories in East Asia" (2014); Designing Worlds ch. 5 (Kondo). links: MOV024; INS061
A83: GAP082 | B83: Escola Superior de Desenho Industrial (ESDI) | C83: ESDI | D83: institution | E83: People | F83: F1.7 | G83: AM-LAT | H83: 1962 | J83: founded 1962, teaching from 1963, Rio de Janeiro | K83: Often described as the first university-level industrial design school in Latin America, drawing on the Ulm model. | L83: design teaching | N83: tools | O83: the state of Guanabara | Q83: none | R83: collection search link-out | S83: R3 | T83: F1.20;F1.17 | U83: high | V83: benchmark: JDH special issue "Locating Design Exchanges in Latin America and the Caribbean" (2019); Fernández and Bonsiepe (eds), Historia del diseño en América Latina y el Caribe (2008). links: INS060
A84: GAP083 | B84: Faculty of Applied Arts, Cairo | C84: Applied Arts School, Cairo | D84: institution | E84: People | F84: F1.10;F1.6 | G84: AF-EGY | J84: origins and dates to verify | K84: A Cairo school that trained designers, printers and craftspeople, named in histories of Arab graphic design as a training ground. | L84: design teaching | N84: record and writing | O84: the Egyptian state | Q84: none | R84: collection search link-out | S84: R3 | T84: F1.17 | U84: low | V84: benchmark: Shehab and Nawar, A History of Arab Graphic Design (2020), per Brooklyn Rail review, which also names the College of Fine Arts, Baghdad
A85: GAP084 | B85: Salon (Paris) | C85: Salon de Paris | D85: event | E85: Time | F85: F1.11 | G85: EU-WCE | H85: 1667 | J85: first held 1667; regular from 1737; rival salons from 1863 (Salon des Refusés) | K85: The Paris academy's official exhibition, whose juries decided what counted as art until independent salons broke away. | L85: exhibition juries | M85: paintings;sculpture | N85: rule and display | O85: the Académie royale; later the state | Q85: none | R85: Wikimedia Commons;Gallica (commercial reuse paid) | S85: R3 | T85: F1.15;F1.3 | U85: high | V85: benchmark: Heilbrunn essay "The Salon and the Royal Academy in the Nineteenth Century". links: GAP075
A86: GAP085 | B86: Ljubljana Biennial of Graphic Arts | D86: event | E86: Time | F86: F1.11 | G86: EU-BYZ | H86: 1955 | J86: founded 1955 | K86: An international print exhibition in Yugoslavia that showed printmakers from both Cold War blocs and from Non-Aligned states. | L86: printmaking | M86: prints | N86: rule and display | O86: its organisers | Q86: none | R86: collection search link-out only (works in copyright);Wikimedia Commons (per-item licence) | S86: R3 | T86: F1.15;F1.20 | U86: medium | V86: benchmark: Videkanić, Nonaligned Modernism (2020), via ARTMargins review
A87: BEL001 | B87: Ancient Egyptian religion | C87: Egyptian temple and funerary religion | D87: belief-tradition | E87: People | F87: F1.6 | G87: AF-EGY;AF-NUB | H87: -3100 | I87: 550 | J87: c.; last temple (Philae) closed c. 537 CE | K87: Egyptian religion drove the production of temples, divine statues, amulets, coffins and Books of the Dead by temple and funerary workshops. | L87: stone carving; faience; cartonnage; papyrus illustration; mummification | M87: amulets; coffins; Books of the Dead; votive bronzes | N87: ritual and belief;rule and display;record and writing | O87: Egyptologists; Greek writers | P87: household and popular piety; Nubian forms of the same gods; human remains treated as objects | Q87: sacred;funerary | R87: Met Open Access (CC0);Cleveland Museum of Art Open Access (CC0);Brooklyn Museum (CC BY where marked);Wikimedia Commons | S87: R1 | T87: F1.16;F1.24 | U87: high | V87: Human remains and funerary material hidden by default.
A88: BEL002 | B88: Mesopotamian religion | C88: Sumerian, Akkadian, Babylonian and Assyrian religion | D88: belief-tradition | E88: People | F88: F1.9a | G88: WA-MES;WA-IRN;WA-LEV | H88: -3500 | I88: 100 | J88: c.; temple cults to the Parthian period | K88: Mesopotamian temples commissioned cult statues, votive figures, foundation deposits and incantation bowls and ran large workshops. | L88: stone and copper-alloy votive figures; clay tablets; foundation pegs | M88: votive statues; foundation pegs; incantation texts | N88: ritual and belief;rule and display;record and writing | O88: Assyriologists | P88: household cults; the temple-dependent labourers; neighbouring religions | Q88: sacred | R88: Met Open Access (CC0);Cuneiform Digital Library Initiative;Wikimedia Commons | S88: R2 | T88: F1.16 | U88: high
A89: BEL003 | B89: Greco-Roman religion | C89: Greek and Roman polytheism | D89: belief-tradition | E89: People | F89: F1.11 | G89: EU-GRR;AF-EGY;WA-LEV;WA-ANA | H89: -800 | I89: 400 | J89: c.; imperial bans in 390s | K89: Greek and Roman cults paid for temples, cult statues, votive offerings and sacrificial equipment, sustaining sculptors, bronze-casters and potters. | L89: marble and bronze sculpture; terracotta votives; temple building | M89: cult statues; votives; altars; temples | N89: ritual and belief;rule and display | O89: classicists; ancient authors | P89: mystery cults and local deities; enslaved temple workers; Christian destruction and reuse | Q89: sacred | R89: Met Open Access (CC0);Getty Museum Open Content (public-domain images);Cleveland Museum of Art Open Access (CC0);Wikimedia Commons | S89: R2 | T89: F1.16 | U89: high
A90: BEL004 | B90: Norse religion | C90: Old Norse religion; heathen Scandinavia | D90: belief-tradition | E90: People | F90: F1.11 | G90: EU-SCA;EU-BLC | H90: 200 | I90: 1100 | J90: c.; conversion 10th–11th c. | K90: Norse religion shaped picture stones, amulets such as Thor's hammers, ship burials and carved ornament. | L90: stone carving; silver casting; woodcarving | M90: picture stones; hammer amulets; ship burials | N90: ritual and belief;rule and display | O90: historians; Snorri Sturluson (13th c. Christian writer) | P90: Sámi religion alongside; enslaved people in burials; modern nationalist misuse | Q90: funerary;sacred | R90: Wikimedia Commons;SMK Denmark (public domain);Nationalmuseum Sweden (public domain) | S90: R3 | T90: F1.16 | U90: medium | V90: Watch for far-right appropriation of symbols.
A91: BEL005 | B91: Zoroastrianism | C91: Mazdayasna; Parsi and Irani faith | D91: belief-tradition | E91: People | F91: F1.9a;F1.9 | G91: WA-IRN;AS-CEN;AS-SAS | H91: -1000 | J91: c.; origins debated; continues | K91: Zoroastrian practice built fire temples and towers of silence and, among Parsis in India, patronised embroidered gara saris and silver ritual vessels. | L91: fire-temple building; silverwork; silk embroidery | M91: fire altars; ritual vessels; gara saris | N91: ritual and belief;clothing and adornment | O91: the community; Iranologists | P91: Irani Zoroastrians under persecution; converts' descendants; funerary practice | Q91: sacred;funerary;living-community | R91: Met Open Access (CC0);Wikimedia Commons;community-published site | S91: R2 | T91: F1.16 | U91: medium | V91: Date of Zarathustra debated (c. 1500–500 BCE).
A92: BEL006 | B92: Manichaeism | C92: Religion of Light | D92: belief-tradition | E92: People | F92: F1.9a;F1.12a;F1.8 | G92: WA-MES;WA-IRN;AS-CEN;AS-CHN | H92: 240 | I92: 1600 | J92: c.; Mani's preaching from 240; last traces in south China c. 16th c. | K92: Manichaeans used richly illuminated books and painting as teaching, including silk paintings from Turfan and south China. | L92: manuscript illumination; silk painting | M92: illuminated fragments; hanging scrolls | N92: ritual and belief;record and writing | O92: historians; Turfan finds | P92: a persecuted faith known mostly from its enemies' texts | Q92: sacred | R92: Wikimedia Commons;International Dunhuang Programme (link out; check terms) | S92: R2 | T92: F1.16 | U92: medium
A93: BEL007 | B93: Judaism | C93: Jewish religious tradition | D93: belief-tradition | E93: People | F93: F1.9a;F1.11;F1.6;F1.10;THEME | G93: GL | H93: -1000 | J93: c.; continues | K93: Jewish practice commissions Torah scrolls, ritual silver (Torah ornaments, Hanukkah lamps), synagogue buildings and illuminated Haggadot, often from Jewish and non-Jewish makers alike. | L93: scribal writing on parchment; silversmithing; embroidery; illumination | M93: Torah scrolls; rimonim; Haggadot; ketubbot | N93: ritual and belief;record and writing | O93: the community; historians | P93: makers barred from guilds in many places; Beta Israel, Yemeni and other non-European traditions; objects looted 1933–45 | Q93: sacred;living-community;conflict-looting | R93: Met Open Access (CC0);British Library digitised collections (public-domain items);NYPL Digital Collections (public-domain items);Wikimedia Commons | S93: R1 | T93: F1.16;F1.24 | U93: high
A94: BEL008 | B94: Coptic Orthodox Christianity | C94: Coptic Church | D94: belief-tradition | E94: People | F94: F1.6 | G94: AF-EGY;AF-NUB | H94: 300 | J94: c.; continues | K94: Coptic monasteries and churches commissioned icons, textiles, carved wood and manuscripts, including the well-known Coptic tapestry-woven tunic fragments. | L94: tapestry weaving in wool and linen; icon painting; woodcarving | M94: textiles; icons; manuscripts | N94: ritual and belief;clothing and adornment;record and writing | O94: the Church; historians | P94: the dead whose burial textiles fill museums; Muslim makers of church fittings | Q94: sacred;funerary;living-community | R94: Met Open Access (CC0);Cleveland Museum of Art Open Access (CC0);Brooklyn Museum (CC BY where marked);Wikimedia Commons | S94: R2 | T94: F1.16;F1.18 | U94: high | V94: Many "Coptic textiles" come from graves.
A95: BEL009 | B95: Ethiopian Orthodox Tewahedo Christianity | C95: Tewahedo Church | D95: belief-tradition | E95: People | F95: F1.6 | G95: AF-HRN | H95: 330 | J95: c.; Aksumite conversion; continues | K95: The Ethiopian church sustains parchment manuscripts, painted icons and diptychs, processional crosses and rock-hewn churches. | L95: parchment making; tempera painting; metal casting; rock-cutting | M95: manuscripts; icons; crosses; tabots | N95: ritual and belief;record and writing;rule and display | O95: the Church; historians | P95: Muslim and Beta Israel neighbours; tabots that must not be seen by laypeople | Q95: sacred;living-community;conflict-looting | R95: Walters Art Museum (CC0);Met Open Access (CC0);British Library digitised collections (public-domain items);Wikimedia Commons | S95: R1 | T95: F1.16;F1.24 | U95: high | V95: Tabots are never displayed; some taken at Maqdala (1868) have been returned by churches (e.g. Edinburgh 2002); verify others.
A96: BEL010 | B96: Eastern Orthodox Christianity (Byzantine rite) | C96: Orthodox Church | D96: belief-tradition | E96: People | F96: F1.11;F1.9a | G96: EU-BYZ;EU-EER;WA-ANA;WA-LEV;WA-CAU | H96: 330 | J96: c.; continues | K96: Orthodox practice centres on icons, iconostases, mosaics, frescoes and embroidered liturgical textiles, and its Iconoclast controversy (726–843) fought over images. | L96: icon painting in tempera; mosaic; fresco; gold embroidery | M96: icons; iconostases; epitaphioi | N96: ritual and belief;rule and display | O96: the Church; historians | P96: Iconoclasts' losses; non-Orthodox subjects; icons taken as war booty | Q96: sacred;living-community | R96: Met Open Access (CC0);Walters Art Museum (CC0);Wikimedia Commons | S96: R1 | T96: F1.16;F1.14 | U96: high
A97: BEL011 | B97: Latin (Roman) Catholic Christianity | C97: Catholic Church; Western Church | D97: belief-tradition | E97: People | F97: F1.11;F1.7;THEME | G97: GL | H97: 300 | J97: c.; continues | K97: Catholic patronage commissioned cathedrals, altarpieces, reliquaries, vestments and devotional prints and, through missions, colonial church art worldwide. | L97: stained glass; panel painting; goldsmithing; embroidery; printing | M97: altarpieces; reliquaries; vestments; santos | N97: ritual and belief;rule and display;record and writing | O97: the Church; historians | P97: Indigenous and African makers of mission art; Reformation destruction; objects taken from colonised peoples by missionaries | Q97: sacred;living-community | R97: Met Open Access (CC0);Rijksmuseum (CC0);National Gallery of Art Washington (CC0);Wikimedia Commons | S97: R2 | T97: F1.16;F1.17 | U97: high
A98: BEL012 | B98: Protestant Christianities | C98: Lutheran, Reformed, Anglican and others | D98: belief-tradition | E98: People | F98: F1.11;F1.7;F1.6;F1.12;THEME | G98: GL | H98: 1517 | J98: continues | K98: Protestant reform destroyed many images (iconoclasm) while promoting printed Bibles, hymnals and plain meeting houses, and missions spread print and dress codes. | L98: printing; engraving; plain carpentry | M98: Bibles; catechisms; meeting houses | N98: ritual and belief;record and writing | O98: historians | P98: Catholic makers whose work was destroyed; missionised peoples told to abandon their images | Q98: sacred | R98: Rijksmuseum (CC0);Library of Congress (public-domain items);Wikimedia Commons | S98: R2 | T98: F1.16;F1.28 | U98: high
A99: BEL013 | B99: Shakers | C99: United Society of Believers in Christ's Second Appearing | D99: belief-tradition | E99: People | F99: F1.7 | G99: AM-EWD | H99: 1774 | J99: continues (very small community) | K99: The Shakers made plain furniture, oval boxes and tools whose simplicity later influenced modern designers. | L99: joinery; bentwood boxes; broom making | M99: chairs; oval boxes; tools | N99: ritual and belief;shelter;tools | O99: the Shakers themselves; design historians | P99: the women who led the society; its celibate community's survival | Q99: living-community | R99: Met Open Access (CC0);Smithsonian Open Access (CC0 items);Library of Congress (public-domain items) | S99: R2 | T99: F1.20;F1.29 | U99: high
A100: BEL014 | B100: Armenian Apostolic Christianity | C100: Armenian Church | D100: belief-tradition | E100: People | F100: F1.9a | G100: WA-CAU;WA-ANA;WA-IRN | H100: 301 | J100: c.; conversion c. 301; continues | K100: The Armenian church produced carved khachkar cross-stones, stone churches and illuminated gospels, many destroyed in and after 1915. | L100: stone carving; manuscript illumination | M100: khachkars; gospels; churches | N100: ritual and belief;record and writing | O100: the Church; historians | P100: makers killed or displaced in the genocide; khachkars destroyed at Julfa (1998–2006) | Q100: sacred;conflict-looting;living-community | R100: Walters Art Museum (CC0);Wikimedia Commons | S100: R2 | T100: F1.16;F1.19a;F1.24 | U100: high
...

Sheet Sources
A1: id | B1: name | C1: type | D1: covers_worlds | E1: covers_sub_regions | F1: access | G1: cost | H1: licence_content | I1: licence_metadata | J1: commercial_safe | K1: what_it_fills | L1: known_limits | M1: verified | N1: verification_url | O1: notes
A2: SRC001 | B2: Cleveland Museum of Art Open Access | C2: museum-api | D2: F1.6;F1.7;F1.8;F1.9;F1.9a;F1.10;F1.11;F1.12;F1.12a;F1.13 | E2: GL | F2: Web collection + Open Access API (no key) + GitHub data dump | G2: free | H2: CC0 for public-domain works (in-copyright works excluded) | I2: CC0 | J2: yes | K2: High-res images and data across world collections (Egypt, Andes, Islamic textiles, East and South Asia, Africa) | L2: In-copyright and some loan objects not CC0 | M2: yes 2026-09-28 | N2: https://www.clevelandart.org/open-access | O2: Page states 'No key or token is required'; 61,000+ CC0 records via API. Also on Sketchfab CC0 programme.
A3: SRC002 | B3: The Met Open Access | C3: museum-open-access | D3: F1.6;F1.7;F1.8;F1.9;F1.9a;F1.10;F1.11;F1.12;F1.12a;F1.13 | E3: GL | F3: Web collection (OA filter) + CSV on GitHub; public Collection API | G3: free | H3: CC0 for Open Access (public-domain) images | I3: CC0 | J3: yes | K3: 400,000+ PD images; strongest single source for many worlds | L3: Only works the Met believes PD; restricted images link out | M3: yes 2026-09-28 | N3: https://www.metmuseum.org/policies/image-resources | O3: Page says 406,000+ OA images; collection data CC0 'including commercial'. Collection API existence not checked on this page.
A4: SRC003 | B4: Art Institute of Chicago API | C4: museum-api | D4: F1.6;F1.7;F1.8;F1.9;F1.9a;F1.10;F1.11;F1.12;F1.12a;F1.13 | E4: GL | F4: REST API (no authentication) + IIIF images | G4: free-limited (60 requests/min anonymous; higher on request) | H4: Use only artworks tagged public domain (CC0 designation) | I4: CC0 except 'description' field = CC BY 4.0 | J4: yes | K4: PD images and structured data incl. textiles, Asian and Indigenous American collections | L4: Attribute CC BY descriptions; copyrighted images excluded | M4: yes 2026-09-28 | N4: https://api.artic.edu/docs/ | O4: Add AIC-User-Agent header as courtesy.
A5: SRC004 | B5: Smithsonian Open Access | C5: museum-open-access | D5: F1.6;F1.7;F1.8;F1.9;F1.9a;F1.10;F1.11;F1.12;F1.12a;F1.13 | E5: GL | F5: Web portal + bulk data + 3D | G5: free | H5: CC0 where designated | I5: CC0 | J5: yes | K5: Millions of CC0 assets across 20+ Smithsonian units (NMAfA, Freer/Sackler, NMNH Anthropology, Cooper Hewitt, NMAH) | L5: Only items marked CC0; third-party/privacy rights may still apply | M5: yes 2026-09-28 | N5: https://www.si.edu/openaccess/faq | O5: FAQ: CC0 'for commercial purposes without any attribution, permission, or fee'. Check NMAI/NMNH items for CARE sensitivity before display.
A6: SRC005 | B6: Smithsonian Open Access API (via api.data.gov) | C6: museum-api | D6: F1.6;F1.7;F1.8;F1.9;F1.9a;F1.10;F1.11;F1.12;F1.12a;F1.13 | E6: GL | F6: REST API; key issued through api.data.gov | G6: free-with-key | H6: CC0 where designated | I6: CC0 | J6: yes | K6: Programmatic search and harvest of Smithsonian CC0 records | L6: Rate limit not stated in FAQ; api.data.gov default limits not checked | M6: partial 2026-09-28 | N6: https://www.si.edu/openaccess/faq | O6: Docs at edan.si.edu/openaccess/apidocs (not fetched).
A7: SRC006 | B7: Smithsonian 3D Digitization (3d.si.edu) | C7: 3d | D7: F1.6;F1.7;F1.8;F1.9;F1.9a;F1.10;F1.11;F1.12;F1.12a;F1.13 | E7: GL | F7: Voyager viewer; downloads glTF/glb/obj for CC0 models | G7: free | H7: CC0 only where the model is marked CC0; others view-only | I7: CC0 (Open Access records) | J7: per-item | K7: Downloadable 3D models of objects and sites for the web app | L7: Many models not CC0: embed/view only | M7: yes 2026-09-28 | N7: https://3d.si.edu/collections/openaccesshighlights | O7: Page: 'If you see CC0 by a 3D model, it is yours to take and remix'. Formats per si.edu OA FAQ.
A8: SRC007 | B8: Cooper Hewitt collection data and API | C8: museum-api | D8: F1.11;F1.8;F1.7;THEME | E8: GL | F8: GitHub dataset + API | G8: free | H8: Images NOT covered by dataset licence (many images CC0 via Smithsonian Open Access) | I8: CC0 | J8: per-item | K8: Design/decorative-arts metadata; 19th-21st c. design, textiles, wallcoverings | L8: Check each image in Smithsonian OA for CC0 | M8: yes 2026-09-28 | N8: https://github.com/cooperhewitt/collection | O8: README: 'images are not included... not covered by the same license'.
A9: SRC008 | B9: National Gallery of Art (US) Open Access | C9: museum-open-access | D9: F1.11;F1.7;THEME | E9: GL | F9: Web + GitHub CSV (daily) | G9: free | H9: CC0 for open-access images | I9: CC0 | J9: yes | K9: European/American painting, prints, drawings; object data | L9: Gallery can convey only its own rights | M9: yes 2026-09-28 | N9: https://www.nga.gov/artworks/free-images-and-open-access | O9: 'free of charge for any use, whether commercial or non-commercial'.
A10: SRC009 | B10: Walters Art Museum | C10: museum-open-access | D10: F1.6;F1.8;F1.9;F1.10;F1.11 | E10: GL | F10: Online collection + API | G10: free | H10: CC0 for works believed PD | I10: unverified | J10: yes | K10: Manuscripts (Ethiopian, Islamic, Armenian, European), ancient and Asian art | L10: Loans/copyright works excluded; credit requested | M10: yes 2026-09-28 | N10: https://thewalters.org/about/policies/rights-reproductions/ | O10: Credit 'The Walters Art Museum' requested.
A11: SRC010 | B11: OPenn (Penn Libraries; hosts Walters legacy and partner manuscripts) | C11: manuscript-library | D11: F1.10;F1.11;F1.9;F1.6 | E11: GL | F11: Direct file download (TIFF/JPEG + TEI) | G11: free | H11: 'All materials on OPenn are in the public domain or released under Creative Commons licenses as Free Cultural Works' | I11: per-item (see each repository page) | J11: per-item | K11: Complete manuscript image sets (Islamic, Ethiopic, Indic, European) | L11: Check each repository's CC variant (BY vs BY-SA) | M11: partial 2026-09-28 | N11: https://openn.library.upenn.edu/ | O11: Free Cultural Works = commercial allowed, but SA may apply.
A12: SRC011 | B12: Yale Center for British Art Open Access | C12: museum-open-access | D12: F1.11;F1.19 | E12: GL | F12: Web collection downloads | G12: free | H12: Public-domain images free 'without further application, authorization, or fees' (Yale Open Access Policy) | I12: unverified (see YCBA Open Data terms page) | J12: yes | K12: British art, prints, rare books on industry, empire and trade | L12: In-copyright works need permission | M12: yes 2026-09-28 | N12: https://britishart.yale.edu/using-images | O12: Commercial use not explicitly mentioned; PD status implies it.
A13: SRC012 | B13: Yale University Art Gallery / Yale LUX | C13: museum-open-access | D13: F1.6;F1.7;F1.8;F1.9;F1.9a;F1.10;F1.11;F1.12;F1.12a;F1.13 | E13: GL | F13: LUX cross-collection search | G13: free | H13: unverified | I13: unverified | J13: per-item | K13: Yale art, natural history and library holdings in one search | L13: Not checked | M13: unverified
A14: SRC013 | B14: Getty Museum Open Content Program | C14: museum-open-access | D14: F1.11;F1.9a;F1.10 | E14: GL | F14: Collection website downloads | G14: free | H14: CC0 | I14: unverified | J14: yes | K14: Antiquities, manuscripts, photographs, European decorative arts | L14: Must not imply Getty endorsement | M14: yes 2026-09-28 | N14: https://www.getty.edu/projects/open-content-program/faqs/ | O14: Suggested credit 'Digital image courtesy of Getty's Open Content Program'.
A15: SRC014 | B15: LACMA Collections Online (Public Domain High Resolution) | C15: museum-open-access | D15: F1.6;F1.7;F1.8;F1.9;F1.9a;F1.10;F1.11;F1.12;F1.12a;F1.13 | E15: GL | F15: Web downloads | G15: free | H15: PD images 'free of charge and for use without restriction' | I15: unverified | J15: yes | K15: Islamic, Latin American, Korean, Japanese, costume and textiles | L15: User must clear third-party/privacy rights | M15: yes 2026-09-28 | N15: https://www.lacma.org/about/contact-us/terms-use
A16: SRC015 | B16: Princeton University Art Museum | C16: museum-open-access | D16: F1.6;F1.7;F1.8;F1.9;F1.9a;F1.10;F1.11;F1.12;F1.12a;F1.13 | E16: GL | F16: Web + IIIF | G16: free | H16: PD images: 'No approval required' | I16: unverified | J16: yes | K16: Mesoamerican, Chinese, ancient Mediterranean | L16: Credit line required | M16: yes 2026-09-28 | N16: https://artmuseum.princeton.edu/art/image-use-and-access
A17: SRC016 | B17: Brooklyn Museum Open Collection | C17: museum-open-access | D17: F1.6;F1.7;F1.8;F1.9;F1.9a;F1.10;F1.11;F1.12;F1.12a;F1.13 | E17: GL | F17: Web + API (key) | G17: unverified | H17: unverified | I17: unverified | J17: per-item | K17: Egypt, Africa, Americas, decorative arts | L17: Not checked | M17: unverified
A18: SRC017 | B18: Minneapolis Institute of Art (Mia) | C18: museum-open-access | D18: F1.6;F1.7;F1.8;F1.9;F1.9a;F1.10;F1.11;F1.12;F1.12a;F1.13 | E18: GL | F18: Web + GitHub data | G18: free | H18: PD works marked CC PDM; commercial use without permission | I18: unverified | J18: yes | K18: Chinese, African, Native American, textiles | L18: Only PDM-marked works | M18: yes 2026-09-28 | N18: https://new.artsmia.org/copyright-and-image-access
A19: SRC018 | B19: Harvard Art Museums (web + API) | C19: museum-api | D19: F1.6;F1.7;F1.8;F1.9;F1.9a;F1.10;F1.11;F1.12;F1.12a;F1.13 | E19: GL | F19: API requires key on request | G19: free-with-key (cost not stated on page) | H19: Downloads for personal, non-commercial use only | I19: unverified | J19: no | K19: Object data for teaching; link-out images | L19: Images non-commercial; link out only | M19: partial 2026-09-28 | N19: https://harvardartmuseums.org/licensing | O19: API page: every request needs apikey.
A20: SRC019 | B20: Library of Congress loc.gov JSON API | C20: museum-api | D20: F1.6;F1.7;F1.8;F1.9;F1.9a;F1.10;F1.11;F1.12;F1.12a;F1.13 | E20: GL | F20: JSON API over all loc.gov collections | G20: free | H20: per-item rights advisories | I20: U.S. Government Work (guide text) | J20: per-item | K20: Programmatic access to LoC collections incl. maps, prints, newspapers | L20: Per-item rights; bulk OCR throttled | M20: partial 2026-09-28 | N20: https://guides.loc.gov/chronicling-america/additional-features | O20: 'no API key or authentication required'.
A21: SRC020 | B21: Library of Congress Prints & Photographs Online Catalog | C21: image-commons | D21: F1.6;F1.7;F1.8;F1.9;F1.9a;F1.10;F1.11;F1.12;F1.12a;F1.13 | E21: GL | F21: Web catalogue | G21: free | H21: per-item ('No known restrictions' on many) | I21: unverified | J21: per-item | K21: Photographs of workshops, industry, architecture, world fairs | L21: Check each rights advisory | M21: unverified
A22: SRC021 | B22: Chronicling America (LoC) | C22: text-library | D22: F1.7;F1.19;F1.21 | E22: AM-EWD;AM-WST;AM-LAT | F22: Web portal/collection (see verification_url or site) | G22: free-limited (no key; bulk OCR 10 requests per 10 min per IP) | H22: not stated on guide page | I22: U.S. Government Work (guide) | J22: per-item | K22: US newspapers for advertising, industry, exhibitions | L22: Rights of papers not stated on checked page | M22: partial 2026-09-28 | N22: https://guides.loc.gov/chronicling-america/additional-features
A23: SRC022 | B23: National Jukebox (LoC) | C23: audio | D23: F1.4;THEME | E23: AM-EWD;GL | F23: Streaming under rightsholder permission | G23: free | H23: Pre-1923 recordings PD since 1 Jan 2022 (Music Modernization Act); 1923-1956 recordings still protected; labels >95 yrs PD | I23: unverified | J23: per-item | K23: Early sound recordings for F1.4 (sound, performance) | L23: Most post-1922 tracks: embed/link only | M23: yes 2026-09-28 | N23: https://www.loc.gov/collections/national-jukebox/about-this-collection/rights-and-access/ | O23: 'You will need written permission from the rightsholders' for copyrighted items.
A24: SRC023 | B24: World Digital Library (now at Library of Congress) | C24: manuscript-library | D24: F1.6;F1.7;F1.8;F1.9;F1.9a;F1.10;F1.11;F1.12;F1.12a;F1.13 | E24: GL | F24: loc.gov collection | G24: free | H24: 'Absent any such restrictions, these materials are free to use and reuse'; per-item partner restrictions | I24: unverified | J24: per-item | K24: Manuscripts, maps and books from partner libraries worldwide (e.g. Florentine Codex facsimile) | L24: Check partner source info per item | M24: yes 2026-09-28 | N24: https://www.loc.gov/collections/world-digital-library/about-this-collection/rights-and-access/ | O24: Credit '[source], World Digital Library'.
A25: SRC024 | B25: US National Archives Catalog | C25: image-commons | D25: F1.7;F1.19;F1.19a | E25: GL | F25: Web + API | G25: unverified | H25: Federal records generally PD (not re-verified) | I25: unverified | J25: per-item | K25: Patent drawings, WPA craft, industry photography | L25: Not checked | M25: unverified
A26: SRC025 | B26: NYPL Digital Collections (public domain) | C26: image-commons | D26: F1.6;F1.7;F1.8;F1.9;F1.9a;F1.10;F1.11;F1.12;F1.12a;F1.13 | E26: GL | F26: Web + API (api.repo.nypl.org) | G26: free | H26: PD items: 'No permission required. No restrictions on use.' | I26: unverified | J26: yes | K26: Prints, photographs, maps, menus, trade catalogues | L26: Only PD-flagged items | M26: yes 2026-09-28 | N26: https://www.nypl.org/research/resources/public-domain-collections | O26: 180,000+ PD items.
A27: SRC026 | B27: Internet Archive (texts) | C27: text-library | D27: F1.6;F1.7;F1.8;F1.9;F1.9a;F1.10;F1.11;F1.12;F1.12a;F1.13 | E27: GL | F27: Web + API; download | G27: free | H27: per-item (uploader-stated); many PD scans; some lending-only copies | I27: unverified | J27: per-item | K27: PD translations and treatises (Digital Library of India scans, university scans) | L27: Lending-only items are in copyright; verify each | M27: unverified | O27: Examples found: Hoover's Agricola, Hendrie's Theophilus, Acharya's Manasara (DLI scan).
A28: SRC027 | B28: Prelinger Archives (Internet Archive) | C28: film-video | D28: F1.19;F1.21;F1.4;THEME | E28: AM-EWD;GL | F28: Download from archive.org | G28: free | H28: Per-film CC licence where shown; derivatives may be sold 'without any limitations' | I28: Descriptions/metadata © Prelinger & Getty Images, no commercial reproduction | J28: per-item | K28: Industrial, advertising, educational films (making, factories, consumer society) | L28: Do not copy descriptions commercially | M28: yes 2026-09-28 | N28: https://help.archive.org/help/prelinger-archive/ | O28: Attribution appreciated not required.
A29: SRC028 | B29: HathiTrust full view | C29: text-library | D29: F1.6;F1.7;F1.8;F1.9;F1.9a;F1.10;F1.11;F1.12;F1.12a;F1.13 | E29: GL | F29: Web reader + downloads | G29: free | H29: Rights codes: pd = world; pdus = US IPs only (1899-1929 non-US works); CC variants incl. NC/ND | I29: unverified | J29: per-item | K29: 19th-early 20th c. scholarship, catalogues, journals | L29: pdus blocked outside US; NC/ND items link out | M29: yes 2026-09-28 | N29: https://www.hathitrust.org/the-collection/preservation/rights-database/
A30: SRC029 | B30: Project Gutenberg | C30: text-library | D30: F1.6;F1.7;F1.8;F1.9;F1.9a;F1.10;F1.11;F1.12;F1.12a;F1.13 | E30: GL | F30: Web download | G30: free | H30: US public domain texts; PG trademark terms apply to branded files (not re-verified) | I30: unverified | J30: yes | K30: Clean PD texts (e.g. Agricola De re metallica 1912 = ebook 38015) | L30: US-centric PD judgements | M30: unverified
A31: SRC030 | B31: Wikisource | C31: text-library | D31: F1.6;F1.7;F1.8;F1.9;F1.9a;F1.10;F1.11;F1.12;F1.12a;F1.13 | E31: GL | F31: Web | G31: free | H31: PD source texts; transcriptions CC BY-SA (not re-verified) | I31: unverified | J31: yes | K31: Transcribed PD translations (e.g. De re metallica 1912) | L31: Quality varies | M31: unverified
A32: SRC031 | B32: Wikimedia Commons | C32: image-commons | D32: F1.6;F1.7;F1.8;F1.9;F1.9a;F1.10;F1.11;F1.12;F1.12a;F1.13 | E32: GL | F32: Web + API | G32: free | H32: Only free licences (CC0, PD, CC BY, CC BY-SA...); NC and ND not accepted | I32: CC0 structured data (not re-verified) | J32: yes | K32: Largest pool of reusable images incl. museum batch uploads | L32: Per-file attribution/share-alike; some files mis-licensed | M32: yes 2026-09-28 | N32: https://commons.wikimedia.org/wiki/Commons:Licensing | O32: Commons forbids -NC and -ND licences.
